Workbook

Sheet Master Modelo
A1: PRODUTO | B1: NCM | C1: ALIQ. II | D1: ALIQ. IPI | E1: ALIQ PIS | F1: ALIQ. COFINS | G1: DESCRICAO | H1: PESO./UNIT | I1: PREÇO UNIT. | J1: Dumping/Kg | K1: Cubagem/Unit | N1: FOB SEM DESCONTO | O1: MINIMO | P1: MEDIO
L2: =I2/H2 -> #DIV/0! | N2: 7.48
L3: =I3/H3 -> #DIV/0! | N3: 7.48
L4: =I4/H4 -> #DIV/0! | N4: 1.8
L5: =I5/H5 -> #DIV/0! | N5: 1.8
L6: =I6/H6 -> #DIV/0! | N6: 4.24
L7: =I7/H7 -> #DIV/0! | N7: 4.24
L8: =I8/H8 -> #DIV/0! | N8: 4.07
L9: =I9/H9 -> #DIV/0! | N9: 4.24
L10: =I10/H10 -> #DIV/0! | N10: 0.98
L11: =I11/H11 -> #DIV/0! | N11: 3.6
L12: =I12/H12 -> #DIV/0! | N12: 3.6
L13: =I13/H13 -> #DIV/0! | N13: 2.33
... L19: =I19/H19 -> #DIV/0! | N19: 2.8

Sheet Produtos
A1: PRODUTO | B1: DESCRIÇÃO | C1: NCM | E1: VALOR UNITÁRIO | F1: PESO UNITÁRIO | G1: CUBAGEM UNITARIA | H1: PREÇO POR KG | I1: II | J1: PIS | K1: COFINS | L1: Dumping | M1: IPI | N1: ICMS ESTADO DESTINO | O1: MVA AJUSTADO | P1: PESO TOTAL | Q1: CUBAGEM TOTAL | R1: VALOR FOB | S1: FRETE INTERNACIONAL/PESO | T1: FRETE INTERNACIONAL/CUBAGEM | U1: CAPATAZIA/PESO | V1: CAPATAZIA/CUBAGEM | W1: VALOR ADUANEIRO: | X1: SISCOMEX | Y1: MARINHA MERCANTE | Z1: OUTRAS DESP. ADUANEIRAS | AA1: DESPESAS ADUANEIRAS: | AB1: II | AC1: PIS | AD1: COFINS | AE1: IPI | AF1: Dumping | AG1: ICMS | AH1: IMPOSTOS NACIONALIZAÇÃO: | AI1: DESPESAS OPERACIONAIS: | AJ1: VARIAÇÃO CAMBIAL | AK1: CUSTO TOTAL DA OPERAÇÃO: | AL1: CRÉDITO PIS | AM1: CRÉDITO COFINS | AN1: CRÉDITO IPI | AO1: CRÉDITO ICMS | AP1: CUSTO DE ESTOQUE | AQ1: CUSTO TRADING | AR1: DÉBITO PIS | AS1: DÉBITO COFINS | AT1: DÉBITO ICMS | AU1: VALOR SEM IPI | AV1: IPI DESTACADO | AW1: NOTA FISCAL DE SAÍDA: | AX1: DESC. COMERCIAL | AY1: VALOR A PAGAR | AZ1: LUCRO BRUTO OPERAÇÃO | BA1: IR | BB1: CSLL | BC1: LUCRO LIQUIDO | BD1: =IF('Entrada e Saida'!$H$11="TRADING","Valor Venda Unit. C/IPI","Custo C/IPI") -> Valor Venda Unit. C/IPI | BE1: Desconto | BF1: Valor Final C/Desc. | BG1: Credito Unit. IPI | BH1: Credito Unit PIS | BI1: Credito Unit. Cofins | BJ1: Credito Unit. ICMS | BK1: Valor Unit. Sem Impostos | BL1: =IF('Entrada e Saida'!$H$14="P.JURIDICA","VALOR ST", "VALOR DIFAL") -> VALOR ST | BM1: =IF('Entrada e Saida'!$H$14="P.JURIDICA","Valor Final C/Desc.+IPI+ST","Valor Final C/Desc.+IPI+DIFAL") -> Valor Final C/Desc.+IPI+ST
B2: =VLOOKUP(A2,'Master Modelo'!A:I,7,FALSE) -> #N/A | C2: =VLOOKUP(A2,'Master Modelo'!A:I,2,FALSE) -> #N/A | E2: =VLOOKUP(A2,'Master Modelo'!A:I,9,FALSE) -> #N/A | F2: =IFERROR(VLOOKUP(A2,'Master Modelo'!A:I,8,FALSE),0) -> 0 | G2: =IFERROR(VLOOKUP(A2,'Master Modelo'!A:K,11,FALSE),0) -> 0 | H2: =(D2*E2)/(D2*F2) -> #N/A | I2: =VLOOKUP(A2,'Master Modelo'!A:I,3,FALSE) -> #N/A | J2: =VLOOKUP(A2,'Master Modelo'!A:I,5,FALSE) -> #N/A | K2: =VLOOKUP(A2,'Master Modelo'!A:I,6,FALSE) -> #N/A | L2: =VLOOKUP(A2,'Master Modelo'!A:J,10,FALSE) -> #N/A | M2: =VLOOKUP(A2,'Master Modelo'!A:I,4,FALSE) -> #N/A | P2: =D2*F2 -> 0 | Q2: =D2*G2 -> 0 | R2: =D2*E2*'Entrada e Saida'!$K$8 -> #N/A | S2: ='Entrada e Saida'!$H$21*'Entrada e Saida'!$K$8*(P2/(SUM(P:P))) -> #DIV/0! | T2: ='Entrada e Saida'!$H$21*'Entrada e Saida'!$K$8*(Q2/(SUM(Q:Q))) -> #DIV/0! | U2: ='Entrada e Saida'!$H$22*(P2/(SUM(P:P))) -> #DIV/0! | V2: ='Entrada e Saida'!$H$22*(Q2/(SUM(Q:Q))) -> #DIV/0! | W2: =R2+S2+U2 -> #N/A | X2: ='Entrada e Saida'!$H$26*(IF('Entrada e Saida'!$H$15="PESO",(P2/(SUM(P:P))),(Q2/(SUM(Q:Q))))) -> #DIV/0! | Y2: ='Entrada e Saida'!$H$27*(IF('Entrada e Saida'!$H$15="PESO",(P2/(SUM(P:P))),(Q2/(SUM(Q:Q))))) -> #DIV/0! | Z2: ='Entrada e Saida'!$H$28*(IF('Entrada e Saida'!$H$15="PESO",(P2/(SUM(P:P))),(Q2/(SUM(Q:Q))))) -> #DIV/0! | AA2: =X2+Y2+Z2 -> #DIV/0! | AB2: =W2*I2 -> #N/A | AC2: =W2*J2 -> #N/A | AD2: =W2*K2 -> #N/A | AE2: =(W2+AB2)*M2 -> #N/A | AF2: =IFERROR(D2*F2*L2*'Entrada e Saida'!$K$8,0) -> 0 | AG2: =((W2+AA2+AB2+AC2+AD2+AE2+AF2)/(1-'Entrada e Saida'!$G$65))*'Entrada e Saida'!$I$66 -> #N/A | AH2: =SUM(AB2:AG2) -> #N/A | AI2: ='Entrada e Saida'!$K$51*(IF('Entrada e Saida'!$H$15="PESO",(P2/(SUM(P:P))),(Q2/(SUM(Q:Q))))) -> #DIV/0! | AJ2: =(('Entrada e Saida'!$K$10-'Entrada e Saida'!$K$8)*E2*D2) -> #N/A | AK2: =IF('Entrada e Saida'!$H$15="PESO",W2+AA2+AH2+AI2+AJ2,W2+AA2+AH2+AI2+AJ2-S2+T2-U2+V2) -> #N/A | AL2: =IF('Entrada e Saida'!$H$12="REAL",AC2,0) -> #N/A | AM2: =IF('Entrada e Saida'!$H$12="REAL",AD2,0) -> #N/A | AN2: =IF('Entrada e Saida'!$H$13= "NÃO",AE2,0) -> #N/A | AO2: =AG2 -> #N/A | AP2: =AK2-SUM(AL2:AO2) -> #N/A | AQ2: =IF('Entrada e Saida'!$H$11="TRADING",AU2*'Custo Resumido'!D2,0) -> #N/A | AR2: =IF('Entrada e Saida'!$H$11="TRADING",AU2*'Entrada e Saida'!$G$63,0) -> #N/A | AS2: =IF('Entrada e Saida'!$H$11="TRADING",AU2*'Entrada e Saida'!$G$64,0) -> #N/A | AT2: =IF('Entrada e Saida'!$H$11="TRADING",AU2*'Entrada e Saida'!$G$65,0) -> #N/A | AU2: =IF('Entrada e Saida'!$H$11="TRADING",AP2/(1-(SUM('Entrada e Saida'!$G$63:$G$65)+'Custo Resumido'!D2)),0) -> #N/A | AV2: =IF('Entrada e Saida'!$H$13="NÃO",AU2*M2,0) -> #N/A | AW2: =AU2+AV2 -> #N/A | AX2: ='Entrada e Saida'!$G$74*AU2 -> #N/A | AY2: =AW2-AX2 -> #N/A | AZ2: =AQ2+('Entrada e Saida'!$G$65-'Entrada e Saida'!$I$65)*AU2-AX2 -> #N/A | BA2: =IF('Entrada e Saida'!$H$12="REAL",AZ2*'Entrada e Saida'!$G$81,AU2*'Entrada e Saida'!$G$81) -> #N/A | BB2: =IF('Entrada e Saida'!$H$12="REAL",AZ2*'Entrada e Saida'!$G$82,AU2*'Entrada e Saida'!$G$82) -> #N/A | BC2: =AZ2-BA2-BB2 -> #N/A | BD2: =IF('Entrada e Saida'!$H$11="TRADING",AW2/D2,AK2/D2) -> #N/A | BE2: =AX2/D2 -> #N/A | BF2: =BD2-BE2 -> #N/A | BG2: =IF('Entrada e Saida'!$H$11="TRADING",AV2/D2,AN2/D2) -> #N/A | BH2: =IF('Entrada e Saida'!$H$11="TRADING",IF('Entrada e Saida'!$H$12="REAL",AR2/D2,0),AL2/D2) -> #N/A | BI2: =IF('Entrada e Saida'!$H$11="TRADING",IF('Entrada e Saida'!$H$12="REAL",AS2/D2,0),AM2/D2) -> #N/A | BJ2: =IF('Entrada e Saida'!$H$11="TRADING",AT2/D2,AO2/D2) -> #N/A | BK2: =BF2-SUM(BG2:BJ2) -> #N/A | BL2: =IF(O2>0,IFERROR(IF('Entrada e Saida'!$H$11="DIRETA",0,(IF('Entrada e Saida'!$H$14="P.JURIDICA",(BD2*(1+O2)*N2)-((BD2/(1+M2))*'Entrada e Saida'!$G$65),((Produtos!N2-'Entrada e Saida'!$G$65)*Produtos!BD2)))),0),0) -> 0 | BM2: =BF2+BL2 -> #N/A
B3: =VLOOKUP(A3,'Master Modelo'!A:I,7,FALSE) -> #N/A | C3: =VLOOKUP(A3,'Master Modelo'!A:I,2,FALSE) -> #N/A | E3: =IFERROR(VLOOKUP(A3,'Master Modelo'!A:I,9,FALSE),0) -> 0 | F3: =IFERROR(VLOOKUP(A3,'Master Modelo'!A:I,8,FALSE),0) -> 0 | G3: =IFERROR(VLOOKUP(A3,'Master Modelo'!A:K,11,FALSE),0) -> 0 | H3: =(D3*E3)/(D3*F3) -> #DIV/0! | I3: =IFERROR(VLOOKUP(A3,'Master Modelo'!A:I,3,FALSE),0) -> 0 | J3: =IFERROR(VLOOKUP(A3,'Master Modelo'!A:I,5,FALSE),0) -> 0 | K3: =IFERROR(VLOOKUP(A3,'Master Modelo'!A:I,6,FALSE),0) -> 0 | L3: =VLOOKUP(A3,'Master Modelo'!A:J,10,FALSE) -> #N/A | M3: =IFERROR(VLOOKUP(A3,'Master Modelo'!A:I,4,FALSE),0) -> 0 | P3: =D3*F3 -> 0 | Q3: =D3*G3 -> 0 | R3: =D3*E3*'Entrada e Saida'!$K$8 -> 0 | S3: ='Entrada e Saida'!$H$21*'Entrada e Saida'!$K$8*(P3/(SUM(P:P))) -> #DIV/0! | T3: ='Entrada e Saida'!$H$21*'Entrada e Saida'!$K$8*(Q3/(SUM(Q:Q))) -> #DIV/0! | U3: ='Entrada e Saida'!$H$22*(P3/(SUM(P:P))) -> #DIV/0! | V3: ='Entrada e Saida'!$H$22*(Q3/(SUM(Q:Q))) -> #DIV/0! | W3: =R3+S3+U3 -> #DIV/0! | X3: ='Entrada e Saida'!$H$26*(IF('Entrada e Saida'!$H$15="PESO",(P3/(SUM(P:P))),(Q3/(SUM(Q:Q))))) -> #DIV/0! | Y3: ='Entrada e Saida'!$H$27*(IF('Entrada e Saida'!$H$15="PESO",(P3/(SUM(P:P))),(Q3/(SUM(Q:Q))))) -> #DIV/0! | Z3: ='Entrada e Saida'!$H$28*(IF('Entrada e Saida'!$H$15="PESO",(P3/(SUM(P:P))),(Q3/(SUM(Q:Q))))) -> #DIV/0! | AA3: =X3+Y3+Z3 -> #DIV/0! | AB3: =W3*I3 -> #DIV/0! | AC3: =W3*J3 -> #DIV/0! | AD3: =W3*K3 -> #DIV/0! | AE3: =(W3+AB3)*M3 -> #DIV/0! | AF3: =IFERROR(D3*F3*L3*'Entrada e Saida'!$K$8,0) -> 0 | AG3: =((W3+AA3+AB3+AC3+AD3+AE3+AF3)/(1-'Entrada e Saida'!$G$65))*'Entrada e Saida'!$I$66 -> #DIV/0! | AH3: =SUM(AB3:AG3) -> #DIV/0! | AI3: ='Entrada e Saida'!$K$51*(IF('Entrada e Saida'!$H$15="PESO",(P3/(SUM(P:P))),(Q3/(SUM(Q:Q))))) -> #DIV/0! | AJ3: =(('Entrada e Saida'!$K$10-'Entrada e Saida'!$K$8)*E3*D3) -> 0 | AK3: =IF('Entrada e Saida'!$H$15="PESO",W3+AA3+AH3+AI3+AJ3,W3+AA3+AH3+AI3+AJ3-S3+T3-U3+V3) -> #DIV/0! | AL3: =IF('Entrada e Saida'!$H$12="REAL",AC3,0) -> #DIV/0! | AM3: =IF('Entrada e Saida'!$H$12="REAL",AD3,0) -> #DIV/0! | AN3: =IF('Entrada e Saida'!$H$13= "NÃO",AE3,0) -> #DIV/0! | AO3: =AG3 -> #DIV/0! | AP3: =AK3-SUM(AL3:AO3) -> #DIV/0! | AQ3: =IF('Entrada e Saida'!$H$11="TRADING",AU3*'Custo Resumido'!D3,0) -> #DIV/0! | AR3: =IF('Entrada e Saida'!$H$11="TRADING",AU3*'Entrada e Saida'!$G$63,0) -> #DIV/0! | AS3: =IF('Entrada e Saida'!$H$11="TRADING",AU3*'Entrada e Saida'!$G$64,0) -> #DIV/0! | AT3: =IF('Entrada e Saida'!$H$11="TRADING",AU3*'Entrada e Saida'!$G$65,0) -> #DIV/0! | AU3: =IF('Entrada e Saida'!$H$11="TRADING",AP3/(1-(SUM('Entrada e Saida'!$G$63:$G$65)+'Custo Resumido'!D3)),0) -> #DIV/0! | AV3: =IF('Entrada e Saida'!$H$13="NÃO",AU3*M3,0) -> #DIV/0! | AW3: =AU3+AV3 -> #DIV/0! | AX3: ='Entrada e Saida'!$G$74*AU3 -> #DIV/0! | AY3: =AW3-AX3 -> #DIV/0! | AZ3: =AQ3+('Entrada e Saida'!$G$65-'Entrada e Saida'!$I$65)*AU3-AX3 -> #DIV/0! | BA3: =IF('Entrada e Saida'!$H$12="REAL",AZ3*'Entrada e Saida'!$G$81,AU3*'Entrada e Saida'!$G$81) -> #DIV/0! | BB3: =IF('Entrada e Saida'!$H$12="REAL",AZ3*'Entrada e Saida'!$G$82,AU3*'Entrada e Saida'!$G$82) -> #DIV/0! | BC3: =AZ3-BA3-BB3 -> #DIV/0! | BD3: =IF('Entrada e Saida'!$H$11="TRADING",AW3/D3,AK3/D3) -> #DIV/0! | BE3: =AX3/D3 -> #DIV/0! | BF3: =BD3-BE3 -> #DIV/0! | BG3: =IF('Entrada e Saida'!$H$11="TRADING",AV3/D3,AN3/D3) -> #DIV/0! | BH3: =IF('Entrada e Saida'!$H$11="TRADING",IF('Entrada e Saida'!$H$12="REAL",AR3/D3,0),AL3/D3) -> #DIV/0! | BI3: =IF('Entrada e Saida'!$H$11="TRADING",IF('Entrada e Saida'!$H$12="REAL",AS3/D3,0),AM3/D3) -> #DIV/0! | BJ3: =IF('Entrada e Saida'!$H$11="TRADING",AT3/D3,AO3/D3) -> #DIV/0! | BK3: =BF3-SUM(BG3:BJ3) -> #DIV/0! | BL3: =IF(O3>0,IFERROR(IF('Entrada e Saida'!$H$11="DIRETA",0,(IF('Entrada e Saida'!$H$14="P.JURIDICA",(BD3*(1+O3)*N3)-((BD3/(1+M3))*'Entrada e Saida'!$G$65),((Produtos!N3-'Entrada e Saida'!$G$65)*Produtos!BD3)))),0),0) -> 0 | BM3: =BF3+BL3 -> #DIV/0!
B4: =VLOOKUP(A4,'Master Modelo'!A:I,7,FALSE) -> #N/A | C4: =VLOOKUP(A4,'Master Modelo'!A:I,2,FALSE) -> #N/A | E4: =IFERROR(VLOOKUP(A4,'Master Modelo'!A:I,9,FALSE),0) -> 0 | F4: =IFERROR(VLOOKUP(A4,'Master Modelo'!A:I,8,FALSE),0) -> 0 | G4: =IFERROR(VLOOKUP(A4,'Master Modelo'!A:K,11,FALSE),0) -> 0 | H4: =(D4*E4)/(D4*F4) -> #DIV/0! | I4: =IFERROR(VLOOKUP(A4,'Master Modelo'!A:I,3,FALSE),0) -> 0 | J4: =IFERROR(VLOOKUP(A4,'Master Modelo'!A:I,5,FALSE),0) -> 0 | K4: =IFERROR(VLOOKUP(A4,'Master Modelo'!A:I,6,FALSE),0) -> 0 | L4: =VLOOKUP(A4,'Master Modelo'!A:J,10,FALSE) -> #N/A | M4: =IFERROR(VLOOKUP(A4,'Master Modelo'!A:I,4,FALSE),0) -> 0 | P4: =D4*F4 -> 0 | Q4: =D4*G4 -> 0 | R4: =D4*E4*'Entrada e Saida'!$K$8 -> 0 | S4: ='Entrada e Saida'!$H$21*'Entrada e Saida'!$K$8*(P4/(SUM(P:P))) -> #DIV/0! | T4: ='Entrada e Saida'!$H$21*'Entrada e Saida'!$K$8*(Q4/(SUM(Q:Q))) -> #DIV/0! | U4: ='Entrada e Saida'!$H$22*(P4/(SUM(P:P))) -> #DIV/0! | V4: ='Entrada e Saida'!$H$22*(Q4/(SUM(Q:Q))) -> #DIV/0! | W4: =R4+S4+U4 -> #DIV/0! | X4: ='Entrada e Saida'!$H$26*(IF('Entrada e Saida'!$H$15="PESO",(P4/(SUM(P:P))),(Q4/(SUM(Q:Q))))) -> #DIV/0! | Y4: ='Entrada e Saida'!$H$27*(IF('Entrada e Saida'!$H$15="PESO",(P4/(SUM(P:P))),(Q4/(SUM(Q:Q))))) -> #DIV/0! | Z4: ='Entrada e Saida'!$H$28*(IF('Entrada e Saida'!$H$15="PESO",(P4/(SUM(P:P))),(Q4/(SUM(Q:Q))))) -> #DIV/0! | AA4: =X4+Y4+Z4 -> #DIV/0! | AB4: =W4*I4 -> #DIV/0! | AC4: =W4*J4 -> #DIV/0! | AD4: =W4*K4 -> #DIV/0! | AE4: =(W4+AB4)*M4 -> #DIV/0! | AF4: =IFERROR(D4*F4*L4*'Entrada e Saida'!$K$8,0) -> 0 | AG4: =((W4+AA4+AB4+AC4+AD4+AE4+AF4)/(1-'Entrada e Saida'!$G$65))*'Entrada e Saida'!$I$66 -> #DIV/0! | AH4: =SUM(AB4:AG4) -> #DIV/0! | AI4: ='Entrada e Saida'!$K$51*(IF('Entrada e Saida'!$H$15="PESO",(P4/(SUM(P:P))),(Q4/(SUM(Q:Q))))) -> #DIV/0! | AJ4: =(('Entrada e Saida'!$K$10-'Entrada e Saida'!$K$8)*E4*D4) -> 0 | AK4: =IF('Entrada e Saida'!$H$15="PESO",W4+AA4+AH4+AI4+AJ4,W4+AA4+AH4+AI4+AJ4-S4+T4-U4+V4) -> #DIV/0! | AL4: =IF('Entrada e Saida'!$H$12="REAL",AC4,0) -> #DIV/0! | AM4: =IF('Entrada e Saida'!$H$12="REAL",AD4,0) -> #DIV/0! | AN4: =IF('Entrada e Saida'!$H$13= "NÃO",AE4,0) -> #DIV/0! | AO4: =AG4 -> #DIV/0! | AP4: =AK4-SUM(AL4:AO4) -> #DIV/0! | AQ4: =IF('Entrada e Saida'!$H$11="TRADING",AU4*'Custo Resumido'!D4,0) -> #DIV/0! | AR4: =IF('Entrada e Saida'!$H$11="TRADING",AU4*'Entrada e Saida'!$G$63,0) -> #DIV/0! | AS4: =IF('Entrada e Saida'!$H$11="TRADING",AU4*'Entrada e Saida'!$G$64,0) -> #DIV/0! | AT4: =IF('Entrada e Saida'!$H$11="TRADING",AU4*'Entrada e Saida'!$G$65,0) -> #DIV/0! | AU4: =IF('Entrada e Saida'!$H$11="TRADING",AP4/(1-(SUM('Entrada e Saida'!$G$63:$G$65)+'Custo Resumido'!D4)),0) -> #DIV/0! | AV4: =IF('Entrada e Saida'!$H$13="NÃO",AU4*M4,0) -> #DIV/0! | AW4: =AU4+AV4 -> #DIV/0! | AX4: ='Entrada e Saida'!$G$74*AU4 -> #DIV/0! | AY4: =AW4-AX4 -> #DIV/0! | AZ4: =AQ4+('Entrada e Saida'!$G$65-'Entrada e Saida'!$I$65)*AU4-AX4 -> #DIV/0! | BA4: =IF('Entrada e Saida'!$H$12="REAL",AZ4*'Entrada e Saida'!$G$81,AU4*'Entrada e Saida'!$G$81) -> #DIV/0! | BB4: =IF('Entrada e Saida'!$H$12="REAL",AZ4*'Entrada e Saida'!$G$82,AU4*'Entrada e Saida'!$G$82) -> #DIV/0! | BC4: =AZ4-BA4-BB4 -> #DIV/0! | BD4: =IF('Entrada e Saida'!$H$11="TRADING",AW4/D4,AK4/D4) -> #DIV/0! | BE4: =AX4/D4 -> #DIV/0! | BF4: =BD4-BE4 -> #DIV/0! | BG4: =IF('Entrada e Saida'!$H$11="TRADING",AV4/D4,AN4/D4) -> #DIV/0! | BH4: =IF('Entrada e Saida'!$H$11="TRADING",IF('Entrada e Saida'!$H$12="REAL",AR4/D4,0),AL4/D4) -> #DIV/0! | BI4: =IF('Entrada e Saida'!$H$11="TRADING",IF('Entrada e Saida'!$H$12="REAL",AS4/D4,0),AM4/D4) -> #DIV/0! | BJ4: =IF('Entrada e Saida'!$H$11="TRADING",AT4/D4,AO4/D4) -> #DIV/0! | BK4: =BF4-SUM(BG4:BJ4) -> #DIV/0! | BL4: =IF(O4>0,IFERROR(IF('Entrada e Saida'!$H$11="DIRETA",0,(IF('Entrada e Saida'!$H$14="P.JURIDICA",(BD4*(1+O4)*N4)-((BD4/(1+M4))*'Entrada e Saida'!$G$65),((Produtos!N4-'Entrada e Saida'!$G$65)*Produtos!BD4)))),0),0) -> 0 | BM4: =BF4+BL4 -> #DIV/0!
B5: =VLOOKUP(A5,'Master Modelo'!A:I,7,FALSE) -> #N/A | C5: =VLOOKUP(A5,'Master Modelo'!A:I,2,FALSE) -> #N/A | E5: =IFERROR(VLOOKUP(A5,'Master Modelo'!A:I,9,FALSE),0) -> 0 | F5: =IFERROR(VLOOKUP(A5,'Master Modelo'!A:I,8,FALSE),0) -> 0 | G5: =IFERROR(VLOOKUP(A5,'Master Modelo'!A:K,11,FALSE),0) -> 0 | H5: =(D5*E5)/(D5*F5) -> #DIV/0! | I5: =IFERROR(VLOOKUP(A5,'Master Modelo'!A:I,3,FALSE),0) -> 0 | J5: =IFERROR(VLOOKUP(A5,'Master Modelo'!A:I,5,FALSE),0) -> 0 | K5: =IFERROR(VLOOKUP(A5,'Master Modelo'!A:I,6,FALSE),0) -> 0 | L5: =VLOOKUP(A5,'Master Modelo'!A:J,10,FALSE) -> #N/A | M5: =IFERROR(VLOOKUP(A5,'Master Modelo'!A:I,4,FALSE),0) -> 0 | P5: =D5*F5 -> 0 | Q5: =D5*G5 -> 0 | R5: =D5*E5*'Entrada e Saida'!$K$8 -> 0 | S5: ='Entrada e Saida'!$H$21*'Entrada e Saida'!$K$8*(P5/(SUM(P:P))) -> #DIV/0! | T5: ='Entrada e Saida'!$H$21*'Entrada e Saida'!$K$8*(Q5/(SUM(Q:Q))) -> #DIV/0! | U5: ='Entrada e Saida'!$H$22*(P5/(SUM(P:P))) -> #DIV/0! | V5: ='Entrada e Saida'!$H$22*(Q5/(SUM(Q:Q))) -> #DIV/0! | W5: =R5+S5+U5 -> #DIV/0! | X5: ='Entrada e Saida'!$H$26*(IF('Entrada e Saida'!$H$15="PESO",(P5/(SUM(P:P))),(Q5/(SUM(Q:Q))))) -> #DIV/0! | Y5: ='Entrada e Saida'!$H$27*(IF('Entrada e Saida'!$H$15="PESO",(P5/(SUM(P:P))),(Q5/(SUM(Q:Q))))) -> #DIV/0! | Z5: ='Entrada e Saida'!$H$28*(IF('Entrada e Saida'!$H$15="PESO",(P5/(SUM(P:P))),(Q5/(SUM(Q:Q))))) -> #DIV/0! | AA5: =X5+Y5+Z5 -> #DIV/0! | AB5: =W5*I5 -> #DIV/0! | AC5: =W5*J5 -> #DIV/0! | AD5: =W5*K5 -> #DIV/0! | AE5: =(W5+AB5)*M5 -> #DIV/0! | AF5: =IFERROR(D5*F5*L5*'Entrada e Saida'!$K$8,0) -> 0 | AG5: =((W5+AA5+AB5+AC5+AD5+AE5+AF5)/(1-'Entrada e Saida'!$G$65))*'Entrada e Saida'!$I$66 -> #DIV/0! | AH5: =SUM(AB5:AG5) -> #DIV/0! | AI5: ='Entrada e Saida'!$K$51*(IF('Entrada e Saida'!$H$15="PESO",(P5/(SUM(P:P))),(Q5/(SUM(Q:Q))))) -> #DIV/0! | AJ5: =(('Entrada e Saida'!$K$10-'Entrada e Saida'!$K$8)*E5*D5) -> 0 | AK5: =IF('Entrada e Saida'!$H$15="PESO",W5+AA5+AH5+AI5+AJ5,W5+AA5+AH5+AI5+AJ5-S5+T5-U5+V5) -> #DIV/0! | AL5: =IF('Entrada e Saida'!$H$12="REAL",AC5,0) -> #DIV/0! | AM5: =IF('Entrada e Saida'!$H$12="REAL",AD5,0) -> #DIV/0! | AN5: =IF('Entrada e Saida'!$H$13= "NÃO",AE5,0) -> #DIV/0! | AO5: =AG5 -> #DIV/0! | AP5: =AK5-SUM(AL5:AO5) -> #DIV/0! | AQ5: =IF('Entrada e Saida'!$H$11="TRADING",AU5*'Custo Resumido'!D5,0) -> #DIV/0! | AR5: =IF('Entrada e Saida'!$H$11="TRADING",AU5*'Entrada e Saida'!$G$63,0) -> #DIV/0! | AS5: =IF('Entrada e Saida'!$H$11="TRADING",AU5*'Entrada e Saida'!$G$64,0) -> #DIV/0! | AT5: =IF('Entrada e Saida'!$H$11="TRADING",AU5*'Entrada e Saida'!$G$65,0) -> #DIV/0! | AU5: =IF('Entrada e Saida'!$H$11="TRADING",AP5/(1-(SUM('Entrada e Saida'!$G$63:$G$65)+'Custo Resumido'!D5)),0) -> #DIV/0! | AV5: =IF('Entrada e Saida'!$H$13="NÃO",AU5*M5,0) -> #DIV/0! | AW5: =AU5+AV5 -> #DIV/0! | AX5: ='Entrada e Saida'!$G$74*AU5 -> #DIV/0! | AY5: =AW5-AX5 -> #DIV/0! | AZ5: =AQ5+('Entrada e Saida'!$G$65-'Entrada e Saida'!$I$65)*AU5-AX5 -> #DIV/0! | BA5: =IF('Entrada e Saida'!$H$12="REAL",AZ5*'Entrada e Saida'!$G$81,AU5*'Entrada e Saida'!$G$81) -> #DIV/0! | BB5: =IF('Entrada e Saida'!$H$12="REAL",AZ5*'Entrada e Saida'!$G$82,AU5*'Entrada e Saida'!$G$82) -> #DIV/0! | BC5: =AZ5-BA5-BB5 -> #DIV/0! | BD5: =IF('Entrada e Saida'!$H$11="TRADING",AW5/D5,AK5/D5) -> #DIV/0! | BE5: =AX5/D5 -> #DIV/0! | BF5: =BD5-BE5 -> #DIV/0! | BG5: =IF('Entrada e Saida'!$H$11="TRADING",AV5/D5,AN5/D5) -> #DIV/0! | BH5: =IF('Entrada e Saida'!$H$11="TRADING",IF('Entrada e Saida'!$H$12="REAL",AR5/D5,0),AL5/D5) -> #DIV/0! | BI5: =IF('Entrada e Saida'!$H$11="TRADING",IF('Entrada e Saida'!$H$12="REAL",AS5/D5,0),AM5/D5) -> #DIV/0! | BJ5: =IF('Entrada e Saida'!$H$11="TRADING",AT5/D5,AO5/D5) -> #DIV/0! | BK5: =BF5-SUM(BG5:BJ5) -> #DIV/0! | BL5: =IF(O5>0,IFERROR(IF('Entrada e Saida'!$H$11="DIRETA",0,(IF('Entrada e Saida'!$H$14="P.JURIDICA",(BD5*(1+O5)*N5)-((BD5/(1+M5))*'Entrada e Saida'!$G$65),((Produtos!N5-'Entrada e Saida'!$G$65)*Produtos!BD5)))),0),0) -> 0 | BM5: =BF5+BL5 -> #DIV/0!
B6: =VLOOKUP(A6,'Master Modelo'!A:I,7,FALSE) -> #N/A | C6: =VLOOKUP(A6,'Master Modelo'!A:I,2,FALSE) -> #N/A | E6: =IFERROR(VLOOKUP(A6,'Master Modelo'!A:I,9,FALSE),0) -> 0 | F6: =IFERROR(VLOOKUP(A6,'Master Modelo'!A:I,8,FALSE),0) -> 0 | G6: =IFERROR(VLOOKUP(A6,'Master Modelo'!A:K,11,FALSE),0) -> 0 | H6: =(D6*E6)/(D6*F6) -> #DIV/0! | I6: =IFERROR(VLOOKUP(A6,'Master Modelo'!A:I,3,FALSE),0) -> 0 | J6: =IFERROR(VLOOKUP(A6,'Master Modelo'!A:I,5,FALSE),0) -> 0 | K6: =IFERROR(VLOOKUP(A6,'Master Modelo'!A:I,6,FALSE),0) -> 0 | L6: =VLOOKUP(A6,'Master Modelo'!A:J,10,FALSE) -> #N/A | M6: =IFERROR(VLOOKUP(A6,'Master Modelo'!A:I,4,FALSE),0) -> 0 | P6: =D6*F6 -> 0 | Q6: =D6*G6 -> 0 | R6: =D6*E6*'Entrada e Saida'!$K$8 -> 0 | S6: ='Entrada e Saida'!$H$21*'Entrada e Saida'!$K$8*(P6/(SUM(P:P))) -> #DIV/0! | T6: ='Entrada e Saida'!$H$21*'Entrada e Saida'!$K$8*(Q6/(SUM(Q:Q))) -> #DIV/0! | U6: ='Entrada e Saida'!$H$22*(P6/(SUM(P:P))) -> #DIV/0! | V6: ='Entrada e Saida'!$H$22*(Q6/(SUM(Q:Q))) -> #DIV/0! | W6: =R6+S6+U6 -> #DIV/0! | X6: ='Entrada e Saida'!$H$26*(IF('Entrada e Saida'!$H$15="PESO",(P6/(SUM(P:P))),(Q6/(SUM(Q:Q))))) -> #DIV/0! | Y6: ='Entrada e Saida'!$H$27*(IF('Entrada e Saida'!$H$15="PESO",(P6/(SUM(P:P))),(Q6/(SUM(Q:Q))))) -> #DIV/0! | Z6: ='Entrada e Saida'!$H$28*(IF('Entrada e Saida'!$H$15="PESO",(P6/(SUM(P:P))),(Q6/(SUM(Q:Q))))) -> #DIV/0! | AA6: =X6+Y6+Z6 -> #DIV/0! | AB6: =W6*I6 -> #DIV/0! | AC6: =W6*J6 -> #DIV/0! | AD6: =W6*K6 -> #DIV/0! | AE6: =(W6+AB6)*M6 -> #DIV/0! | AF6: =IFERROR(D6*F6*L6*'Entrada e Saida'!$K$8,0) -> 0 | AG6: =((W6+AA6+AB6+AC6+AD6+AE6+AF6)/(1-'Entrada e Saida'!$G$65))*'Entrada e Saida'!$I$66 -> #DIV/0! | AH6: =SUM(AB6:AG6) -> #DIV/0! | AI6: ='Entrada e Saida'!$K$51*(IF('Entrada e Saida'!$H$15="PESO",(P6/(SUM(P:P))),(Q6/(SUM(Q:Q))))) -> #DIV/0! | AJ6: =(('Entrada e Saida'!$K$10-'Entrada e Saida'!$K$8)*E6*D6) -> 0 | AK6: =IF('Entrada e Saida'!$H$15="PESO",W6+AA6+AH6+AI6+AJ6,W6+AA6+AH6+AI6+AJ6-S6+T6-U6+V6) -> #DIV/0! | AL6: =IF('Entrada e Saida'!$H$12="REAL",AC6,0) -> #DIV/0! | AM6: =IF('Entrada e Saida'!$H$12="REAL",AD6,0) -> #DIV/0! | AN6: =IF('Entrada e Saida'!$H$13= "NÃO",AE6,0) -> #DIV/0! | AO6: =AG6 -> #DIV/0! | AP6: =AK6-SUM(AL6:AO6) -> #DIV/0! | AQ6: =IF('Entrada e Saida'!$H$11="TRADING",AU6*'Custo Resumido'!D6,0) -> #DIV/0! | AR6: =IF('Entrada e Saida'!$H$11="TRADING",AU6*'Entrada e Saida'!$G$63,0) -> #DIV/0! | AS6: =IF('Entrada e Saida'!$H$11="TRADING",AU6*'Entrada e Saida'!$G$64,0) -> #DIV/0! | AT6: =IF('Entrada e Saida'!$H$11="TRADING",AU6*'Entrada e Saida'!$G$65,0) -> #DIV/0! | AU6: =IF('Entrada e Saida'!$H$11="TRADING",AP6/(1-(SUM('Entrada e Saida'!$G$63:$G$65)+'Custo Resumido'!D6)),0) -> #DIV/0! | AV6: =IF('Entrada e Saida'!$H$13="NÃO",AU6*M6,0) -> #DIV/0! | AW6: =AU6+AV6 -> #DIV/0! | AX6: ='Entrada e Saida'!$G$74*AU6 -> #DIV/0! | AY6: =AW6-AX6 -> #DIV/0! | AZ6: =AQ6+('Entrada e Saida'!$G$65-'Entrada e Saida'!$I$65)*AU6-AX6 -> #DIV/0! | BA6: =IF('Entrada e Saida'!$H$12="REAL",AZ6*'Entrada e Saida'!$G$81,AU6*'Entrada e Saida'!$G$81) -> #DIV/0! | BB6: =IF('Entrada e Saida'!$H$12="REAL",AZ6*'Entrada e Saida'!$G$82,AU6*'Entrada e Saida'!$G$82) -> #DIV/0! | BC6: =AZ6-BA6-BB6 -> #DIV/0! | BD6: =IF('Entrada e Saida'!$H$11="TRADING",AW6/D6,AK6/D6) -> #DIV/0! | BE6: =AX6/D6 -> #DIV/0! | BF6: =BD6-BE6 -> #DIV/0! | BG6: =IF('Entrada e Saida'!$H$11="TRADING",AV6/D6,AN6/D6) -> #DIV/0! | BH6: =IF('Entrada e Saida'!$H$11="TRADING",IF('Entrada e Saida'!$H$12="REAL",AR6/D6,0),AL6/D6) -> #DIV/0! | BI6: =IF('Entrada e Saida'!$H$11="TRADING",IF('Entrada e Saida'!$H$12="REAL",AS6/D6,0),AM6/D6) -> #DIV/0! | BJ6: =IF('Entrada e Saida'!$H$11="TRADING",AT6/D6,AO6/D6) -> #DIV/0! | BK6: =BF6-SUM(BG6:BJ6) -> #DIV/0! | BL6: =IF(O6>0,IFERROR(IF('Entrada e Saida'!$H$11="DIRETA",0,(IF('Entrada e Saida'!$H$14="P.JURIDICA",(BD6*(1+O6)*N6)-((BD6/(1+M6))*'Entrada e Saida'!$G$65),((Produtos!N6-'Entrada e Saida'!$G$65)*Produtos!BD6)))),0),0) -> 0 | BM6: =BF6+BL6 -> #DIV/0!
B7: =VLOOKUP(A7,'Master Modelo'!A:I,7,FALSE) -> #N/A | C7: =VLOOKUP(A7,'Master Modelo'!A:I,2,FALSE) -> #N/A | E7: =IFERROR(VLOOKUP(A7,'Master Modelo'!A:I,9,FALSE),0) -> 0 | F7: =IFERROR(VLOOKUP(A7,'Master Modelo'!A:I,8,FALSE),0) -> 0 | G7: =IFERROR(VLOOKUP(A7,'Master Modelo'!A:K,11,FALSE),0) -> 0 | H7: =(D7*E7)/(D7*F7) -> #DIV/0! | I7: =IFERROR(VLOOKUP(A7,'Master Modelo'!A:I,3,FALSE),0) -> 0 | J7: =IFERROR(VLOOKUP(A7,'Master Modelo'!A:I,5,FALSE),0) -> 0 | K7: =IFERROR(VLOOKUP(A7,'Master Modelo'!A:I,6,FALSE),0) -> 0 | L7: =VLOOKUP(A7,'Master Modelo'!A:J,10,FALSE) -> #N/A | M7: =IFERROR(VLOOKUP(A7,'Master Modelo'!A:I,4,FALSE),0) -> 0 | P7: =D7*F7 -> 0 | Q7: =D7*G7 -> 0 | R7: =D7*E7*'Entrada e Saida'!$K$8 -> 0 | S7: ='Entrada e Saida'!$H$21*'Entrada e Saida'!$K$8*(P7/(SUM(P:P))) -> #DIV/0! | T7: ='Entrada e Saida'!$H$21*'Entrada e Saida'!$K$8*(Q7/(SUM(Q:Q))) -> #DIV/0! | U7: ='Entrada e Saida'!$H$22*(P7/(SUM(P:P))) -> #DIV/0! | V7: ='Entrada e Saida'!$H$22*(Q7/(SUM(Q:Q))) -> #DIV/0! | W7: =R7+S7+U7 -> #DIV/0! | X7: ='Entrada e Saida'!$H$26*(IF('Entrada e Saida'!$H$15="PESO",(P7/(SUM(P:P))),(Q7/(SUM(Q:Q))))) -> #DIV/0! | Y7: ='Entrada e Saida'!$H$27*(IF('Entrada e Saida'!$H$15="PESO",(P7/(SUM(P:P))),(Q7/(SUM(Q:Q))))) -> #DIV/0! | Z7: ='Entrada e Saida'!$H$28*(IF('Entrada e Saida'!$H$15="PESO",(P7/(SUM(P:P))),(Q7/(SUM(Q:Q))))) -> #DIV/0! | AA7: =X7+Y7+Z7 -> #DIV/0! | AB7: =W7*I7 -> #DIV/0! | AC7: =W7*J7 -> #DIV/0! | AD7: =W7*K7 -> #DIV/0! | AE7: =(W7+AB7)*M7 -> #DIV/0! | AF7: =IFERROR(D7*F7*L7*'Entrada e Saida'!$K$8,0) -> 0 | AG7: =((W7+AA7+AB7+AC7+AD7+AE7+AF7)/(1-'Entrada e Saida'!$G$65))*'Entrada e Saida'!$I$66 -> #DIV/0! | AH7: =SUM(AB7:AG7) -> #DIV/0! | AI7: ='Entrada e Saida'!$K$51*(IF('Entrada e Saida'!$H$15="PESO",(P7/(SUM(P:P))),(Q7/(SUM(Q:Q))))) -> #DIV/0! | AJ7: =(('Entrada e Saida'!$K$10-'Entrada e Saida'!$K$8)*E7*D7) -> 0 | AK7: =IF('Entrada e Saida'!$H$15="PESO",W7+AA7+AH7+AI7+AJ7,W7+AA7+AH7+AI7+AJ7-S7+T7-U7+V7) -> #DIV/0! | AL7: =IF('Entrada e Saida'!$H$12="REAL",AC7,0) -> #DIV/0! | AM7: =IF('Entrada e Saida'!$H$12="REAL",AD7,0) -> #DIV/0! | AN7: =IF('Entrada e Saida'!$H$13= "NÃO",AE7,0) -> #DIV/0! | AO7: =AG7 -> #DIV/0! | AP7: =AK7-SUM(AL7:AO7) -> #DIV/0! | AQ7: =IF('Entrada e Saida'!$H$11="TRADING",AU7*'Custo Resumido'!D7,0) -> #DIV/0! | AR7: =IF('Entrada e Saida'!$H$11="TRADING",AU7*'Entrada e Saida'!$G$63,0) -> #DIV/0! | AS7: =IF('Entrada e Saida'!$H$11="TRADING",AU7*'Entrada e Saida'!$G$64,0) -> #DIV/0! | AT7: =IF('Entrada e Saida'!$H$11="TRADING",AU7*'Entrada e Saida'!$G$65,0) -> #DIV/0! | AU7: =IF('Entrada e Saida'!$H$11="TRADING",AP7/(1-(SUM('Entrada e Saida'!$G$63:$G$65)+'Custo Resumido'!D7)),0) -> #DIV/0! | AV7: =IF('Entrada e Saida'!$H$13="NÃO",AU7*M7,0) -> #DIV/0! | AW7: =AU7+AV7 -> #DIV/0! | AX7: ='Entrada e Saida'!$G$74*AU7 -> #DIV/0! | AY7: =AW7-AX7 -> #DIV/0! | AZ7: =AQ7+('Entrada e Saida'!$G$65-'Entrada e Saida'!$I$65)*AU7-AX7 -> #DIV/0! | BA7: =IF('Entrada e Saida'!$H$12="REAL",AZ7*'Entrada e Saida'!$G$81,AU7*'Entrada e Saida'!$G$81) -> #DIV/0! | BB7: =IF('Entrada e Saida'!$H$12="REAL",AZ7*'Entrada e Saida'!$G$82,AU7*'Entrada e Saida'!$G$82) -> #DIV/0! | BC7: =AZ7-BA7-BB7 -> #DIV/0! | BD7: =IF('Entrada e Saida'!$H$11="TRADING",AW7/D7,AK7/D7) -> #DIV/0! | BE7: =AX7/D7 -> #DIV/0! | BF7: =BD7-BE7 -> #DIV/0! | BG7: =IF('Entrada e Saida'!$H$11="TRADING",AV7/D7,AN7/D7) -> #DIV/0! | BH7: =IF('Entrada e Saida'!$H$11="TRADING",IF('Entrada e Saida'!$H$12="REAL",AR7/D7,0),AL7/D7) -> #DIV/0! | BI7: =IF('Entrada e Saida'!$H$11="TRADING",IF('Entrada e Saida'!$H$12="REAL",AS7/D7,0),AM7/D7) -> #DIV/0! | BJ7: =IF('Entrada e Saida'!$H$11="TRADING",AT7/D7,AO7/D7) -> #DIV/0! | BK7: =BF7-SUM(BG7:BJ7) -> #DIV/0! | BL7: =IF(O7>0,IFERROR(IF('Entrada e Saida'!$H$11="DIRETA",0,(IF('Entrada e Saida'!$H$14="P.JURIDICA",(BD7*(1+O7)*N7)-((BD7/(1+M7))*'Entrada e Saida'!$G$65),((Produtos!N7-'Entrada e Saida'!$G$65)*Produtos!BD7)))),0),0) -> 0 | BM7: =BF7+BL7 -> #DIV/0!
B8: =VLOOKUP(A8,'Master Modelo'!A:I,7,FALSE) -> #N/A | C8: =VLOOKUP(A8,'Master Modelo'!A:I,2,FALSE) -> #N/A | E8: =IFERROR(VLOOKUP(A8,'Master Modelo'!A:I,9,FALSE),0) -> 0 | F8: =IFERROR(VLOOKUP(A8,'Master Modelo'!A:I,8,FALSE),0) -> 0 | G8: =IFERROR(VLOOKUP(A8,'Master Modelo'!A:K,11,FALSE),0) -> 0 | H8: =(D8*E8)/(D8*F8) -> #DIV/0! | I8: =IFERROR(VLOOKUP(A8,'Master Modelo'!A:I,3,FALSE),0) -> 0 | J8: =IFERROR(VLOOKUP(A8,'Master Modelo'!A:I,5,FALSE),0) -> 0 | K8: =IFERROR(VLOOKUP(A8,'Master Modelo'!A:I,6,FALSE),0) -> 0 | L8: =VLOOKUP(A8,'Master Modelo'!A:J,10,FALSE) -> #N/A | M8: =IFERROR(VLOOKUP(A8,'Master Modelo'!A:I,4,FALSE),0) -> 0 | P8: =D8*F8 -> 0 | Q8: =D8*G8 -> 0 | R8: =D8*E8*'Entrada e Saida'!$K$8 -> 0 | S8: ='Entrada e Saida'!$H$21*'Entrada e Saida'!$K$8*(P8/(SUM(P:P))) -> #DIV/0! | T8: ='Entrada e Saida'!$H$21*'Entrada e Saida'!$K$8*(Q8/(SUM(Q:Q))) -> #DIV/0! | U8: ='Entrada e Saida'!$H$22*(P8/(SUM(P:P))) -> #DIV/0! | V8: ='Entrada e Saida'!$H$22*(Q8/(SUM(Q:Q))) -> #DIV/0! | W8: =R8+S8+U8 -> #DIV/0! | X8: ='Entrada e Saida'!$H$26*(IF('Entrada e Saida'!$H$15="PESO",(P8/(SUM(P:P))),(Q8/(SUM(Q:Q))))) -> #DIV/0! | Y8: ='Entrada e Saida'!$H$27*(IF('Entrada e Saida'!$H$15="PESO",(P8/(SUM(P:P))),(Q8/(SUM(Q:Q))))) -> #DIV/0! | Z8: ='Entrada e Saida'!$H$28*(IF('Entrada e Saida'!$H$15="PESO",(P8/(SUM(P:P))),(Q8/(SUM(Q:Q))))) -> #DIV/0! | AA8: =X8+Y8+Z8 -> #DIV/0! | AB8: =W8*I8 -> #DIV/0! | AC8: =W8*J8 -> #DIV/0! | AD8: =W8*K8 -> #DIV/0! | AE8: =(W8+AB8)*M8 -> #DIV/0! | AF8: =IFERROR(D8*F8*L8*'Entrada e Saida'!$K$8,0) -> 0 | AG8: =((W8+AA8+AB8+AC8+AD8+AE8+AF8)/(1-'Entrada e Saida'!$G$65))*'Entrada e Saida'!$I$66 -> #DIV/0! | AH8: =SUM(AB8:AG8) -> #DIV/0! | AI8: ='Entrada e Saida'!$K$51*(IF('Entrada e Saida'!$H$15="PESO",(P8/(SUM(P:P))),(Q8/(SUM(Q:Q))))) -> #DIV/0! | AJ8: =(('Entrada e Saida'!$K$10-'Entrada e Saida'!$K$8)*E8*D8) -> 0 | AK8: =IF('Entrada e Saida'!$H$15="PESO",W8+AA8+AH8+AI8+AJ8,W8+AA8+AH8+AI8+AJ8-S8+T8-U8+V8) -> #DIV/0! | AL8: =IF('Entrada e Saida'!$H$12="REAL",AC8,0) -> #DIV/0! | AM8: =IF('Entrada e Saida'!$H$12="REAL",AD8,0) -> #DIV/0! | AN8: =IF('Entrada e Saida'!$H$13= "NÃO",AE8,0) -> #DIV/0! | AO8: =AG8 -> #DIV/0! | AP8: =AK8-SUM(AL8:AO8) -> #DIV/0! | AQ8: =IF('Entrada e Saida'!$H$11="TRADING",AU8*'Custo Resumido'!D8,0) -> #DIV/0! | AR8: =IF('Entrada e Saida'!$H$11="TRADING",AU8*'Entrada e Saida'!$G$63,0) -> #DIV/0! | AS8: =IF('Entrada e Saida'!$H$11="TRADING",AU8*'Entrada e Saida'!$G$64,0) -> #DIV/0! | AT8: =IF('Entrada e Saida'!$H$11="TRADING",AU8*'Entrada e Saida'!$G$65,0) -> #DIV/0! | AU8: =IF('Entrada e Saida'!$H$11="TRADING",AP8/(1-(SUM('Entrada e Saida'!$G$63:$G$65)+'Custo Resumido'!D8)),0) -> #DIV/0! | AV8: =IF('Entrada e Saida'!$H$13="NÃO",AU8*M8,0) -> #DIV/0! | AW8: =AU8+AV8 -> #DIV/0! | AX8: ='Entrada e Saida'!$G$74*AU8 -> #DIV/0! | AY8: =AW8-AX8 -> #DIV/0! | AZ8: =AQ8+('Entrada e Saida'!$G$65-'Entrada e Saida'!$I$65)*AU8-AX8 -> #DIV/0! | BA8: =IF('Entrada e Saida'!$H$12="REAL",AZ8*'Entrada e Saida'!$G$81,AU8*'Entrada e Saida'!$G$81) -> #DIV/0! | BB8: =IF('Entrada e Saida'!$H$12="REAL",AZ8*'Entrada e Saida'!$G$82,AU8*'Entrada e Saida'!$G$82) -> #DIV/0! | BC8: =AZ8-BA8-BB8 -> #DIV/0! | BD8: =IF('Entrada e Saida'!$H$11="TRADING",AW8/D8,AK8/D8) -> #DIV/0! | BE8: =AX8/D8 -> #DIV/0! | BF8: =BD8-BE8 -> #DIV/0! | BG8: =IF('Entrada e Saida'!$H$11="TRADING",AV8/D8,AN8/D8) -> #DIV/0! | BH8: =IF('Entrada e Saida'!$H$11="TRADING",IF('Entrada e Saida'!$H$12="REAL",AR8/D8,0),AL8/D8) -> #DIV/0! | BI8: =IF('Entrada e Saida'!$H$11="TRADING",IF('Entrada e Saida'!$H$12="REAL",AS8/D8,0),AM8/D8) -> #DIV/0! | BJ8: =IF('Entrada e Saida'!$H$11="TRADING",AT8/D8,AO8/D8) -> #DIV/0! | BK8: =BF8-SUM(BG8:BJ8) -> #DIV/0! | BL8: =IF(O8>0,IFERROR(IF('Entrada e Saida'!$H$11="DIRETA",0,(IF('Entrada e Saida'!$H$14="P.JURIDICA",(BD8*(1+O8)*N8)-((BD8/(1+M8))*'Entrada e Saida'!$G$65),((Produtos!N8-'Entrada e Saida'!$G$65)*Produtos!BD8)))),0),0) -> 0 | BM8: =BF8+BL8 -> #DIV/0!
B9: =VLOOKUP(A9,'Master Modelo'!A:I,7,FALSE) -> #N/A | C9: =VLOOKUP(A9,'Master Modelo'!A:I,2,FALSE) -> #N/A | E9: =IFERROR(VLOOKUP(A9,'Master Modelo'!A:I,9,FALSE),0) -> 0 | F9: =IFERROR(VLOOKUP(A9,'Master Modelo'!A:I,8,FALSE),0) -> 0 | G9: =IFERROR(VLOOKUP(A9,'Master Modelo'!A:K,11,FALSE),0) -> 0 | H9: =(D9*E9)/(D9*F9) -> #DIV/0! | I9: =IFERROR(VLOOKUP(A9,'Master Modelo'!A:I,3,FALSE),0) -> 0 | J9: =IFERROR(VLOOKUP(A9,'Master Modelo'!A:I,5,FALSE),0) -> 0 | K9: =IFERROR(VLOOKUP(A9,'Master Modelo'!A:I,6,FALSE),0) -> 0 | L9: =VLOOKUP(A9,'Master Modelo'!A:J,10,FALSE) -> #N/A | M9: =IFERROR(VLOOKUP(A9,'Master Modelo'!A:I,4,FALSE),0) -> 0 | P9: =D9*F9 -> 0 | Q9: =D9*G9 -> 0 | R9: =D9*E9*'Entrada e Saida'!$K$8 -> 0 | S9: ='Entrada e Saida'!$H$21*'Entrada e Saida'!$K$8*(P9/(SUM(P:P))) -> #DIV/0! | T9: ='Entrada e Saida'!$H$21*'Entrada e Saida'!$K$8*(Q9/(SUM(Q:Q))) -> #DIV/0! | U9: ='Entrada e Saida'!$H$22*(P9/(SUM(P:P))) -> #DIV/0! | V9: ='Entrada e Saida'!$H$22*(Q9/(SUM(Q:Q))) -> #DIV/0! | W9: =R9+S9+U9 -> #DIV/0! | X9: ='Entrada e Saida'!$H$26*(IF('Entrada e Saida'!$H$15="PESO",(P9/(SUM(P:P))),(Q9/(SUM(Q:Q))))) -> #DIV/0! | Y9: ='Entrada e Saida'!$H$27*(IF('Entrada e Saida'!$H$15="PESO",(P9/(SUM(P:P))),(Q9/(SUM(Q:Q))))) -> #DIV/0! | Z9: ='Entrada e Saida'!$H$28*(IF('Entrada e Saida'!$H$15="PESO",(P9/(SUM(P:P))),(Q9/(SUM(Q:Q))))) -> #DIV/0! | AA9: =X9+Y9+Z9 -> #DIV/0! | AB9: =W9*I9 -> #DIV/0! | AC9: =W9*J9 -> #DIV/0! | AD9: =W9*K9 -> #DIV/0! | AE9: =(W9+AB9)*M9 -> #DIV/0! | AF9: =IFERROR(D9*F9*L9*'Entrada e Saida'!$K$8,0) -> 0 | AG9: =((W9+AA9+AB9+AC9+AD9+AE9+AF9)/(1-'Entrada e Saida'!$G$65))*'Entrada e Saida'!$I$66 -> #DIV/0! | AH9: =SUM(AB9:AG9) -> #DIV/0! | AI9: ='Entrada e Saida'!$K$51*(IF('Entrada e Saida'!$H$15="PESO",(P9/(SUM(P:P))),(Q9/(SUM(Q:Q))))) -> #DIV/0! | AJ9: =(('Entrada e Saida'!$K$10-'Entrada e Saida'!$K$8)*E9*D9) -> 0 | AK9: =IF('Entrada e Saida'!$H$15="PESO",W9+AA9+AH9+AI9+AJ9,W9+AA9+AH9+AI9+AJ9-S9+T9-U9+V9) -> #DIV/0! | AL9: =IF('Entrada e Saida'!$H$12="REAL",AC9,0) -> #DIV/0! | AM9: =IF('Entrada e Saida'!$H$12="REAL",AD9,0) -> #DIV/0! | AN9: =IF('Entrada e Saida'!$H$13= "NÃO",AE9,0) -> #DIV/0! | AO9: =AG9 -> #DIV/0! | AP9: =AK9-SUM(AL9:AO9) -> #DIV/0! | AQ9: =IF('Entrada e Saida'!$H$11="TRADING",AU9*'Custo Resumido'!D9,0) -> #DIV/0! | AR9: =IF('Entrada e Saida'!$H$11="TRADING",AU9*'Entrada e Saida'!$G$63,0) -> #DIV/0! | AS9: =IF('Entrada e Saida'!$H$11="TRADING",AU9*'Entrada e Saida'!$G$64,0) -> #DIV/0! | AT9: =IF('Entrada e Saida'!$H$11="TRADING",AU9*'Entrada e Saida'!$G$65,0) -> #DIV/0! | AU9: =IF('Entrada e Saida'!$H$11="TRADING",AP9/(1-(SUM('Entrada e Saida'!$G$63:$G$65)+'Custo Resumido'!D9)),0) -> #DIV/0! | AV9: =IF('Entrada e Saida'!$H$13="NÃO",AU9*M9,0) -> #DIV/0! | AW9: =AU9+AV9 -> #DIV/0! | AX9: ='Entrada e Saida'!$G$74*AU9 -> #DIV/0! | AY9: =AW9-AX9 -> #DIV/0! | AZ9: =AQ9+('Entrada e Saida'!$G$65-'Entrada e Saida'!$I$65)*AU9-AX9 -> #DIV/0! | BA9: =IF('Entrada e Saida'!$H$12="REAL",AZ9*'Entrada e Saida'!$G$81,AU9*'Entrada e Saida'!$G$81) -> #DIV/0! | BB9: =IF('Entrada e Saida'!$H$12="REAL",AZ9*'Entrada e Saida'!$G$82,AU9*'Entrada e Saida'!$G$82) -> #DIV/0! | BC9: =AZ9-BA9-BB9 -> #DIV/0! | BD9: =IF('Entrada e Saida'!$H$11="TRADING",AW9/D9,AK9/D9) -> #DIV/0! | BE9: =AX9/D9 -> #DIV/0! | BF9: =BD9-BE9 -> #DIV/0! | BG9: =IF('Entrada e Saida'!$H$11="TRADING",AV9/D9,AN9/D9) -> #DIV/0! | BH9: =IF('Entrada e Saida'!$H$11="TRADING",IF('Entrada e Saida'!$H$12="REAL",AR9/D9,0),AL9/D9) -> #DIV/0! | BI9: =IF('Entrada e Saida'!$H$11="TRADING",IF('Entrada e Saida'!$H$12="REAL",AS9/D9,0),AM9/D9) -> #DIV/0! | BJ9: =IF('Entrada e Saida'!$H$11="TRADING",AT9/D9,AO9/D9) -> #DIV/0! | BK9: =BF9-SUM(BG9:BJ9) -> #DIV/0! | BL9: =IF(O9>0,IFERROR(IF('Entrada e Saida'!$H$11="DIRETA",0,(IF('Entrada e Saida'!$H$14="P.JURIDICA",(BD9*(1+O9)*N9)-((BD9/(1+M9))*'Entrada e Saida'!$G$65),((Produtos!N9-'Entrada e Saida'!$G$65)*Produtos!BD9)))),0),0) -> 0 | BM9: =BF9+BL9 -> #DIV/0!
B10: =VLOOKUP(A10,'Master Modelo'!A:I,7,FALSE) -> #N/A | C10: =VLOOKUP(A10,'Master Modelo'!A:I,2,FALSE) -> #N/A | E10: =IFERROR(VLOOKUP(A10,'Master Modelo'!A:I,9,FALSE),0) -> 0 | F10: =IFERROR(VLOOKUP(A10,'Master Modelo'!A:I,8,FALSE),0) -> 0 | G10: =IFERROR(VLOOKUP(A10,'Master Modelo'!A:K,11,FALSE),0) -> 0 | H10: =(D10*E10)/(D10*F10) -> #DIV/0! | I10: =IFERROR(VLOOKUP(A10,'Master Modelo'!A:I,3,FALSE),0) -> 0 | J10: =IFERROR(VLOOKUP(A10,'Master Modelo'!A:I,5,FALSE),0) -> 0 | K10: =IFERROR(VLOOKUP(A10,'Master Modelo'!A:I,6,FALSE),0) -> 0 | L10: =VLOOKUP(A10,'Master Modelo'!A:J,10,FALSE) -> #N/A | M10: =IFERROR(VLOOKUP(A10,'Master Modelo'!A:I,4,FALSE),0) -> 0 | P10: =D10*F10 -> 0 | Q10: =D10*G10 -> 0 | R10: =D10*E10*'Entrada e Saida'!$K$8 -> 0 | S10: ='Entrada e Saida'!$H$21*'Entrada e Saida'!$K$8*(P10/(SUM(P:P))) -> #DIV/0! | T10: ='Entrada e Saida'!$H$21*'Entrada e Saida'!$K$8*(Q10/(SUM(Q:Q))) -> #DIV/0! | U10: ='Entrada e Saida'!$H$22*(P10/(SUM(P:P))) -> #DIV/0! | V10: ='Entrada e Saida'!$H$22*(Q10/(SUM(Q:Q))) -> #DIV/0! | W10: =R10+S10+U10 -> #DIV/0! | X10: ='Entrada e Saida'!$H$26*(IF('Entrada e Saida'!$H$15="PESO",(P10/(SUM(P:P))),(Q10/(SUM(Q:Q))))) -> #DIV/0! | Y10: ='Entrada e Saida'!$H$27*(IF('Entrada e Saida'!$H$15="PESO",(P10/(SUM(P:P))),(Q10/(SUM(Q:Q))))) -> #DIV/0! | Z10: ='Entrada e Saida'!$H$28*(IF('Entrada e Saida'!$H$15="PESO",(P10/(SUM(P:P))),(Q10/(SUM(Q:Q))))) -> #DIV/0! | AA10: =X10+Y10+Z10 -> #DIV/0! | AB10: =W10*I10 -> #DIV/0! | AC10: =W10*J10 -> #DIV/0! | AD10: =W10*K10 -> #DIV/0! | AE10: =(W10+AB10)*M10 -> #DIV/0! | AF10: =IFERROR(D10*F10*L10*'Entrada e Saida'!$K$8,0) -> 0 | AG10: =((W10+AA10+AB10+AC10+AD10+AE10+AF10)/(1-'Entrada e Saida'!$G$65))*'Entrada e Saida'!$I$66 -> #DIV/0! | AH10: =SUM(AB10:AG10) -> #DIV/0! | AI10: ='Entrada e Saida'!$K$51*(IF('Entrada e Saida'!$H$15="PESO",(P10/(SUM(P:P))),(Q10/(SUM(Q:Q))))) -> #DIV/0! | AJ10: =(('Entrada e Saida'!$K$10-'Entrada e Saida'!$K$8)*E10*D10) -> 0 | AK10: =IF('Entrada e Saida'!$H$15="PESO",W10+AA10+AH10+AI10+AJ10,W10+AA10+AH10+AI10+AJ10-S10+T10-U10+V10) -> #DIV/0! | AL10: =IF('Entrada e Saida'!$H$12="REAL",AC10,0) -> #DIV/0! | AM10: =IF('Entrada e Saida'!$H$12="REAL",AD10,0) -> #DIV/0! | AN10: =IF('Entrada e Saida'!$H$13= "NÃO",AE10,0) -> #DIV/0! | AO10: =AG10 -> #DIV/0! | AP10: =AK10-SUM(AL10:AO10) -> #DIV/0! | AQ10: =IF('Entrada e Saida'!$H$11="TRADING",AU10*'Custo Resumido'!D10,0) -> #DIV/0! | AR10: =IF('Entrada e Saida'!$H$11="TRADING",AU10*'Entrada e Saida'!$G$63,0) -> #DIV/0! | AS10: =IF('Entrada e Saida'!$H$11="TRADING",AU10*'Entrada e Saida'!$G$64,0) -> #DIV/0! | AT10: =IF('Entrada e Saida'!$H$11="TRADING",AU10*'Entrada e Saida'!$G$65,0) -> #DIV/0! | AU10: =IF('Entrada e Saida'!$H$11="TRADING",AP10/(1-(SUM('Entrada e Saida'!$G$63:$G$65)+'Custo Resumido'!D10)),0) -> #DIV/0! | AV10: =IF('Entrada e Saida'!$H$13="NÃO",AU10*M10,0) -> #DIV/0! | AW10: =AU10+AV10 -> #DIV/0! | AX10: ='Entrada e Saida'!$G$74*AU10 -> #DIV/0! | AY10: =AW10-AX10 -> #DIV/0! | AZ10: =AQ10+('Entrada e Saida'!$G$65-'Entrada e Saida'!$I$65)*AU10-AX10 -> #DIV/0! | BA10: =IF('Entrada e Saida'!$H$12="REAL",AZ10*'Entrada e Saida'!$G$81,AU10*'Entrada e Saida'!$G$81) -> #DIV/0! | BB10: =IF('Entrada e Saida'!$H$12="REAL",AZ10*'Entrada e Saida'!$G$82,AU10*'Entrada e Saida'!$G$82) -> #DIV/0! | BC10: =AZ10-BA10-BB10 -> #DIV/0! | BD10: =IF('Entrada e Saida'!$H$11="TRADING",AW10/D10,AK10/D10) -> #DIV/0! | BE10: =AX10/D10 -> #DIV/0! | BF10: =BD10-BE10 -> #DIV/0! | BG10: =IF('Entrada e Saida'!$H$11="TRADING",AV10/D10,AN10/D10) -> #DIV/0! | BH10: =IF('Entrada e Saida'!$H$11="TRADING",IF('Entrada e Saida'!$H$12="REAL",AR10/D10,0),AL10/D10) -> #DIV/0! | BI10: =IF('Entrada e Saida'!$H$11="TRADING",IF('Entrada e Saida'!$H$12="REAL",AS10/D10,0),AM10/D10) -> #DIV/0! | BJ10: =IF('Entrada e Saida'!$H$11="TRADING",AT10/D10,AO10/D10) -> #DIV/0! | BK10: =BF10-SUM(BG10:BJ10) -> #DIV/0! | BL10: =IF(O10>0,IFERROR(IF('Entrada e Saida'!$H$11="DIRETA",0,(IF('Entrada e Saida'!$H$14="P.JURIDICA",(BD10*(1+O10)*N10)-((BD10/(1+M10))*'Entrada e Saida'!$G$65),((Produtos!N10-'Entrada e Saida'!$G$65)*Produtos!BD10)))),0),0) -> 0 | BM10: =BF10+BL10 -> #DIV/0!
B11: =VLOOKUP(A11,'Master Modelo'!A:I,7,FALSE) -> #N/A | C11: =VLOOKUP(A11,'Master Modelo'!A:I,2,FALSE) -> #N/A | E11: =IFERROR(VLOOKUP(A11,'Master Modelo'!A:I,9,FALSE),0) -> 0 | F11: =IFERROR(VLOOKUP(A11,'Master Modelo'!A:I,8,FALSE),0) -> 0 | G11: =IFERROR(VLOOKUP(A11,'Master Modelo'!A:K,11,FALSE),0) -> 0 | H11: =(D11*E11)/(D11*F11) -> #DIV/0! | I11: =IFERROR(VLOOKUP(A11,'Master Modelo'!A:I,3,FALSE),0) -> 0 | J11: =IFERROR(VLOOKUP(A11,'Master Modelo'!A:I,5,FALSE),0) -> 0 | K11: =IFERROR(VLOOKUP(A11,'Master Modelo'!A:I,6,FALSE),0) -> 0 | L11: =VLOOKUP(A11,'Master Modelo'!A:J,10,FALSE) -> #N/A | M11: =IFERROR(VLOOKUP(A11,'Master Modelo'!A:I,4,FALSE),0) -> 0 | P11: =D11*F11 -> 0 | Q11: =D11*G11 -> 0 | R11: =D11*E11*'Entrada e Saida'!$K$8 -> 0 | S11: ='Entrada e Saida'!$H$21*'Entrada e Saida'!$K$8*(P11/(SUM(P:P))) -> #DIV/0! | T11: ='Entrada e Saida'!$H$21*'Entrada e Saida'!$K$8*(Q11/(SUM(Q:Q))) -> #DIV/0! | U11: ='Entrada e Saida'!$H$22*(P11/(SUM(P:P))) -> #DIV/0! | V11: ='Entrada e Saida'!$H$22*(Q11/(SUM(Q:Q))) -> #DIV/0! | W11: =R11+S11+U11 -> #DIV/0! | X11: ='Entrada e Saida'!$H$26*(IF('Entrada e Saida'!$H$15="PESO",(P11/(SUM(P:P))),(Q11/(SUM(Q:Q))))) -> #DIV/0! | Y11: ='Entrada e Saida'!$H$27*(IF('Entrada e Saida'!$H$15="PESO",(P11/(SUM(P:P))),(Q11/(SUM(Q:Q))))) -> #DIV/0! | Z11: ='Entrada e Saida'!$H$28*(IF('Entrada e Saida'!$H$15="PESO",(P11/(SUM(P:P))),(Q11/(SUM(Q:Q))))) -> #DIV/0! | AA11: =X11+Y11+Z11 -> #DIV/0! | AB11: =W11*I11 -> #DIV/0! | AC11: =W11*J11 -> #DIV/0! | AD11: =W11*K11 -> #DIV/0! | AE11: =(W11+AB11)*M11 -> #DIV/0! | AF11: =IFERROR(D11*F11*L11*'Entrada e Saida'!$K$8,0) -> 0 | AG11: =((W11+AA11+AB11+AC11+AD11+AE11+AF11)/(1-'Entrada e Saida'!$G$65))*'Entrada e Saida'!$I$66 -> #DIV/0! | AH11: =SUM(AB11:AG11) -> #DIV/0! | AI11: ='Entrada e Saida'!$K$51*(IF('Entrada e Saida'!$H$15="PESO",(P11/(SUM(P:P))),(Q11/(SUM(Q:Q))))) -> #DIV/0! | AJ11: =(('Entrada e Saida'!$K$10-'Entrada e Saida'!$K$8)*E11*D11) -> 0 | AK11: =IF('Entrada e Saida'!$H$15="PESO",W11+AA11+AH11+AI11+AJ11,W11+AA11+AH11+AI11+AJ11-S11+T11-U11+V11) -> #DIV/0! | AL11: =IF('Entrada e Saida'!$H$12="REAL",AC11,0) -> #DIV/0! | AM11: =IF('Entrada e Saida'!$H$12="REAL",AD11,0) -> #DIV/0! | AN11: =IF('Entrada e Saida'!$H$13= "NÃO",AE11,0) -> #DIV/0! | AO11: =AG11 -> #DIV/0! | AP11: =AK11-SUM(AL11:AO11) -> #DIV/0! | AQ11: =IF('Entrada e Saida'!$H$11="TRADING",AU11*'Custo Resumido'!D11,0) -> #DIV/0! | AR11: =IF('Entrada e Saida'!$H$11="TRADING",AU11*'Entrada e Saida'!$G$63,0) -> #DIV/0! | AS11: =IF('Entrada e Saida'!$H$11="TRADING",AU11*'Entrada e Saida'!$G$64,0) -> #DIV/0! | AT11: =IF('Entrada e Saida'!$H$11="TRADING",AU11*'Entrada e Saida'!$G$65,0) -> #DIV/0! | AU11: =IF('Entrada e Saida'!$H$11="TRADING",AP11/(1-(SUM('Entrada e Saida'!$G$63:$G$65)+'Custo Resumido'!D11)),0) -> #DIV/0! | AV11: =IF('Entrada e Saida'!$H$13="NÃO",AU11*M11,0) -> #DIV/0! | AW11: =AU11+AV11 -> #DIV/0! | AX11: ='Entrada e Saida'!$G$74*AU11 -> #DIV/0! | AY11: =AW11-AX11 -> #DIV/0! | AZ11: =AQ11+('Entrada e Saida'!$G$65-'Entrada e Saida'!$I$65)*AU11-AX11 -> #DIV/0! | BA11: =IF('Entrada e Saida'!$H$12="REAL",AZ11*'Entrada e Saida'!$G$81,AU11*'Entrada e Saida'!$G$81) -> #DIV/0! | BB11: =IF('Entrada e Saida'!$H$12="REAL",AZ11*'Entrada e Saida'!$G$82,AU11*'Entrada e Saida'!$G$82) -> #DIV/0! | BC11: =AZ11-BA11-BB11 -> #DIV/0! | BD11: =IF('Entrada e Saida'!$H$11="TRADING",AW11/D11,AK11/D11) -> #DIV/0! | BE11: =AX11/D11 -> #DIV/0! | BF11: =BD11-BE11 -> #DIV/0! | BG11: =IF('Entrada e Saida'!$H$11="TRADING",AV11/D11,AN11/D11) -> #DIV/0! | BH11: =IF('Entrada e Saida'!$H$11="TRADING",IF('Entrada e Saida'!$H$12="REAL",AR11/D11,0),AL11/D11) -> #DIV/0! | BI11: =IF('Entrada e Saida'!$H$11="TRADING",IF('Entrada e Saida'!$H$12="REAL",AS11/D11,0),AM11/D11) -> #DIV/0! | BJ11: =IF('Entrada e Saida'!$H$11="TRADING",AT11/D11,AO11/D11) -> #DIV/0! | BK11: =BF11-SUM(BG11:BJ11) -> #DIV/0! | BL11: =IF(O11>0,IFERROR(IF('Entrada e Saida'!$H$11="DIRETA",0,(IF('Entrada e Saida'!$H$14="P.JURIDICA",(BD11*(1+O11)*N11)-((BD11/(1+M11))*'Entrada e Saida'!$G$65),((Produtos!N11-'Entrada e Saida'!$G$65)*Produtos!BD11)))),0),0) -> 0 | BM11: =BF11+BL11 -> #DIV/0!
B12: =VLOOKUP(A12,'Master Modelo'!A:I,7,FALSE) -> #N/A | C12: =VLOOKUP(A12,'Master Modelo'!A:I,2,FALSE) -> #N/A | E12: =IFERROR(VLOOKUP(A12,'Master Modelo'!A:I,9,FALSE),0) -> 0 | F12: =IFERROR(VLOOKUP(A12,'Master Modelo'!A:I,8,FALSE),0) -> 0 | G12: =IFERROR(VLOOKUP(A12,'Master Modelo'!A:K,11,FALSE),0) -> 0 | H12: =(D12*E12)/(D12*F12) -> #DIV/0! | I12: =IFERROR(VLOOKUP(A12,'Master Modelo'!A:I,3,FALSE),0) -> 0 | J12: =IFERROR(VLOOKUP(A12,'Master Modelo'!A:I,5,FALSE),0) -> 0 | K12: =IFERROR(VLOOKUP(A12,'Master Modelo'!A:I,6,FALSE),0) -> 0 | L12: =VLOOKUP(A12,'Master Modelo'!A:J,10,FALSE) -> #N/A | M12: =IFERROR(VLOOKUP(A12,'Master Modelo'!A:I,4,FALSE),0) -> 0 | P12: =D12*F12 -> 0 | Q12: =D12*G12 -> 0 | R12: =D12*E12*'Entrada e Saida'!$K$8 -> 0 | S12: ='Entrada e Saida'!$H$21*'Entrada e Saida'!$K$8*(P12/(SUM(P:P))) -> #DIV/0! | T12: ='Entrada e Saida'!$H$21*'Entrada e Saida'!$K$8*(Q12/(SUM(Q:Q))) -> #DIV/0! | U12: ='Entrada e Saida'!$H$22*(P12/(SUM(P:P))) -> #DIV/0! | V12: ='Entrada e Saida'!$H$22*(Q12/(SUM(Q:Q))) -> #DIV/0! | W12: =R12+S12+U12 -> #DIV/0! | X12: ='Entrada e Saida'!$H$26*(IF('Entrada e Saida'!$H$15="PESO",(P12/(SUM(P:P))),(Q12/(SUM(Q:Q))))) -> #DIV/0! | Y12: ='Entrada e Saida'!$H$27*(IF('Entrada e Saida'!$H$15="PESO",(P12/(SUM(P:P))),(Q12/(SUM(Q:Q))))) -> #DIV/0! | Z12: ='Entrada e Saida'!$H$28*(IF('Entrada e Saida'!$H$15="PESO",(P12/(SUM(P:P))),(Q12/(SUM(Q:Q))))) -> #DIV/0! | AA12: =X12+Y12+Z12 -> #DIV/0! | AB12: =W12*I12 -> #DIV/0! | AC12: =W12*J12 -> #DIV/0! | AD12: =W12*K12 -> #DIV/0! | AE12: =(W12+AB12)*M12 -> #DIV/0! | AF12: =IFERROR(D12*F12*L12*'Entrada e Saida'!$K$8,0) -> 0 | AG12: =((W12+AA12+AB12+AC12+AD12+AE12+AF12)/(1-'Entrada e Saida'!$G$65))*'Entrada e Saida'!$I$66 -> #DIV/0! | AH12: =SUM(AB12:AG12) -> #DIV/0! | AI12: ='Entrada e Saida'!$K$51*(IF('Entrada e Saida'!$H$15="PESO",(P12/(SUM(P:P))),(Q12/(SUM(Q:Q))))) -> #DIV/0! | AJ12: =(('Entrada e Saida'!$K$10-'Entrada e Saida'!$K$8)*E12*D12) -> 0 | AK12: =IF('Entrada e Saida'!$H$15="PESO",W12+AA12+AH12+AI12+AJ12,W12+AA12+AH12+AI12+AJ12-S12+T12-U12+V12) -> #DIV/0! | AL12: =IF('Entrada e Saida'!$H$12="REAL",AC12,0) -> #DIV/0! | AM12: =IF('Entrada e Saida'!$H$12="REAL",AD12,0) -> #DIV/0! | AN12: =IF('Entrada e Saida'!$H$13= "NÃO",AE12,0) -> #DIV/0! | AO12: =AG12 -> #DIV/0! | AP12: =AK12-SUM(AL12:AO12) -> #DIV/0! | AQ12: =IF('Entrada e Saida'!$H$11="TRADING",AU12*'Custo Resumido'!D12,0) -> #DIV/0! | AR12: =IF('Entrada e Saida'!$H$11="TRADING",AU12*'Entrada e Saida'!$G$63,0) -> #DIV/0! | AS12: =IF('Entrada e Saida'!$H$11="TRADING",AU12*'Entrada e Saida'!$G$64,0) -> #DIV/0! | AT12: =IF('Entrada e Saida'!$H$11="TRADING",AU12*'Entrada e Saida'!$G$65,0) -> #DIV/0! | AU12: =IF('Entrada e Saida'!$H$11="TRADING",AP12/(1-(SUM('Entrada e Saida'!$G$63:$G$65)+'Custo Resumido'!D12)),0) -> #DIV/0! | AV12: =IF('Entrada e Saida'!$H$13="NÃO",AU12*M12,0) -> #DIV/0! | AW12: =AU12+AV12 -> #DIV/0! | AX12: ='Entrada e Saida'!$G$74*AU12 -> #DIV/0! | AY12: =AW12-AX12 -> #DIV/0! | AZ12: =AQ12+('Entrada e Saida'!$G$65-'Entrada e Saida'!$I$65)*AU12-AX12 -> #DIV/0! | BA12: =IF('Entrada e Saida'!$H$12="REAL",AZ12*'Entrada e Saida'!$G$81,AU12*'Entrada e Saida'!$G$81) -> #DIV/0! | BB12: =IF('Entrada e Saida'!$H$12="REAL",AZ12*'Entrada e Saida'!$G$82,AU12*'Entrada e Saida'!$G$82) -> #DIV/0! | BC12: =AZ12-BA12-BB12 -> #DIV/0! | BD12: =IF('Entrada e Saida'!$H$11="TRADING",AW12/D12,AK12/D12) -> #DIV/0! | BE12: =AX12/D12 -> #DIV/0! | BF12: =BD12-BE12 -> #DIV/0! | BG12: =IF('Entrada e Saida'!$H$11="TRADING",AV12/D12,AN12/D12) -> #DIV/0! | BH12: =IF('Entrada e Saida'!$H$11="TRADING",IF('Entrada e Saida'!$H$12="REAL",AR12/D12,0),AL12/D12) -> #DIV/0! | BI12: =IF('Entrada e Saida'!$H$11="TRADING",IF('Entrada e Saida'!$H$12="REAL",AS12/D12,0),AM12/D12) -> #DIV/0! | BJ12: =IF('Entrada e Saida'!$H$11="TRADING",AT12/D12,AO12/D12) -> #DIV/0! | BK12: =BF12-SUM(BG12:BJ12) -> #DIV/0! | BL12: =IF(O12>0,IFERROR(IF('Entrada e Saida'!$H$11="DIRETA",0,(IF('Entrada e Saida'!$H$14="P.JURIDICA",(BD12*(1+O12)*N12)-((BD12/(1+M12))*'Entrada e Saida'!$G$65),((Produtos!N12-'Entrada e Saida'!$G$65)*Produtos!BD12)))),0),0) -> 0 | BM12: =BF12+BL12 -> #DIV/0!
B13: =VLOOKUP(A13,'Master Modelo'!A:I,7,FALSE) -> #N/A | C13: =VLOOKUP(A13,'Master Modelo'!A:I,2,FALSE) -> #N/A | E13: =IFERROR(VLOOKUP(A13,'Master Modelo'!A:I,9,FALSE),0) -> 0 | F13: =IFERROR(VLOOKUP(A13,'Master Modelo'!A:I,8,FALSE),0) -> 0 | G13: =IFERROR(VLOOKUP(A13,'Master Modelo'!A:K,11,FALSE),0) -> 0 | H13: =(D13*E13)/(D13*F13) -> #DIV/0! | I13: =IFERROR(VLOOKUP(A13,'Master Modelo'!A:I,3,FALSE),0) -> 0 | J13: =IFERROR(VLOOKUP(A13,'Master Modelo'!A:I,5,FALSE),0) -> 0 | K13: =IFERROR(VLOOKUP(A13,'Master Modelo'!A:I,6,FALSE),0) -> 0 | L13: =VLOOKUP(A13,'Master Modelo'!A:J,10,FALSE) -> #N/A | M13: =IFERROR(VLOOKUP(A13,'Master Modelo'!A:I,4,FALSE),0) -> 0 | P13: =D13*F13 -> 0 | Q13: =D13*G13 -> 0 | R13: =D13*E13*'Entrada e Saida'!$K$8 -> 0 | S13: ='Entrada e Saida'!$H$21*'Entrada e Saida'!$K$8*(P13/(SUM(P:P))) -> #DIV/0! | T13: ='Entrada e Saida'!$H$21*'Entrada e Saida'!$K$8*(Q13/(SUM(Q:Q))) -> #DIV/0! | U13: ='Entrada e Saida'!$H$22*(P13/(SUM(P:P))) -> #DIV/0! | V13: ='Entrada e Saida'!$H$22*(Q13/(SUM(Q:Q))) -> #DIV/0! | W13: =R13+S13+U13 -> #DIV/0! | X13: ='Entrada e Saida'!$H$26*(IF('Entrada e Saida'!$H$15="PESO",(P13/(SUM(P:P))),(Q13/(SUM(Q:Q))))) -> #DIV/0! | Y13: ='Entrada e Saida'!$H$27*(IF('Entrada e Saida'!$H$15="PESO",(P13/(SUM(P:P))),(Q13/(SUM(Q:Q))))) -> #DIV/0! | Z13: ='Entrada e Saida'!$H$28*(IF('Entrada e Saida'!$H$15="PESO",(P13/(SUM(P:P))),(Q13/(SUM(Q:Q))))) -> #DIV/0! | AA13: =X13+Y13+Z13 -> #DIV/0! | AB13: =W13*I13 -> #DIV/0! | AC13: =W13*J13 -> #DIV/0! | AD13: =W13*K13 -> #DIV/0! | AE13: =(W13+AB13)*M13 -> #DIV/0! | AF13: =IFERROR(D13*F13*L13*'Entrada e Saida'!$K$8,0) -> 0 | AG13: =((W13+AA13+AB13+AC13+AD13+AE13+AF13)/(1-'Entrada e Saida'!$G$65))*'Entrada e Saida'!$I$66 -> #DIV/0! | AH13: =SUM(AB13:AG13) -> #DIV/0! | AI13: ='Entrada e Saida'!$K$51*(IF('Entrada e Saida'!$H$15="PESO",(P13/(SUM(P:P))),(Q13/(SUM(Q:Q))))) -> #DIV/0! | AJ13: =(('Entrada e Saida'!$K$10-'Entrada e Saida'!$K$8)*E13*D13) -> 0 | AK13: =IF('Entrada e Saida'!$H$15="PESO",W13+AA13+AH13+AI13+AJ13,W13+AA13+AH13+AI13+AJ13-S13+T13-U13+V13) -> #DIV/0! | AL13: =IF('Entrada e Saida'!$H$12="REAL",AC13,0) -> #DIV/0! | AM13: =IF('Entrada e Saida'!$H$12="REAL",AD13,0) -> #DIV/0! | AN13: =IF('Entrada e Saida'!$H$13= "NÃO",AE13,0) -> #DIV/0! | AO13: =AG13 -> #DIV/0! | AP13: =AK13-SUM(AL13:AO13) -> #DIV/0! | AQ13: =IF('Entrada e Saida'!$H$11="TRADING",AU13*'Custo Resumido'!D13,0) -> #DIV/0! | AR13: =IF('Entrada e Saida'!$H$11="TRADING",AU13*'Entrada e Saida'!$G$63,0) -> #DIV/0! | AS13: =IF('Entrada e Saida'!$H$11="TRADING",AU13*'Entrada e Saida'!$G$64,0) -> #DIV/0! | AT13: =IF('Entrada e Saida'!$H$11="TRADING",AU13*'Entrada e Saida'!$G$65,0) -> #DIV/0! | AU13: =IF('Entrada e Saida'!$H$11="TRADING",AP13/(1-(SUM('Entrada e Saida'!$G$63:$G$65)+'Custo Resumido'!D13)),0) -> #DIV/0! | AV13: =IF('Entrada e Saida'!$H$13="NÃO",AU13*M13,0) -> #DIV/0! | AW13: =AU13+AV13 -> #DIV/0! | AX13: ='Entrada e Saida'!$G$74*AU13 -> #DIV/0! | AY13: =AW13-AX13 -> #DIV/0! | AZ13: =AQ13+('Entrada e Saida'!$G$65-'Entrada e Saida'!$I$65)*AU13-AX13 -> #DIV/0! | BA13: =IF('Entrada e Saida'!$H$12="REAL",AZ13*'Entrada e Saida'!$G$81,AU13*'Entrada e Saida'!$G$81) -> #DIV/0! | BB13: =IF('Entrada e Saida'!$H$12="REAL",AZ13*'Entrada e Saida'!$G$82,AU13*'Entrada e Saida'!$G$82) -> #DIV/0! | BC13: =AZ13-BA13-BB13 -> #DIV/0! | BD13: =IF('Entrada e Saida'!$H$11="TRADING",AW13/D13,AK13/D13) -> #DIV/0! | BE13: =AX13/D13 -> #DIV/0! | BF13: =BD13-BE13 -> #DIV/0! | BG13: =IF('Entrada e Saida'!$H$11="TRADING",AV13/D13,AN13/D13) -> #DIV/0! | BH13: =IF('Entrada e Saida'!$H$11="TRADING",IF('Entrada e Saida'!$H$12="REAL",AR13/D13,0),AL13/D13) -> #DIV/0! | BI13: =IF('Entrada e Saida'!$H$11="TRADING",IF('Entrada e Saida'!$H$12="REAL",AS13/D13,0),AM13/D13) -> #DIV/0! | BJ13: =IF('Entrada e Saida'!$H$11="TRADING",AT13/D13,AO13/D13) -> #DIV/0! | BK13: =BF13-SUM(BG13:BJ13) -> #DIV/0! | BL13: =IF(O13>0,IFERROR(IF('Entrada e Saida'!$H$11="DIRETA",0,(IF('Entrada e Saida'!$H$14="P.JURIDICA",(BD13*(1+O13)*N13)-((BD13/(1+M13))*'Entrada e Saida'!$G$65),((Produtos!N13-'Entrada e Saida'!$G$65)*Produtos!BD13)))),0),0) -> 0 | BM13: =BF13+BL13 -> #DIV/0!
B14: =VLOOKUP(A14,'Master Modelo'!A:I,7,FALSE) -> #N/A | C14: =VLOOKUP(A14,'Master Modelo'!A:I,2,FALSE) -> #N/A | E14: =IFERROR(VLOOKUP(A14,'Master Modelo'!A:I,9,FALSE),0) -> 0 | F14: =IFERROR(VLOOKUP(A14,'Master Modelo'!A:I,8,FALSE),0) -> 0 | G14: =IFERROR(VLOOKUP(A14,'Master Modelo'!A:K,11,FALSE),0) -> 0 | H14: =(D14*E14)/(D14*F14) -> #DIV/0! | I14: =IFERROR(VLOOKUP(A14,'Master Modelo'!A:I,3,FALSE),0) -> 0 | J14: =IFERROR(VLOOKUP(A14,'Master Modelo'!A:I,5,FALSE),0) -> 0 | K14: =IFERROR(VLOOKUP(A14,'Master Modelo'!A:I,6,FALSE),0) -> 0 | L14: =VLOOKUP(A14,'Master Modelo'!A:J,10,FALSE) -> #N/A | M14: =IFERROR(VLOOKUP(A14,'Master Modelo'!A:I,4,FALSE),0) -> 0 | P14: =D14*F14 -> 0 | Q14: =D14*G14 -> 0 | R14: =D14*E14*'Entrada e Saida'!$K$8 -> 0 | S14: ='Entrada e Saida'!$H$21*'Entrada e Saida'!$K$8*(P14/(SUM(P:P))) -> #DIV/0! | T14: ='Entrada e Saida'!$H$21*'Entrada e Saida'!$K$8*(Q14/(SUM(Q:Q))) -> #DIV/0! | U14: ='Entrada e Saida'!$H$22*(P14/(SUM(P:P))) -> #DIV/0! | V14: ='Entrada e Saida'!$H$22*(Q14/(SUM(Q:Q))) -> #DIV/0! | W14: =R14+S14+U14 -> #DIV/0! | X14: ='Entrada e Saida'!$H$26*(IF('Entrada e Saida'!$H$15="PESO",(P14/(SUM(P:P))),(Q14/(SUM(Q:Q))))) -> #DIV/0! | Y14: ='Entrada e Saida'!$H$27*(IF('Entrada e Saida'!$H$15="PESO",(P14/(SUM(P:P))),(Q14/(SUM(Q:Q))))) -> #DIV/0! | Z14: ='Entrada e Saida'!$H$28*(IF('Entrada e Saida'!$H$15="PESO",(P14/(SUM(P:P))),(Q14/(SUM(Q:Q))))) -> #DIV/0! | AA14: =X14+Y14+Z14 -> #DIV/0! | AB14: =W14*I14 -> #DIV/0! | AC14: =W14*J14 -> #DIV/0! | AD14: =W14*K14 -> #DIV/0! | AE14: =(W14+AB14)*M14 -> #DIV/0! | AF14: =IFERROR(D14*F14*L14*'Entrada e Saida'!$K$8,0) -> 0 | AG14: =((W14+AA14+AB14+AC14+AD14+AE14+AF14)/(1-'Entrada e Saida'!$G$65))*'Entrada e Saida'!$I$66 -> #DIV/0! | AH14: =SUM(AB14:AG14) -> #DIV/0! | AI14: ='Entrada e Saida'!$K$51*(IF('Entrada e Saida'!$H$15="PESO",(P14/(SUM(P:P))),(Q14/(SUM(Q:Q))))) -> #DIV/0! | AJ14: =(('Entrada e Saida'!$K$10-'Entrada e Saida'!$K$8)*E14*D14) -> 0 | AK14: =IF('Entrada e Saida'!$H$15="PESO",W14+AA14+AH14+AI14+AJ14,W14+AA14+AH14+AI14+AJ14-S14+T14-U14+V14) -> #DIV/0! | AL14: =IF('Entrada e Saida'!$H$12="REAL",AC14,0) -> #DIV/0! | AM14: =IF('Entrada e Saida'!$H$12="REAL",AD14,0) -> #DIV/0! | AN14: =IF('Entrada e Saida'!$H$13= "NÃO",AE14,0) -> #DIV/0! | AO14: =AG14 -> #DIV/0! | AP14: =AK14-SUM(AL14:AO14) -> #DIV/0! | AQ14: =IF('Entrada e Saida'!$H$11="TRADING",AU14*'Custo Resumido'!D14,0) -> #DIV/0! | AR14: =IF('Entrada e Saida'!$H$11="TRADING",AU14*'Entrada e Saida'!$G$63,0) -> #DIV/0! | AS14: =IF('Entrada e Saida'!$H$11="TRADING",AU14*'Entrada e Saida'!$G$64,0) -> #DIV/0! | AT14: =IF('Entrada e Saida'!$H$11="TRADING",AU14*'Entrada e Saida'!$G$65,0) -> #DIV/0! | AU14: =IF('Entrada e Saida'!$H$11="TRADING",AP14/(1-(SUM('Entrada e Saida'!$G$63:$G$65)+'Custo Resumido'!D14)),0) -> #DIV/0! | AV14: =IF('Entrada e Saida'!$H$13="NÃO",AU14*M14,0) -> #DIV/0! | AW14: =AU14+AV14 -> #DIV/0! | AX14: ='Entrada e Saida'!$G$74*AU14 -> #DIV/0! | AY14: =AW14-AX14 -> #DIV/0! | AZ14: =AQ14+('Entrada e Saida'!$G$65-'Entrada e Saida'!$I$65)*AU14-AX14 -> #DIV/0! | BA14: =IF('Entrada e Saida'!$H$12="REAL",AZ14*'Entrada e Saida'!$G$81,AU14*'Entrada e Saida'!$G$81) -> #DIV/0! | BB14: =IF('Entrada e Saida'!$H$12="REAL",AZ14*'Entrada e Saida'!$G$82,AU14*'Entrada e Saida'!$G$82) -> #DIV/0! | BC14: =AZ14-BA14-BB14 -> #DIV/0! | BD14: =IF('Entrada e Saida'!$H$11="TRADING",AW14/D14,AK14/D14) -> #DIV/0! | BE14: =AX14/D14 -> #DIV/0! | BF14: =BD14-BE14 -> #DIV/0! | BG14: =IF('Entrada e Saida'!$H$11="TRADING",AV14/D14,AN14/D14) -> #DIV/0! | BH14: =IF('Entrada e Saida'!$H$11="TRADING",IF('Entrada e Saida'!$H$12="REAL",AR14/D14,0),AL14/D14) -> #DIV/0! | BI14: =IF('Entrada e Saida'!$H$11="TRADING",IF('Entrada e Saida'!$H$12="REAL",AS14/D14,0),AM14/D14) -> #DIV/0! | BJ14: =IF('Entrada e Saida'!$H$11="TRADING",AT14/D14,AO14/D14) -> #DIV/0! | BK14: =BF14-SUM(BG14:BJ14) -> #DIV/0! | BL14: =IF(O14>0,IFERROR(IF('Entrada e Saida'!$H$11="DIRETA",0,(IF('Entrada e Saida'!$H$14="P.JURIDICA",(BD14*(1+O14)*N14)-((BD14/(1+M14))*'Entrada e Saida'!$G$65),((Produtos!N14-'Entrada e Saida'!$G$65)*Produtos!BD14)))),0),0) -> 0 | BM14: =BF14+BL14 -> #DIV/0!
... B96: =VLOOKUP(A96,'Master Modelo'!A:I,7,FALSE) -> #N/A | C96: =VLOOKUP(A96,'Master Modelo'!A:I,2,FALSE) -> #N/A | E96: =IFERROR(VLOOKUP(A96,'Master Modelo'!A:I,9,FALSE),0) -> 0 | F96: =IFERROR(VLOOKUP(A96,'Master Modelo'!A:I,8,FALSE),0) -> 0 | G96: =IFERROR(VLOOKUP(A96,'Master Modelo'!A:K,11,FALSE),0) -> 0 | H96: =(D96*E96)/(D96*F96) -> #DIV/0! | I96: =IFERROR(VLOOKUP(A96,'Master Modelo'!A:I,3,FALSE),0) -> 0 | J96: =IFERROR(VLOOKUP(A96,'Master Modelo'!A:I,5,FALSE),0) -> 0 | K96: =IFERROR(VLOOKUP(A96,'Master Modelo'!A:I,6,FALSE),0) -> 0 | L96: =VLOOKUP(A96,'Master Modelo'!A:J,10,FALSE) -> #N/A | M96: =IFERROR(VLOOKUP(A96,'Master Modelo'!A:I,4,FALSE),0) -> 0 | P96: =D96*F96 -> 0 | Q96: =D96*G96 -> 0 | R96: =D96*E96*'Entrada e Saida'!$K$8 -> 0 | S96: ='Entrada e Saida'!$H$21*'Entrada e Saida'!$K$8*(P96/(SUM(P:P))) -> #DIV/0! | T96: ='Entrada e Saida'!$H$21*'Entrada e Saida'!$K$8*(Q96/(SUM(Q:Q))) -> #DIV/0! | U96: ='Entrada e Saida'!$H$22*(P96/(SUM(P:P))) -> #DIV/0! | V96: ='Entrada e Saida'!$H$22*(Q96/(SUM(Q:Q))) -> #DIV/0! | W96: =R96+S96+U96 -> #DIV/0! | X96: ='Entrada e Saida'!$H$26*(IF('Entrada e Saida'!$H$15="PESO",(P96/(SUM(P:P))),(Q96/(SUM(Q:Q))))) -> #DIV/0! | Y96: ='Entrada e Saida'!$H$27*(IF('Entrada e Saida'!$H$15="PESO",(P96/(SUM(P:P))),(Q96/(SUM(Q:Q))))) -> #DIV/0! | Z96: ='Entrada e Saida'!$H$28*(IF('Entrada e Saida'!$H$15="PESO",(P96/(SUM(P:P))),(Q96/(SUM(Q:Q))))) -> #DIV/0! | AA96: =X96+Y96+Z96 -> #DIV/0! | AB96: =W96*I96 -> #DIV/0! | AC96: =W96*J96 -> #DIV/0! | AD96: =W96*K96 -> #DIV/0! | AE96: =(W96+AB96)*M96 -> #DIV/0! | AF96: =IFERROR(D96*F96*L96*'Entrada e Saida'!$K$8,0) -> 0 | AG96: =((W96+AA96+AB96+AC96+AD96+AE96+AF96)/(1-'Entrada e Saida'!$G$65))*'Entrada e Saida'!$I$66 -> #DIV/0! | AH96: =SUM(AB96:AG96) -> #DIV/0! | AI96: ='Entrada e Saida'!$K$51*(IF('Entrada e Saida'!$H$15="PESO",(P96/(SUM(P:P))),(Q96/(SUM(Q:Q))))) -> #DIV/0! | AJ96: =(('Entrada e Saida'!$K$10-'Entrada e Saida'!$K$8)*E96*D96) -> 0 | AK96: =IF('Entrada e Saida'!$H$15="PESO",W96+AA96+AH96+AI96+AJ96,W96+AA96+AH96+AI96+AJ96-S96+T96-U96+V96) -> #DIV/0! | AL96: =IF('Entrada e Saida'!$H$12="REAL",AC96,0) -> #DIV/0! | AM96: =IF('Entrada e Saida'!$H$12="REAL",AD96,0) -> #DIV/0! | AN96: =IF('Entrada e Saida'!$H$13= "NÃO",AE96,0) -> #DIV/0! | AO96: =AG96 -> #DIV/0! | AP96: =AK96-SUM(AL96:AO96) -> #DIV/0! | AQ96: =IF('Entrada e Saida'!$H$11="TRADING",AU96*'Custo Resumido'!D96,0) -> #DIV/0! | AR96: =IF('Entrada e Saida'!$H$11="TRADING",AU96*'Entrada e Saida'!$G$63,0) -> #DIV/0! | AS96: =IF('Entrada e Saida'!$H$11="TRADING",AU96*'Entrada e Saida'!$G$64,0) -> #DIV/0! | AT96: =IF('Entrada e Saida'!$H$11="TRADING",AU96*'Entrada e Saida'!$G$65,0) -> #DIV/0! | AU96: =IF('Entrada e Saida'!$H$11="TRADING",AP96/(1-(SUM('Entrada e Saida'!$G$63:$G$65)+'Custo Resumido'!D96)),0) -> #DIV/0! | AV96: =IF('Entrada e Saida'!$H$13="NÃO",AU96*M96,0) -> #DIV/0! | AW96: =AU96+AV96 -> #DIV/0! | AX96: ='Entrada e Saida'!$G$74*AU96 -> #DIV/0! | AY96: =AW96-AX96 -> #DIV/0! | AZ96: =AQ96+('Entrada e Saida'!$G$65-'Entrada e Saida'!$I$65)*AU96-AX96 -> #DIV/0! | BA96: =IF('Entrada e Saida'!$H$12="REAL",AZ96*'Entrada e Saida'!$G$81,AU96*'Entrada e Saida'!$G$81) -> #DIV/0! | BB96: =IF('Entrada e Saida'!$H$12="REAL",AZ96*'Entrada e Saida'!$G$82,AU96*'Entrada e Saida'!$G$82) -> #DIV/0! | BC96: =AZ96-BA96-BB96 -> #DIV/0! | BD96: =IF('Entrada e Saida'!$H$11="TRADING",AW96/D96,AK96/D96) -> #DIV/0! | BE96: =AX96/D96 -> #DIV/0! | BF96: =BD96-BE96 -> #DIV/0! | BG96: =IF('Entrada e Saida'!$H$11="TRADING",AV96/D96,AN96/D96) -> #DIV/0! | BH96: =IF('Entrada e Saida'!$H$11="TRADING",IF('Entrada e Saida'!$H$12="REAL",AR96/D96,0),AL96/D96) -> #DIV/0! | BI96: =IF('Entrada e Saida'!$H$11="TRADING",IF('Entrada e Saida'!$H$12="REAL",AS96/D96,0),AM96/D96) -> #DIV/0! | BJ96: =IF('Entrada e Saida'!$H$11="TRADING",AT96/D96,AO96/D96) -> #DIV/0! | BK96: =BF96-SUM(BG96:BJ96) -> #DIV/0! | BL96: =IF(O96>0,IFERROR(IF('Entrada e Saida'!$H$11="DIRETA",0,(IF('Entrada e Saida'!$H$14="P.JURIDICA",(BD96*(1+O96)*N96)-((BD96/(1+M96))*'Entrada e Saida'!$G$65),((Produtos!N96-'Entrada e Saida'!$G$65)*Produtos!BD96)))),0),0) -> 0 | BM96: =BF96+BL96 -> #DIV/0!
E97: =IFERROR(VLOOKUP(A97,'Master Modelo'!A:I,9,FALSE),0) -> 0 | F97: =IFERROR(VLOOKUP(A97,'Master Modelo'!A:I,8,FALSE),0) -> 0 | G97: =IFERROR(VLOOKUP(A97,'Master Modelo'!A:K,11,FALSE),0) -> 0 | H97: =(D97*E97)/(D97*F97) -> #DIV/0! | I97: =IFERROR(VLOOKUP(A97,'Master Modelo'!A:I,3,FALSE),0) -> 0 | J97: =IFERROR(VLOOKUP(A97,'Master Modelo'!A:I,5,FALSE),0) -> 0 | K97: =IFERROR(VLOOKUP(A97,'Master Modelo'!A:I,6,FALSE),0) -> 0 | L97: =VLOOKUP(A97,'Master Modelo'!A:J,10,FALSE) -> #N/A | M97: =IFERROR(VLOOKUP(A97,'Master Modelo'!A:I,4,FALSE),0) -> 0 | P97: =D97*F97 -> 0 | Q97: =D97*G97 -> 0 | R97: =D97*E97*'Entrada e Saida'!$K$8 -> 0 | S97: ='Entrada e Saida'!$H$21*'Entrada e Saida'!$K$8*(P97/(SUM(P:P))) -> #DIV/0! | T97: ='Entrada e Saida'!$H$21*'Entrada e Saida'!$K$8*(Q97/(SUM(Q:Q))) -> #DIV/0! | U97: ='Entrada e Saida'!$H$22*(P97/(SUM(P:P))) -> #DIV/0! | V97: ='Entrada e Saida'!$H$22*(Q97/(SUM(Q:Q))) -> #DIV/0! | W97: =R97+S97+U97 -> #DIV/0! | X97: ='Entrada e Saida'!$H$26*(IF('Entrada e Saida'!$H$15="PESO",(P97/(SUM(P:P))),(Q97/(SUM(Q:Q))))) -> #DIV/0! | Y97: ='Entrada e Saida'!$H$27*(IF('Entrada e Saida'!$H$15="PESO",(P97/(SUM(P:P))),(Q97/(SUM(Q:Q))))) -> #DIV/0! | Z97: ='Entrada e Saida'!$H$28*(IF('Entrada e Saida'!$H$15="PESO",(P97/(SUM(P:P))),(Q97/(SUM(Q:Q))))) -> #DIV/0! | AA97: =X97+Y97+Z97 -> #DIV/0! | AB97: =W97*I97 -> #DIV/0! | AC97: =W97*J97 -> #DIV/0! | AD97: =W97*K97 -> #DIV/0! | AE97: =(W97+AB97)*M97 -> #DIV/0! | AF97: =IFERROR(D97*F97*L97*'Entrada e Saida'!$K$8,0) -> 0 | AG97: =((W97+AA97+AB97+AC97+AD97+AE97+AF97)/(1-'Entrada e Saida'!$G$65))*'Entrada e Saida'!$I$66 -> #DIV/0! | AH97: =SUM(AB97:AG97) -> #DIV/0! | AI97: ='Entrada e Saida'!$K$51*(IF('Entrada e Saida'!$H$15="PESO",(P97/(SUM(P:P))),(Q97/(SUM(Q:Q))))) -> #DIV/0! | AJ97: =(('Entrada e Saida'!$K$10-'Entrada e Saida'!$K$8)*E97*D97) -> 0 | AK97: =IF('Entrada e Saida'!$H$15="PESO",W97+AA97+AH97+AI97+AJ97,W97+AA97+AH97+AI97+AJ97-S97+T97-U97+V97) -> #DIV/0! | AL97: =IF('Entrada e Saida'!$H$12="REAL",AC97,0) -> #DIV/0! | AM97: =IF('Entrada e Saida'!$H$12="REAL",AD97,0) -> #DIV/0! | AN97: =IF('Entrada e Saida'!$H$13= "NÃO",AE97,0) -> #DIV/0! | AO97: =AG97 -> #DIV/0! | AP97: =AK97-SUM(AL97:AO97) -> #DIV/0! | AQ97: =IF('Entrada e Saida'!$H$11="TRADING",AU97*'Custo Resumido'!D97,0) -> #DIV/0! | AR97: =IF('Entrada e Saida'!$H$11="TRADING",AU97*'Entrada e Saida'!$G$63,0) -> #DIV/0! | AS97: =IF('Entrada e Saida'!$H$11="TRADING",AU97*'Entrada e Saida'!$G$64,0) -> #DIV/0! | AT97: =IF('Entrada e Saida'!$H$11="TRADING",AU97*'Entrada e Saida'!$G$65,0) -> #DIV/0! | AU97: =IF('Entrada e Saida'!$H$11="TRADING",AP97/(1-(SUM('Entrada e Saida'!$G$63:$G$65)+'Custo Resumido'!D97)),0) -> #DIV/0! | AV97: =IF('Entrada e Saida'!$H$13="NÃO",AU97*M97,0) -> #DIV/0! | AW97: =AU97+AV97 -> #DIV/0! | AX97: ='Entrada e Saida'!$G$74*AU97 -> #DIV/0! | AY97: =AW97-AX97 -> #DIV/0! | AZ97: =AQ97+('Entrada e Saida'!$G$65-'Entrada e Saida'!$I$65)*AU97-AX97 -> #DIV/0! | BA97: =IF('Entrada e Saida'!$H$12="REAL",AZ97*'Entrada e Saida'!$G$81,AU97*'Entrada e Saida'!$G$81) -> #DIV/0! | BB97: =IF('Entrada e Saida'!$H$12="REAL",AZ97*'Entrada e Saida'!$G$82,AU97*'Entrada e Saida'!$G$82) -> #DIV/0! | BC97: =AZ97-BA97-BB97 -> #DIV/0! | BD97: =IF('Entrada e Saida'!$H$11="TRADING",AW97/D97,AK97/D97) -> #DIV/0! | BE97: =AX97/D97 -> #DIV/0! | BF97: =BD97-BE97 -> #DIV/0! | BG97: =IF('Entrada e Saida'!$H$11="TRADING",AV97/D97,AN97/D97) -> #DIV/0! | BH97: =IF('Entrada e Saida'!$H$11="TRADING",IF('Entrada e Saida'!$H$12="REAL",AR97/D97,0),AL97/D97) -> #DIV/0! | BI97: =IF('Entrada e Saida'!$H$11="TRADING",IF('Entrada e Saida'!$H$12="REAL",AS97/D97,0),AM97/D97) -> #DIV/0! | BJ97: =IF('Entrada e Saida'!$H$11="TRADING",AT97/D97,AO97/D97) -> #DIV/0! | BK97: =BF97-SUM(BG97:BJ97) -> #DIV/0! | BL97: =IF(O97>0,IFERROR(IF('Entrada e Saida'!$H$11="DIRETA",0,(IF('Entrada e Saida'!$H$14="P.JURIDICA",(BD97*(1+O97)*N97)-((BD97/(1+M97))*'Entrada e Saida'!$G$65),((Produtos!N97-'Entrada e Saida'!$G$65)*Produtos!BD97)))),0),0) -> 0 | BM97: =BF97+BL97 -> #DIV/0!
E98: =IFERROR(VLOOKUP(A98,'Master Modelo'!A:I,9,FALSE),0) -> 0 | F98: =IFERROR(VLOOKUP(A98,'Master Modelo'!A:I,8,FALSE),0) -> 0 | G98: =IFERROR(VLOOKUP(A98,'Master Modelo'!A:K,11,FALSE),0) -> 0 | H98: =(D98*E98)/(D98*F98) -> #DIV/0! | I98: =IFERROR(VLOOKUP(A98,'Master Modelo'!A:I,3,FALSE),0) -> 0 | J98: =IFERROR(VLOOKUP(A98,'Master Modelo'!A:I,5,FALSE),0) -> 0 | K98: =IFERROR(VLOOKUP(A98,'Master Modelo'!A:I,6,FALSE),0) -> 0 | L98: =VLOOKUP(A98,'Master Modelo'!A:J,10,FALSE) -> #N/A | M98: =IFERROR(VLOOKUP(A98,'Master Modelo'!A:I,4,FALSE),0) -> 0 | P98: =D98*F98 -> 0 | Q98: =D98*G98 -> 0 | R98: =D98*E98*'Entrada e Saida'!$K$8 -> 0 | S98: ='Entrada e Saida'!$H$21*'Entrada e Saida'!$K$8*(P98/(SUM(P:P))) -> #DIV/0! | T98: ='Entrada e Saida'!$H$21*'Entrada e Saida'!$K$8*(Q98/(SUM(Q:Q))) -> #DIV/0! | U98: ='Entrada e Saida'!$H$22*(P98/(SUM(P:P))) -> #DIV/0! | V98: ='Entrada e Saida'!$H$22*(Q98/(SUM(Q:Q))) -> #DIV/0! | W98: =R98+S98+U98 -> #DIV/0! | X98: ='Entrada e Saida'!$H$26*(IF('Entrada e Saida'!$H$15="PESO",(P98/(SUM(P:P))),(Q98/(SUM(Q:Q))))) -> #DIV/0! | Y98: ='Entrada e Saida'!$H$27*(IF('Entrada e Saida'!$H$15="PESO",(P98/(SUM(P:P))),(Q98/(SUM(Q:Q))))) -> #DIV/0! | Z98: ='Entrada e Saida'!$H$28*(IF('Entrada e Saida'!$H$15="PESO",(P98/(SUM(P:P))),(Q98/(SUM(Q:Q))))) -> #DIV/0! | AA98: =X98+Y98+Z98 -> #DIV/0! | AB98: =W98*I98 -> #DIV/0! | AC98: =W98*J98 -> #DIV/0! | AD98: =W98*K98 -> #DIV/0! | AE98: =(W98+AB98)*M98 -> #DIV/0! | AF98: =IFERROR(D98*F98*L98*'Entrada e Saida'!$K$8,0) -> 0 | AG98: =((W98+AA98+AB98+AC98+AD98+AE98+AF98)/(1-'Entrada e Saida'!$G$65))*'Entrada e Saida'!$I$66 -> #DIV/0! | AH98: =SUM(AB98:AG98) -> #DIV/0! | AI98: ='Entrada e Saida'!$K$51*(IF('Entrada e Saida'!$H$15="PESO",(P98/(SUM(P:P))),(Q98/(SUM(Q:Q))))) -> #DIV/0! | AJ98: =(('Entrada e Saida'!$K$10-'Entrada e Saida'!$K$8)*E98*D98) -> 0 | AK98: =IF('Entrada e Saida'!$H$15="PESO",W98+AA98+AH98+AI98+AJ98,W98+AA98+AH98+AI98+AJ98-S98+T98-U98+V98) -> #DIV/0! | AL98: =IF('Entrada e Saida'!$H$12="REAL",AC98,0) -> #DIV/0! | AM98: =IF('Entrada e Saida'!$H$12="REAL",AD98,0) -> #DIV/0! | AN98: =IF('Entrada e Saida'!$H$13= "NÃO",AE98,0) -> #DIV/0! | AO98: =AG98 -> #DIV/0! | AP98: =AK98-SUM(AL98:AO98) -> #DIV/0! | AQ98: =IF('Entrada e Saida'!$H$11="TRADING",AU98*'Custo Resumido'!D98,0) -> #DIV/0! | AR98: =IF('Entrada e Saida'!$H$11="TRADING",AU98*'Entrada e Saida'!$G$63,0) -> #DIV/0! | AS98: =IF('Entrada e Saida'!$H$11="TRADING",AU98*'Entrada e Saida'!$G$64,0) -> #DIV/0! | AT98: =IF('Entrada e Saida'!$H$11="TRADING",AU98*'Entrada e Saida'!$G$65,0) -> #DIV/0! | AU98: =IF('Entrada e Saida'!$H$11="TRADING",AP98/(1-(SUM('Entrada e Saida'!$G$63:$G$65)+'Custo Resumido'!D98)),0) -> #DIV/0! | AV98: =IF('Entrada e Saida'!$H$13="NÃO",AU98*M98,0) -> #DIV/0! | AW98: =AU98+AV98 -> #DIV/0! | AX98: ='Entrada e Saida'!$G$74*AU98 -> #DIV/0! | AY98: =AW98-AX98 -> #DIV/0! | AZ98: =AQ98+('Entrada e Saida'!$G$65-'Entrada e Saida'!$I$65)*AU98-AX98 -> #DIV/0! | BA98: =IF('Entrada e Saida'!$H$12="REAL",AZ98*'Entrada e Saida'!$G$81,AU98*'Entrada e Saida'!$G$81) -> #DIV/0! | BB98: =IF('Entrada e Saida'!$H$12="REAL",AZ98*'Entrada e Saida'!$G$82,AU98*'Entrada e Saida'!$G$82) -> #DIV/0! | BC98: =AZ98-BA98-BB98 -> #DIV/0! | BD98: =IF('Entrada e Saida'!$H$11="TRADING",AW98/D98,AK98/D98) -> #DIV/0! | BE98: =AX98/D98 -> #DIV/0! | BF98: =BD98-BE98 -> #DIV/0! | BG98: =IF('Entrada e Saida'!$H$11="TRADING",AV98/D98,AN98/D98) -> #DIV/0! | BH98: =IF('Entrada e Saida'!$H$11="TRADING",IF('Entrada e Saida'!$H$12="REAL",AR98/D98,0),AL98/D98) -> #DIV/0! | BI98: =IF('Entrada e Saida'!$H$11="TRADING",IF('Entrada e Saida'!$H$12="REAL",AS98/D98,0),AM98/D98) -> #DIV/0! | BJ98: =IF('Entrada e Saida'!$H$11="TRADING",AT98/D98,AO98/D98) -> #DIV/0! | BK98: =BF98-SUM(BG98:BJ98) -> #DIV/0! | BL98: =IF(O98>0,IFERROR(IF('Entrada e Saida'!$H$11="DIRETA",0,(IF('Entrada e Saida'!$H$14="P.JURIDICA",(BD98*(1+O98)*N98)-((BD98/(1+M98))*'Entrada e Saida'!$G$65),((Produtos!N98-'Entrada e Saida'!$G$65)*Produtos!BD98)))),0),0) -> 0 | BM98: =BF98+BL98 -> #DIV/0!
E99: =IFERROR(VLOOKUP(A99,'Master Modelo'!A:I,9,FALSE),0) -> 0 | F99: =IFERROR(VLOOKUP(A99,'Master Modelo'!A:I,8,FALSE),0) -> 0 | G99: =IFERROR(VLOOKUP(A99,'Master Modelo'!A:K,11,FALSE),0) -> 0 | H99: =(D99*E99)/(D99*F99) -> #DIV/0! | I99: =IFERROR(VLOOKUP(A99,'Master Modelo'!A:I,3,FALSE),0) -> 0 | J99: =IFERROR(VLOOKUP(A99,'Master Modelo'!A:I,5,FALSE),0) -> 0 | K99: =IFERROR(VLOOKUP(A99,'Master Modelo'!A:I,6,FALSE),0) -> 0 | L99: =VLOOKUP(A99,'Master Modelo'!A:J,10,FALSE) -> #N/A | M99: =IFERROR(VLOOKUP(A99,'Master Modelo'!A:I,4,FALSE),0) -> 0 | P99: =D99*F99 -> 0 | Q99: =D99*G99 -> 0 | R99: =D99*E99*'Entrada e Saida'!$K$8 -> 0 | S99: ='Entrada e Saida'!$H$21*'Entrada e Saida'!$K$8*(P99/(SUM(P:P))) -> #DIV/0! | T99: ='Entrada e Saida'!$H$21*'Entrada e Saida'!$K$8*(Q99/(SUM(Q:Q))) -> #DIV/0! | U99: ='Entrada e Saida'!$H$22*(P99/(SUM(P:P))) -> #DIV/0! | V99: ='Entrada e Saida'!$H$22*(Q99/(SUM(Q:Q))) -> #DIV/0! | W99: =R99+S99+U99 -> #DIV/0! | X99: ='Entrada e Saida'!$H$26*(IF('Entrada e Saida'!$H$15="PESO",(P99/(SUM(P:P))),(Q99/(SUM(Q:Q))))) -> #DIV/0! | Y99: ='Entrada e Saida'!$H$27*(IF('Entrada e Saida'!$H$15="PESO",(P99/(SUM(P:P))),(Q99/(SUM(Q:Q))))) -> #DIV/0! | Z99: ='Entrada e Saida'!$H$28*(IF('Entrada e Saida'!$H$15="PESO",(P99/(SUM(P:P))),(Q99/(SUM(Q:Q))))) -> #DIV/0! | AA99: =X99+Y99+Z99 -> #DIV/0! | AB99: =W99*I99 -> #DIV/0! | AC99: =W99*J99 -> #DIV/0! | AD99: =W99*K99 -> #DIV/0! | AE99: =(W99+AB99)*M99 -> #DIV/0! | AF99: =IFERROR(D99*F99*L99*'Entrada e Saida'!$K$8,0) -> 0 | AG99: =((W99+AA99+AB99+AC99+AD99+AE99+AF99)/(1-'Entrada e Saida'!$G$65))*'Entrada e Saida'!$I$66 -> #DIV/0! | AH99: =SUM(AB99:AG99) -> #DIV/0! | AI99: ='Entrada e Saida'!$K$51*(IF('Entrada e Saida'!$H$15="PESO",(P99/(SUM(P:P))),(Q99/(SUM(Q:Q))))) -> #DIV/0! | AJ99: =(('Entrada e Saida'!$K$10-'Entrada e Saida'!$K$8)*E99*D99) -> 0 | AK99: =IF('Entrada e Saida'!$H$15="PESO",W99+AA99+AH99+AI99+AJ99,W99+AA99+AH99+AI99+AJ99-S99+T99-U99+V99) -> #DIV/0! | AL99: =IF('Entrada e Saida'!$H$12="REAL",AC99,0) -> #DIV/0! | AM99: =IF('Entrada e Saida'!$H$12="REAL",AD99,0) -> #DIV/0! | AN99: =IF('Entrada e Saida'!$H$13= "NÃO",AE99,0) -> #DIV/0! | AO99: =AG99 -> #DIV/0! | AP99: =AK99-SUM(AL99:AO99) -> #DIV/0! | AQ99: =IF('Entrada e Saida'!$H$11="TRADING",AU99*'Custo Resumido'!D99,0) -> #DIV/0! | AR99: =IF('Entrada e Saida'!$H$11="TRADING",AU99*'Entrada e Saida'!$G$63,0) -> #DIV/0! | AS99: =IF('Entrada e Saida'!$H$11="TRADING",AU99*'Entrada e Saida'!$G$64,0) -> #DIV/0! | AT99: =IF('Entrada e Saida'!$H$11="TRADING",AU99*'Entrada e Saida'!$G$65,0) -> #DIV/0! | AU99: =IF('Entrada e Saida'!$H$11="TRADING",AP99/(1-(SUM('Entrada e Saida'!$G$63:$G$65)+'Custo Resumido'!D99)),0) -> #DIV/0! | AV99: =IF('Entrada e Saida'!$H$13="NÃO",AU99*M99,0) -> #DIV/0! | AW99: =AU99+AV99 -> #DIV/0! | AX99: ='Entrada e Saida'!$G$74*AU99 -> #DIV/0! | AY99: =AW99-AX99 -> #DIV/0! | AZ99: =AQ99+('Entrada e Saida'!$G$65-'Entrada e Saida'!$I$65)*AU99-AX99 -> #DIV/0! | BA99: =IF('Entrada e Saida'!$H$12="REAL",AZ99*'Entrada e Saida'!$G$81,AU99*'Entrada e Saida'!$G$81) -> #DIV/0! | BB99: =IF('Entrada e Saida'!$H$12="REAL",AZ99*'Entrada e Saida'!$G$82,AU99*'Entrada e Saida'!$G$82) -> #DIV/0! | BC99: =AZ99-BA99-BB99 -> #DIV/0! | BD99: =IF('Entrada e Saida'!$H$11="TRADING",AW99/D99,AK99/D99) -> #DIV/0! | BE99: =AX99/D99 -> #DIV/0! | BF99: =BD99-BE99 -> #DIV/0! | BG99: =IF('Entrada e Saida'!$H$11="TRADING",AV99/D99,AN99/D99) -> #DIV/0! | BH99: =IF('Entrada e Saida'!$H$11="TRADING",IF('Entrada e Saida'!$H$12="REAL",AR99/D99,0),AL99/D99) -> #DIV/0! | BI99: =IF('Entrada e Saida'!$H$11="TRADING",IF('Entrada e Saida'!$H$12="REAL",AS99/D99,0),AM99/D99) -> #DIV/0! | BJ99: =IF('Entrada e Saida'!$H$11="TRADING",AT99/D99,AO99/D99) -> #DIV/0! | BK99: =BF99-SUM(BG99:BJ99) -> #DIV/0! | BL99: =IF(O99>0,IFERROR(IF('Entrada e Saida'!$H$11="DIRETA",0,(IF('Entrada e Saida'!$H$14="P.JURIDICA",(BD99*(1+O99)*N99)-((BD99/(1+M99))*'Entrada e Saida'!$G$65),((Produtos!N99-'Entrada e Saida'!$G$65)*Produtos!BD99)))),0),0) -> 0 | BM99: =BF99+BL99 -> #DIV/0!
E100: =IFERROR(VLOOKUP(A100,'Master Modelo'!A:I,9,FALSE),0) -> 0 | F100: =IFERROR(VLOOKUP(A100,'Master Modelo'!A:I,8,FALSE),0) -> 0 | G100: =IFERROR(VLOOKUP(A100,'Master Modelo'!A:K,11,FALSE),0) -> 0 | H100: =(D100*E100)/(D100*F100) -> #DIV/0! | I100: =IFERROR(VLOOKUP(A100,'Master Modelo'!A:I,3,FALSE),0) -> 0 | J100: =IFERROR(VLOOKUP(A100,'Master Modelo'!A:I,5,FALSE),0) -> 0 | K100: =IFERROR(VLOOKUP(A100,'Master Modelo'!A:I,6,FALSE),0) -> 0 | L100: =VLOOKUP(A100,'Master Modelo'!A:J,10,FALSE) -> #N/A | M100: =IFERROR(VLOOKUP(A100,'Master Modelo'!A:I,4,FALSE),0) -> 0 | P100: =D100*F100 -> 0 | Q100: =D100*G100 -> 0 | R100: =D100*E100*'Entrada e Saida'!$K$8 -> 0 | S100: ='Entrada e Saida'!$H$21*'Entrada e Saida'!$K$8*(P100/(SUM(P:P))) -> #DIV/0! | T100: ='Entrada e Saida'!$H$21*'Entrada e Saida'!$K$8*(Q100/(SUM(Q:Q))) -> #DIV/0! | U100: ='Entrada e Saida'!$H$22*(P100/(SUM(P:P))) -> #DIV/0! | V100: ='Entrada e Saida'!$H$22*(Q100/(SUM(Q:Q))) -> #DIV/0! | W100: =R100+S100+U100 -> #DIV/0! | X100: ='Entrada e Saida'!$H$26*(IF('Entrada e Saida'!$H$15="PESO",(P100/(SUM(P:P))),(Q100/(SUM(Q:Q))))) -> #DIV/0! | Y100: ='Entrada e Saida'!$H$27*(IF('Entrada e Saida'!$H$15="PESO",(P100/(SUM(P:P))),(Q100/(SUM(Q:Q))))) -> #DIV/0! | Z100: ='Entrada e Saida'!$H$28*(IF('Entrada e Saida'!$H$15="PESO",(P100/(SUM(P:P))),(Q100/(SUM(Q:Q))))) -> #DIV/0! | AA100: =X100+Y100+Z100 -> #DIV/0! | AB100: =W100*I100 -> #DIV/0! | AC100: =W100*J100 -> #DIV/0! | AD100: =W100*K100 -> #DIV/0! | AE100: =(W100+AB100)*M100 -> #DIV/0! | AF100: =IFERROR(D100*F100*L100*'Entrada e Saida'!$K$8,0) -> 0 | AG100: =((W100+AA100+AB100+AC100+AD100+AE100+AF100)/(1-'Entrada e Saida'!$G$65))*'Entrada e Saida'!$I$66 -> #DIV/0! | AH100: =SUM(AB100:AG100) -> #DIV/0! | AI100: ='Entrada e Saida'!$K$51*(IF('Entrada e Saida'!$H$15="PESO",(P100/(SUM(P:P))),(Q100/(SUM(Q:Q))))) -> #DIV/0! | AJ100: =(('Entrada e Saida'!$K$10-'Entrada e Saida'!$K$8)*E100*D100) -> 0 | AK100: =IF('Entrada e Saida'!$H$15="PESO",W100+AA100+AH100+AI100+AJ100,W100+AA100+AH100+AI100+AJ100-S100+T100-U100+V100) -> #DIV/0! | AL100: =IF('Entrada e Saida'!$H$12="REAL",AC100,0) -> #DIV/0! | AM100: =IF('Entrada e Saida'!$H$12="REAL",AD100,0) -> #DIV/0! | AN100: =IF('Entrada e Saida'!$H$13= "NÃO",AE100,0) -> #DIV/0! | AO100: =AG100 -> #DIV/0! | AP100: =AK100-SUM(AL100:AO100) -> #DIV/0! | AQ100: =IF('Entrada e Saida'!$H$11="TRADING",AU100*'Custo Resumido'!D100,0) -> #DIV/0! | AR100: =IF('Entrada e Saida'!$H$11="TRADING",AU100*'Entrada e Saida'!$G$63,0) -> #DIV/0! | AS100: =IF('Entrada e Saida'!$H$11="TRADING",AU100*'Entrada e Saida'!$G$64,0) -> #DIV/0! | AT100: =IF('Entrada e Saida'!$H$11="TRADING",AU100*'Entrada e Saida'!$G$65,0) -> #DIV/0! | AU100: =IF('Entrada e Saida'!$H$11="TRADING",AP100/(1-(SUM('Entrada e Saida'!$G$63:$G$65)+'Custo Resumido'!D100)),0) -> #DIV/0! | AV100: =IF('Entrada e Saida'!$H$13="NÃO",AU100*M100,0) -> #DIV/0! | AW100: =AU100+AV100 -> #DIV/0! | AX100: ='Entrada e Saida'!$G$74*AU100 -> #DIV/0! | AY100: =AW100-AX100 -> #DIV/0! | AZ100: =AQ100+('Entrada e Saida'!$G$65-'Entrada e Saida'!$I$65)*AU100-AX100 -> #DIV/0! | BA100: =IF('Entrada e Saida'!$H$12="REAL",AZ100*'Entrada e Saida'!$G$81,AU100*'Entrada e Saida'!$G$81) -> #DIV/0! | BB100: =IF('Entrada e Saida'!$H$12="REAL",AZ100*'Entrada e Saida'!$G$82,AU100*'Entrada e Saida'!$G$82) -> #DIV/0! | BC100: =AZ100-BA100-BB100 -> #DIV/0! | BD100: =IF('Entrada e Saida'!$H$11="TRADING",AW100/D100,AK100/D100) -> #DIV/0! | BE100: =AX100/D100 -> #DIV/0! | BF100: =BD100-BE100 -> #DIV/0! | BG100: =IF('Entrada e Saida'!$H$11="TRADING",AV100/D100,AN100/D100) -> #DIV/0! | BH100: =IF('Entrada e Saida'!$H$11="TRADING",IF('Entrada e Saida'!$H$12="REAL",AR100/D100,0),AL100/D100) -> #DIV/0! | BI100: =IF('Entrada e Saida'!$H$11="TRADING",IF('Entrada e Saida'!$H$12="REAL",AS100/D100,0),AM100/D100) -> #DIV/0! | BJ100: =IF('Entrada e Saida'!$H$11="TRADING",AT100/D100,AO100/D100) -> #DIV/0! | BK100: =BF100-SUM(BG100:BJ100) -> #DIV/0! | BL100: =IF(O100>0,IFERROR(IF('Entrada e Saida'!$H$11="DIRETA",0,(IF('Entrada e Saida'!$H$14="P.JURIDICA",(BD100*(1+O100)*N100)-((BD100/(1+M100))*'Entrada e Saida'!$G$65),((Produtos!N100-'Entrada e Saida'!$G$65)*Produtos!BD100)))),0),0) -> 0 | BM100: =BF100+BL100 -> #DIV/0!
E101: =IFERROR(VLOOKUP(A101,'Master Modelo'!A:I,9,FALSE),0) -> 0 | F101: =IFERROR(VLOOKUP(A101,'Master Modelo'!A:I,8,FALSE),0) -> 0 | G101: =IFERROR(VLOOKUP(A101,'Master Modelo'!A:K,11,FALSE),0) -> 0 | H101: =(D101*E101)/(D101*F101) -> #DIV/0! | I101: =IFERROR(VLOOKUP(A101,'Master Modelo'!A:I,3,FALSE),0) -> 0 | J101: =IFERROR(VLOOKUP(A101,'Master Modelo'!A:I,5,FALSE),0) -> 0 | K101: =IFERROR(VLOOKUP(A101,'Master Modelo'!A:I,6,FALSE),0) -> 0 | L101: =VLOOKUP(A101,'Master Modelo'!A:J,10,FALSE) -> #N/A | M101: =IFERROR(VLOOKUP(A101,'Master Modelo'!A:I,4,FALSE),0) -> 0 | P101: =D101*F101 -> 0 | Q101: =D101*G101 -> 0 | R101: =D101*E101*'Entrada e Saida'!$K$8 -> 0 | S101: ='Entrada e Saida'!$H$21*'Entrada e Saida'!$K$8*(P101/(SUM(P:P))) -> #DIV/0! | T101: ='Entrada e Saida'!$H$21*'Entrada e Saida'!$K$8*(Q101/(SUM(Q:Q))) -> #DIV/0! | U101: ='Entrada e Saida'!$H$22*(P101/(SUM(P:P))) -> #DIV/0! | V101: ='Entrada e Saida'!$H$22*(Q101/(SUM(Q:Q))) -> #DIV/0! | W101: =R101+S101+U101 -> #DIV/0! | X101: ='Entrada e Saida'!$H$26*(IF('Entrada e Saida'!$H$15="PESO",(P101/(SUM(P:P))),(Q101/(SUM(Q:Q))))) -> #DIV/0! | Y101: ='Entrada e Saida'!$H$27*(IF('Entrada e Saida'!$H$15="PESO",(P101/(SUM(P:P))),(Q101/(SUM(Q:Q))))) -> #DIV/0! | Z101: ='Entrada e Saida'!$H$28*(IF('Entrada e Saida'!$H$15="PESO",(P101/(SUM(P:P))),(Q101/(SUM(Q:Q))))) -> #DIV/0! | AA101: =X101+Y101+Z101 -> #DIV/0! | AB101: =W101*I101 -> #DIV/0! | AC101: =W101*J101 -> #DIV/0! | AD101: =W101*K101 -> #DIV/0! | AE101: =(W101+AB101)*M101 -> #DIV/0! | AF101: =IFERROR(D101*F101*L101*'Entrada e Saida'!$K$8,0) -> 0 | AG101: =((W101+AA101+AB101+AC101+AD101+AE101+AF101)/(1-'Entrada e Saida'!$G$65))*'Entrada e Saida'!$I$66 -> #DIV/0! | AH101: =SUM(AB101:AG101) -> #DIV/0! | AI101: ='Entrada e Saida'!$K$51*(IF('Entrada e Saida'!$H$15="PESO",(P101/(SUM(P:P))),(Q101/(SUM(Q:Q))))) -> #DIV/0! | AJ101: =(('Entrada e Saida'!$K$10-'Entrada e Saida'!$K$8)*E101*D101) -> 0 | AK101: =IF('Entrada e Saida'!$H$15="PESO",W101+AA101+AH101+AI101+AJ101,W101+AA101+AH101+AI101+AJ101-S101+T101-U101+V101) -> #DIV/0! | AL101: =IF('Entrada e Saida'!$H$12="REAL",AC101,0) -> #DIV/0! | AM101: =IF('Entrada e Saida'!$H$12="REAL",AD101,0) -> #DIV/0! | AN101: =IF('Entrada e Saida'!$H$13= "NÃO",AE101,0) -> #DIV/0! | AO101: =AG101 -> #DIV/0! | AP101: =AK101-SUM(AL101:AO101) -> #DIV/0! | AQ101: =IF('Entrada e Saida'!$H$11="TRADING",AU101*'Custo Resumido'!D101,0) -> #DIV/0! | AR101: =IF('Entrada e Saida'!$H$11="TRADING",AU101*'Entrada e Saida'!$G$63,0) -> #DIV/0! | AS101: =IF('Entrada e Saida'!$H$11="TRADING",AU101*'Entrada e Saida'!$G$64,0) -> #DIV/0! | AT101: =IF('Entrada e Saida'!$H$11="TRADING",AU101*'Entrada e Saida'!$G$65,0) -> #DIV/0! | AU101: =IF('Entrada e Saida'!$H$11="TRADING",AP101/(1-(SUM('Entrada e Saida'!$G$63:$G$65)+'Custo Resumido'!D101)),0) -> #DIV/0! | AV101: =IF('Entrada e Saida'!$H$13="NÃO",AU101*M101,0) -> #DIV/0! | AW101: =AU101+AV101 -> #DIV/0! | AX101: ='Entrada e Saida'!$G$74*AU101 -> #DIV/0! | AY101: =AW101-AX101 -> #DIV/0! | AZ101: =AQ101+('Entrada e Saida'!$G$65-'Entrada e Saida'!$I$65)*AU101-AX101 -> #DIV/0! | BA101: =IF('Entrada e Saida'!$H$12="REAL",AZ101*'Entrada e Saida'!$G$81,AU101*'Entrada e Saida'!$G$81) -> #DIV/0! | BB101: =IF('Entrada e Saida'!$H$12="REAL",AZ101*'Entrada e Saida'!$G$82,AU101*'Entrada e Saida'!$G$82) -> #DIV/0! | BC101: =AZ101-BA101-BB101 -> #DIV/0! | BD101: =IF('Entrada e Saida'!$H$11="TRADING",AW101/D101,AK101/D101) -> #DIV/0! | BE101: =AX101/D101 -> #DIV/0! | BF101: =BD101-BE101 -> #DIV/0! | BG101: =IF('Entrada e Saida'!$H$11="TRADING",AV101/D101,AN101/D101) -> #DIV/0! | BH101: =IF('Entrada e Saida'!$H$11="TRADING",IF('Entrada e Saida'!$H$12="REAL",AR101/D101,0),AL101/D101) -> #DIV/0! | BI101: =IF('Entrada e Saida'!$H$11="TRADING",IF('Entrada e Saida'!$H$12="REAL",AS101/D101,0),AM101/D101) -> #DIV/0! | BJ101: =IF('Entrada e Saida'!$H$11="TRADING",AT101/D101,AO101/D101) -> #DIV/0! | BK101: =BF101-SUM(BG101:BJ101) -> #DIV/0! | BL101: =IF(O101>0,IFERROR(IF('Entrada e Saida'!$H$11="DIRETA",0,(IF('Entrada e Saida'!$H$14="P.JURIDICA",(BD101*(1+O101)*N101)-((BD101/(1+M101))*'Entrada e Saida'!$G$65),((Produtos!N101-'Entrada e Saida'!$G$65)*Produtos!BD101)))),0),0) -> 0 | BM101: =BF101+BL101 -> #DIV/0!
E102: =IFERROR(VLOOKUP(A102,'Master Modelo'!A:I,9,FALSE),0) -> 0 | F102: =IFERROR(VLOOKUP(A102,'Master Modelo'!A:I,8,FALSE),0) -> 0 | G102: =IFERROR(VLOOKUP(A102,'Master Modelo'!A:K,11,FALSE),0) -> 0 | H102: =(D102*E102)/(D102*F102) -> #DIV/0! | I102: =IFERROR(VLOOKUP(A102,'Master Modelo'!A:I,3,FALSE),0) -> 0 | J102: =IFERROR(VLOOKUP(A102,'Master Modelo'!A:I,5,FALSE),0) -> 0 | K102: =IFERROR(VLOOKUP(A102,'Master Modelo'!A:I,6,FALSE),0) -> 0 | L102: =VLOOKUP(A102,'Master Modelo'!A:J,10,FALSE) -> #N/A | M102: =IFERROR(VLOOKUP(A102,'Master Modelo'!A:I,4,FALSE),0) -> 0 | P102: =D102*F102 -> 0 | Q102: =D102*G102 -> 0 | R102: =D102*E102*'Entrada e Saida'!$K$8 -> 0 | S102: ='Entrada e Saida'!$H$21*'Entrada e Saida'!$K$8*(P102/(SUM(P:P))) -> #DIV/0! | T102: ='Entrada e Saida'!$H$21*'Entrada e Saida'!$K$8*(Q102/(SUM(Q:Q))) -> #DIV/0! | U102: ='Entrada e Saida'!$H$22*(P102/(SUM(P:P))) -> #DIV/0! | V102: ='Entrada e Saida'!$H$22*(Q102/(SUM(Q:Q))) -> #DIV/0! | W102: =R102+S102+U102 -> #DIV/0! | X102: ='Entrada e Saida'!$H$26*(IF('Entrada e Saida'!$H$15="PESO",(P102/(SUM(P:P))),(Q102/(SUM(Q:Q))))) -> #DIV/0! | Y102: ='Entrada e Saida'!$H$27*(IF('Entrada e Saida'!$H$15="PESO",(P102/(SUM(P:P))),(Q102/(SUM(Q:Q))))) -> #DIV/0! | Z102: ='Entrada e Saida'!$H$28*(IF('Entrada e Saida'!$H$15="PESO",(P102/(SUM(P:P))),(Q102/(SUM(Q:Q))))) -> #DIV/0! | AA102: =X102+Y102+Z102 -> #DIV/0! | AB102: =W102*I102 -> #DIV/0! | AC102: =W102*J102 -> #DIV/0! | AD102: =W102*K102 -> #DIV/0! | AE102: =(W102+AB102)*M102 -> #DIV/0! | AF102: =IFERROR(D102*F102*L102*'Entrada e Saida'!$K$8,0) -> 0 | AG102: =((W102+AA102+AB102+AC102+AD102+AE102+AF102)/(1-'Entrada e Saida'!$G$65))*'Entrada e Saida'!$I$66 -> #DIV/0! | AH102: =SUM(AB102:AG102) -> #DIV/0! | AI102: ='Entrada e Saida'!$K$51*(IF('Entrada e Saida'!$H$15="PESO",(P102/(SUM(P:P))),(Q102/(SUM(Q:Q))))) -> #DIV/0! | AJ102: =(('Entrada e Saida'!$K$10-'Entrada e Saida'!$K$8)*E102*D102) -> 0 | AK102: =IF('Entrada e Saida'!$H$15="PESO",W102+AA102+AH102+AI102+AJ102,W102+AA102+AH102+AI102+AJ102-S102+T102-U102+V102) -> #DIV/0! | AL102: =IF('Entrada e Saida'!$H$12="REAL",AC102,0) -> #DIV/0! | AM102: =IF('Entrada e Saida'!$H$12="REAL",AD102,0) -> #DIV/0! | AN102: =IF('Entrada e Saida'!$H$13= "NÃO",AE102,0) -> #DIV/0! | AO102: =AG102 -> #DIV/0! | AP102: =AK102-SUM(AL102:AO102) -> #DIV/0! | AQ102: =IF('Entrada e Saida'!$H$11="TRADING",AU102*'Custo Resumido'!D102,0) -> #DIV/0! | AR102: =IF('Entrada e Saida'!$H$11="TRADING",AU102*'Entrada e Saida'!$G$63,0) -> #DIV/0! | AS102: =IF('Entrada e Saida'!$H$11="TRADING",AU102*'Entrada e Saida'!$G$64,0) -> #DIV/0! | AT102: =IF('Entrada e Saida'!$H$11="TRADING",AU102*'Entrada e Saida'!$G$65,0) -> #DIV/0! | AU102: =IF('Entrada e Saida'!$H$11="TRADING",AP102/(1-(SUM('Entrada e Saida'!$G$63:$G$65)+'Custo Resumido'!D102)),0) -> #DIV/0! | AV102: =IF('Entrada e Saida'!$H$13="NÃO",AU102*M102,0) -> #DIV/0! | AW102: =AU102+AV102 -> #DIV/0! | AX102: ='Entrada e Saida'!$G$74*AU102 -> #DIV/0! | AY102: =AW102-AX102 -> #DIV/0! | AZ102: =AQ102+('Entrada e Saida'!$G$65-'Entrada e Saida'!$I$65)*AU102-AX102 -> #DIV/0! | BA102: =IF('Entrada e Saida'!$H$12="REAL",AZ102*'Entrada e Saida'!$G$81,AU102*'Entrada e Saida'!$G$81) -> #DIV/0! | BB102: =IF('Entrada e Saida'!$H$12="REAL",AZ102*'Entrada e Saida'!$G$82,AU102*'Entrada e Saida'!$G$82) -> #DIV/0! | BC102: =AZ102-BA102-BB102 -> #DIV/0! | BD102: =IF('Entrada e Saida'!$H$11="TRADING",AW102/D102,AK102/D102) -> #DIV/0! | BE102: =AX102/D102 -> #DIV/0! | BF102: =BD102-BE102 -> #DIV/0! | BG102: =IF('Entrada e Saida'!$H$11="TRADING",AV102/D102,AN102/D102) -> #DIV/0! | BH102: =IF('Entrada e Saida'!$H$11="TRADING",IF('Entrada e Saida'!$H$12="REAL",AR102/D102,0),AL102/D102) -> #DIV/0! | BI102: =IF('Entrada e Saida'!$H$11="TRADING",IF('Entrada e Saida'!$H$12="REAL",AS102/D102,0),AM102/D102) -> #DIV/0! | BJ102: =IF('Entrada e Saida'!$H$11="TRADING",AT102/D102,AO102/D102) -> #DIV/0! | BK102: =BF102-SUM(BG102:BJ102) -> #DIV/0! | BL102: =IF(O102>0,IFERROR(IF('Entrada e Saida'!$H$11="DIRETA",0,(IF('Entrada e Saida'!$H$14="P.JURIDICA",(BD102*(1+O102)*N102)-((BD102/(1+M102))*'Entrada e Saida'!$G$65),((Produtos!N102-'Entrada e Saida'!$G$65)*Produtos!BD102)))),0),0) -> 0 | BM102: =BF102+BL102 -> #DIV/0!
E103: =IFERROR(VLOOKUP(A103,'Master Modelo'!A:I,9,FALSE),0) -> 0 | F103: =IFERROR(VLOOKUP(A103,'Master Modelo'!A:I,8,FALSE),0) -> 0 | G103: =IFERROR(VLOOKUP(A103,'Master Modelo'!A:K,11,FALSE),0) -> 0 | H103: =(D103*E103)/(D103*F103) -> #DIV/0! | I103: =IFERROR(VLOOKUP(A103,'Master Modelo'!A:I,3,FALSE),0) -> 0 | J103: =IFERROR(VLOOKUP(A103,'Master Modelo'!A:I,5,FALSE),0) -> 0 | K103: =IFERROR(VLOOKUP(A103,'Master Modelo'!A:I,6,FALSE),0) -> 0 | L103: =VLOOKUP(A103,'Master Modelo'!A:J,10,FALSE) -> #N/A | M103: =IFERROR(VLOOKUP(A103,'Master Modelo'!A:I,4,FALSE),0) -> 0 | P103: =D103*F103 -> 0 | Q103: =D103*G103 -> 0 | R103: =D103*E103*'Entrada e Saida'!$K$8 -> 0 | S103: ='Entrada e Saida'!$H$21*'Entrada e Saida'!$K$8*(P103/(SUM(P:P))) -> #DIV/0! | T103: ='Entrada e Saida'!$H$21*'Entrada e Saida'!$K$8*(Q103/(SUM(Q:Q))) -> #DIV/0! | U103: ='Entrada e Saida'!$H$22*(P103/(SUM(P:P))) -> #DIV/0! | V103: ='Entrada e Saida'!$H$22*(Q103/(SUM(Q:Q))) -> #DIV/0! | W103: =R103+S103+U103 -> #DIV/0! | X103: ='Entrada e Saida'!$H$26*(IF('Entrada e Saida'!$H$15="PESO",(P103/(SUM(P:P))),(Q103/(SUM(Q:Q))))) -> #DIV/0! | Y103: ='Entrada e Saida'!$H$27*(IF('Entrada e Saida'!$H$15="PESO",(P103/(SUM(P:P))),(Q103/(SUM(Q:Q))))) -> #DIV/0! | Z103: ='Entrada e Saida'!$H$28*(IF('Entrada e Saida'!$H$15="PESO",(P103/(SUM(P:P))),(Q103/(SUM(Q:Q))))) -> #DIV/0! | AA103: =X103+Y103+Z103 -> #DIV/0! | AB103: =W103*I103 -> #DIV/0! | AC103: =W103*J103 -> #DIV/0! | AD103: =W103*K103 -> #DIV/0! | AE103: =(W103+AB103)*M103 -> #DIV/0! | AF103: =IFERROR(D103*F103*L103*'Entrada e Saida'!$K$8,0) -> 0 | AG103: =((W103+AA103+AB103+AC103+AD103+AE103+AF103)/(1-'Entrada e Saida'!$G$65))*'Entrada e Saida'!$I$66 -> #DIV/0! | AH103: =SUM(AB103:AG103) -> #DIV/0! | AI103: ='Entrada e Saida'!$K$51*(IF('Entrada e Saida'!$H$15="PESO",(P103/(SUM(P:P))),(Q103/(SUM(Q:Q))))) -> #DIV/0! | AJ103: =(('Entrada e Saida'!$K$10-'Entrada e Saida'!$K$8)*E103*D103) -> 0 | AK103: =IF('Entrada e Saida'!$H$15="PESO",W103+AA103+AH103+AI103+AJ103,W103+AA103+AH103+AI103+AJ103-S103+T103-U103+V103) -> #DIV/0! | AL103: =IF('Entrada e Saida'!$H$12="REAL",AC103,0) -> #DIV/0! | AM103: =IF('Entrada e Saida'!$H$12="REAL",AD103,0) -> #DIV/0! | AN103: =IF('Entrada e Saida'!$H$13= "NÃO",AE103,0) -> #DIV/0! | AO103: =AG103 -> #DIV/0! | AP103: =AK103-SUM(AL103:AO103) -> #DIV/0! | AQ103: =IF('Entrada e Saida'!$H$11="TRADING",AU103*'Custo Resumido'!D103,0) -> #DIV/0! | AR103: =IF('Entrada e Saida'!$H$11="TRADING",AU103*'Entrada e Saida'!$G$63,0) -> #DIV/0! | AS103: =IF('Entrada e Saida'!$H$11="TRADING",AU103*'Entrada e Saida'!$G$64,0) -> #DIV/0! | AT103: =IF('Entrada e Saida'!$H$11="TRADING",AU103*'Entrada e Saida'!$G$65,0) -> #DIV/0! | AU103: =IF('Entrada e Saida'!$H$11="TRADING",AP103/(1-(SUM('Entrada e Saida'!$G$63:$G$65)+'Custo Resumido'!D103)),0) -> #DIV/0! | AV103: =IF('Entrada e Saida'!$H$13="NÃO",AU103*M103,0) -> #DIV/0! | AW103: =AU103+AV103 -> #DIV/0! | AX103: ='Entrada e Saida'!$G$74*AU103 -> #DIV/0! | AY103: =AW103-AX103 -> #DIV/0! | AZ103: =AQ103+('Entrada e Saida'!$G$65-'Entrada e Saida'!$I$65)*AU103-AX103 -> #DIV/0! | BA103: =IF('Entrada e Saida'!$H$12="REAL",AZ103*'Entrada e Saida'!$G$81,AU103*'Entrada e Saida'!$G$81) -> #DIV/0! | BB103: =IF('Entrada e Saida'!$H$12="REAL",AZ103*'Entrada e Saida'!$G$82,AU103*'Entrada e Saida'!$G$82) -> #DIV/0! | BC103: =AZ103-BA103-BB103 -> #DIV/0! | BD103: =IF('Entrada e Saida'!$H$11="TRADING",AW103/D103,AK103/D103) -> #DIV/0! | BE103: =AX103/D103 -> #DIV/0! | BF103: =BD103-BE103 -> #DIV/0! | BG103: =IF('Entrada e Saida'!$H$11="TRADING",AV103/D103,AN103/D103) -> #DIV/0! | BH103: =IF('Entrada e Saida'!$H$11="TRADING",IF('Entrada e Saida'!$H$12="REAL",AR103/D103,0),AL103/D103) -> #DIV/0! | BI103: =IF('Entrada e Saida'!$H$11="TRADING",IF('Entrada e Saida'!$H$12="REAL",AS103/D103,0),AM103/D103) -> #DIV/0! | BJ103: =IF('Entrada e Saida'!$H$11="TRADING",AT103/D103,AO103/D103) -> #DIV/0! | BK103: =BF103-SUM(BG103:BJ103) -> #DIV/0! | BL103: =IF(O103>0,IFERROR(IF('Entrada e Saida'!$H$11="DIRETA",0,(IF('Entrada e Saida'!$H$14="P.JURIDICA",(BD103*(1+O103)*N103)-((BD103/(1+M103))*'Entrada e Saida'!$G$65),((Produtos!N103-'Entrada e Saida'!$G$65)*Produtos!BD103)))),0),0) -> 0 | BM103: =BF103+BL103 -> #DIV/0!
E104: =IFERROR(VLOOKUP(A104,'Master Modelo'!A:I,9,FALSE),0) -> 0 | F104: =IFERROR(VLOOKUP(A104,'Master Modelo'!A:I,8,FALSE),0) -> 0 | G104: =IFERROR(VLOOKUP(A104,'Master Modelo'!A:K,11,FALSE),0) -> 0 | H104: =(D104*E104)/(D104*F104) -> #DIV/0! | I104: =IFERROR(VLOOKUP(A104,'Master Modelo'!A:I,3,FALSE),0) -> 0 | J104: =IFERROR(VLOOKUP(A104,'Master Modelo'!A:I,5,FALSE),0) -> 0 | K104: =IFERROR(VLOOKUP(A104,'Master Modelo'!A:I,6,FALSE),0) -> 0 | L104: =VLOOKUP(A104,'Master Modelo'!A:J,10,FALSE) -> #N/A | M104: =IFERROR(VLOOKUP(A104,'Master Modelo'!A:I,4,FALSE),0) -> 0 | P104: =D104*F104 -> 0 | Q104: =D104*G104 -> 0 | R104: =D104*E104*'Entrada e Saida'!$K$8 -> 0 | S104: ='Entrada e Saida'!$H$21*'Entrada e Saida'!$K$8*(P104/(SUM(P:P))) -> #DIV/0! | T104: ='Entrada e Saida'!$H$21*'Entrada e Saida'!$K$8*(Q104/(SUM(Q:Q))) -> #DIV/0! | U104: ='Entrada e Saida'!$H$22*(P104/(SUM(P:P))) -> #DIV/0! | V104: ='Entrada e Saida'!$H$22*(Q104/(SUM(Q:Q))) -> #DIV/0! | W104: =R104+S104+U104 -> #DIV/0! | X104: ='Entrada e Saida'!$H$26*(IF('Entrada e Saida'!$H$15="PESO",(P104/(SUM(P:P))),(Q104/(SUM(Q:Q))))) -> #DIV/0! | Y104: ='Entrada e Saida'!$H$27*(IF('Entrada e Saida'!$H$15="PESO",(P104/(SUM(P:P))),(Q104/(SUM(Q:Q))))) -> #DIV/0! | Z104: ='Entrada e Saida'!$H$28*(IF('Entrada e Saida'!$H$15="PESO",(P104/(SUM(P:P))),(Q104/(SUM(Q:Q))))) -> #DIV/0! | AA104: =X104+Y104+Z104 -> #DIV/0! | AB104: =W104*I104 -> #DIV/0! | AC104: =W104*J104 -> #DIV/0! | AD104: =W104*K104 -> #DIV/0! | AE104: =(W104+AB104)*M104 -> #DIV/0! | AF104: =IFERROR(D104*F104*L104*'Entrada e Saida'!$K$8,0) -> 0 | AG104: =((W104+AA104+AB104+AC104+AD104+AE104+AF104)/(1-'Entrada e Saida'!$G$65))*'Entrada e Saida'!$I$66 -> #DIV/0! | AH104: =SUM(AB104:AG104) -> #DIV/0! | AI104: ='Entrada e Saida'!$K$51*(IF('Entrada e Saida'!$H$15="PESO",(P104/(SUM(P:P))),(Q104/(SUM(Q:Q))))) -> #DIV/0! | AJ104: =(('Entrada e Saida'!$K$10-'Entrada e Saida'!$K$8)*E104*D104) -> 0 | AK104: =IF('Entrada e Saida'!$H$15="PESO",W104+AA104+AH104+AI104+AJ104,W104+AA104+AH104+AI104+AJ104-S104+T104-U104+V104) -> #DIV/0! | AL104: =IF('Entrada e Saida'!$H$12="REAL",AC104,0) -> #DIV/0! | AM104: =IF('Entrada e Saida'!$H$12="REAL",AD104,0) -> #DIV/0! | AN104: =IF('Entrada e Saida'!$H$13= "NÃO",AE104,0) -> #DIV/0! | AO104: =AG104 -> #DIV/0! | AP104: =AK104-SUM(AL104:AO104) -> #DIV/0! | AQ104: =IF('Entrada e Saida'!$H$11="TRADING",AU104*'Custo Resumido'!D104,0) -> #DIV/0! | AR104: =IF('Entrada e Saida'!$H$11="TRADING",AU104*'Entrada e Saida'!$G$63,0) -> #DIV/0! | AS104: =IF('Entrada e Saida'!$H$11="TRADING",AU104*'Entrada e Saida'!$G$64,0) -> #DIV/0! | AT104: =IF('Entrada e Saida'!$H$11="TRADING",AU104*'Entrada e Saida'!$G$65,0) -> #DIV/0! | AU104: =IF('Entrada e Saida'!$H$11="TRADING",AP104/(1-(SUM('Entrada e Saida'!$G$63:$G$65)+'Custo Resumido'!D104)),0) -> #DIV/0! | AV104: =IF('Entrada e Saida'!$H$13="NÃO",AU104*M104,0) -> #DIV/0! | AW104: =AU104+AV104 -> #DIV/0! | AX104: ='Entrada e Saida'!$G$74*AU104 -> #DIV/0! | AY104: =AW104-AX104 -> #DIV/0! | AZ104: =AQ104+('Entrada e Saida'!$G$65-'Entrada e Saida'!$I$65)*AU104-AX104 -> #DIV/0! | BA104: =IF('Entrada e Saida'!$H$12="REAL",AZ104*'Entrada e Saida'!$G$81,AU104*'Entrada e Saida'!$G$81) -> #DIV/0! | BB104: =IF('Entrada e Saida'!$H$12="REAL",AZ104*'Entrada e Saida'!$G$82,AU104*'Entrada e Saida'!$G$82) -> #DIV/0! | BC104: =AZ104-BA104-BB104 -> #DIV/0! | BD104: =IF('Entrada e Saida'!$H$11="TRADING",AW104/D104,AK104/D104) -> #DIV/0! | BE104: =AX104/D104 -> #DIV/0! | BF104: =BD104-BE104 -> #DIV/0! | BG104: =IF('Entrada e Saida'!$H$11="TRADING",AV104/D104,AN104/D104) -> #DIV/0! | BH104: =IF('Entrada e Saida'!$H$11="TRADING",IF('Entrada e Saida'!$H$12="REAL",AR104/D104,0),AL104/D104) -> #DIV/0! | BI104: =IF('Entrada e Saida'!$H$11="TRADING",IF('Entrada e Saida'!$H$12="REAL",AS104/D104,0),AM104/D104) -> #DIV/0! | BJ104: =IF('Entrada e Saida'!$H$11="TRADING",AT104/D104,AO104/D104) -> #DIV/0! | BK104: =BF104-SUM(BG104:BJ104) -> #DIV/0! | BL104: =IF(O104>0,IFERROR(IF('Entrada e Saida'!$H$11="DIRETA",0,(IF('Entrada e Saida'!$H$14="P.JURIDICA",(BD104*(1+O104)*N104)-((BD104/(1+M104))*'Entrada e Saida'!$G$65),((Produtos!N104-'Entrada e Saida'!$G$65)*Produtos!BD104)))),0),0) -> 0 | BM104: =BF104+BL104 -> #DIV/0!
E105: =IFERROR(VLOOKUP(A105,'Master Modelo'!A:I,9,FALSE),0) -> 0 | F105: =IFERROR(VLOOKUP(A105,'Master Modelo'!A:I,8,FALSE),0) -> 0 | G105: =IFERROR(VLOOKUP(A105,'Master Modelo'!A:K,11,FALSE),0) -> 0 | H105: =(D105*E105)/(D105*F105) -> #DIV/0! | I105: =IFERROR(VLOOKUP(A105,'Master Modelo'!A:I,3,FALSE),0) -> 0 | J105: =IFERROR(VLOOKUP(A105,'Master Modelo'!A:I,5,FALSE),0) -> 0 | K105: =IFERROR(VLOOKUP(A105,'Master Modelo'!A:I,6,FALSE),0) -> 0 | L105: =VLOOKUP(A105,'Master Modelo'!A:J,10,FALSE) -> #N/A | M105: =IFERROR(VLOOKUP(A105,'Master Modelo'!A:I,4,FALSE),0) -> 0 | P105: =D105*F105 -> 0 | Q105: =D105*G105 -> 0 | R105: =D105*E105*'Entrada e Saida'!$K$8 -> 0 | S105: ='Entrada e Saida'!$H$21*'Entrada e Saida'!$K$8*(P105/(SUM(P:P))) -> #DIV/0! | T105: ='Entrada e Saida'!$H$21*'Entrada e Saida'!$K$8*(Q105/(SUM(Q:Q))) -> #DIV/0! | U105: ='Entrada e Saida'!$H$22*(P105/(SUM(P:P))) -> #DIV/0! | V105: ='Entrada e Saida'!$H$22*(Q105/(SUM(Q:Q))) -> #DIV/0! | W105: =R105+S105+U105 -> #DIV/0! | X105: ='Entrada e Saida'!$H$26*(IF('Entrada e Saida'!$H$15="PESO",(P105/(SUM(P:P))),(Q105/(SUM(Q:Q))))) -> #DIV/0! | Y105: ='Entrada e Saida'!$H$27*(IF('Entrada e Saida'!$H$15="PESO",(P105/(SUM(P:P))),(Q105/(SUM(Q:Q))))) -> #DIV/0! | Z105: ='Entrada e Saida'!$H$28*(IF('Entrada e Saida'!$H$15="PESO",(P105/(SUM(P:P))),(Q105/(SUM(Q:Q))))) -> #DIV/0! | AA105: =X105+Y105+Z105 -> #DIV/0! | AB105: =W105*I105 -> #DIV/0! | AC105: =W105*J105 -> #DIV/0! | AD105: =W105*K105 -> #DIV/0! | AE105: =(W105+AB105)*M105 -> #DIV/0! | AF105: =IFERROR(D105*F105*L105*'Entrada e Saida'!$K$8,0) -> 0 | AG105: =((W105+AA105+AB105+AC105+AD105+AE105+AF105)/(1-'Entrada e Saida'!$G$65))*'Entrada e Saida'!$I$66 -> #DIV/0! | AH105: =SUM(AB105:AG105) -> #DIV/0! | AI105: ='Entrada e Saida'!$K$51*(IF('Entrada e Saida'!$H$15="PESO",(P105/(SUM(P:P))),(Q105/(SUM(Q:Q))))) -> #DIV/0! | AJ105: =(('Entrada e Saida'!$K$10-'Entrada e Saida'!$K$8)*E105*D105) -> 0 | AK105: =IF('Entrada e Saida'!$H$15="PESO",W105+AA105+AH105+AI105+AJ105,W105+AA105+AH105+AI105+AJ105-S105+T105-U105+V105) -> #DIV/0! | AL105: =IF('Entrada e Saida'!$H$12="REAL",AC105,0) -> #DIV/0! | AM105: =IF('Entrada e Saida'!$H$12="REAL",AD105,0) -> #DIV/0! | AN105: =IF('Entrada e Saida'!$H$13= "NÃO",AE105,0) -> #DIV/0! | AO105: =AG105 -> #DIV/0! | AP105: =AK105-SUM(AL105:AO105) -> #DIV/0! | AQ105: =IF('Entrada e Saida'!$H$11="TRADING",AU105*'Custo Resumido'!D105,0) -> #DIV/0! | AR105: =IF('Entrada e Saida'!$H$11="TRADING",AU105*'Entrada e Saida'!$G$63,0) -> #DIV/0! | AS105: =IF('Entrada e Saida'!$H$11="TRADING",AU105*'Entrada e Saida'!$G$64,0) -> #DIV/0! | AT105: =IF('Entrada e Saida'!$H$11="TRADING",AU105*'Entrada e Saida'!$G$65,0) -> #DIV/0! | AU105: =IF('Entrada e Saida'!$H$11="TRADING",AP105/(1-(SUM('Entrada e Saida'!$G$63:$G$65)+'Custo Resumido'!D105)),0) -> #DIV/0! | AV105: =IF('Entrada e Saida'!$H$13="NÃO",AU105*M105,0) -> #DIV/0! | AW105: =AU105+AV105 -> #DIV/0! | AX105: ='Entrada e Saida'!$G$74*AU105 -> #DIV/0! | AY105: =AW105-AX105 -> #DIV/0! | AZ105: =AQ105+('Entrada e Saida'!$G$65-'Entrada e Saida'!$I$65)*AU105-AX105 -> #DIV/0! | BA105: =IF('Entrada e Saida'!$H$12="REAL",AZ105*'Entrada e Saida'!$G$81,AU105*'Entrada e Saida'!$G$81) -> #DIV/0! | BB105: =IF('Entrada e Saida'!$H$12="REAL",AZ105*'Entrada e Saida'!$G$82,AU105*'Entrada e Saida'!$G$82) -> #DIV/0! | BC105: =AZ105-BA105-BB105 -> #DIV/0! | BD105: =IF('Entrada e Saida'!$H$11="TRADING",AW105/D105,AK105/D105) -> #DIV/0! | BE105: =AX105/D105 -> #DIV/0! | BF105: =BD105-BE105 -> #DIV/0! | BG105: =IF('Entrada e Saida'!$H$11="TRADING",AV105/D105,AN105/D105) -> #DIV/0! | BH105: =IF('Entrada e Saida'!$H$11="TRADING",IF('Entrada e Saida'!$H$12="REAL",AR105/D105,0),AL105/D105) -> #DIV/0! | BI105: =IF('Entrada e Saida'!$H$11="TRADING",IF('Entrada e Saida'!$H$12="REAL",AS105/D105,0),AM105/D105) -> #DIV/0! | BJ105: =IF('Entrada e Saida'!$H$11="TRADING",AT105/D105,AO105/D105) -> #DIV/0! | BK105: =BF105-SUM(BG105:BJ105) -> #DIV/0! | BL105: =IF(O105>0,IFERROR(IF('Entrada e Saida'!$H$11="DIRETA",0,(IF('Entrada e Saida'!$H$14="P.JURIDICA",(BD105*(1+O105)*N105)-((BD105/(1+M105))*'Entrada e Saida'!$G$65),((Produtos!N105-'Entrada e Saida'!$G$65)*Produtos!BD105)))),0),0) -> 0 | BM105: =BF105+BL105 -> #DIV/0!
E106: =IFERROR(VLOOKUP(A106,'Master Modelo'!A:I,9,FALSE),0) -> 0 | F106: =IFERROR(VLOOKUP(A106,'Master Modelo'!A:I,8,FALSE),0) -> 0 | G106: =IFERROR(VLOOKUP(A106,'Master Modelo'!A:K,11,FALSE),0) -> 0 | H106: =(D106*E106)/(D106*F106) -> #DIV/0! | I106: =IFERROR(VLOOKUP(A106,'Master Modelo'!A:I,3,FALSE),0) -> 0 | J106: =IFERROR(VLOOKUP(A106,'Master Modelo'!A:I,5,FALSE),0) -> 0 | K106: =IFERROR(VLOOKUP(A106,'Master Modelo'!A:I,6,FALSE),0) -> 0 | L106: =VLOOKUP(A106,'Master Modelo'!A:J,10,FALSE) -> #N/A | M106: =IFERROR(VLOOKUP(A106,'Master Modelo'!A:I,4,FALSE),0) -> 0 | P106: =D106*F106 -> 0 | Q106: =D106*G106 -> 0 | R106: =D106*E106*'Entrada e Saida'!$K$8 -> 0 | S106: ='Entrada e Saida'!$H$21*'Entrada e Saida'!$K$8*(P106/(SUM(P:P))) -> #DIV/0! | T106: ='Entrada e Saida'!$H$21*'Entrada e Saida'!$K$8*(Q106/(SUM(Q:Q))) -> #DIV/0! | U106: ='Entrada e Saida'!$H$22*(P106/(SUM(P:P))) -> #DIV/0! | V106: ='Entrada e Saida'!$H$22*(Q106/(SUM(Q:Q))) -> #DIV/0! | W106: =R106+S106+U106 -> #DIV/0! | X106: ='Entrada e Saida'!$H$26*(IF('Entrada e Saida'!$H$15="PESO",(P106/(SUM(P:P))),(Q106/(SUM(Q:Q))))) -> #DIV/0! | Y106: ='Entrada e Saida'!$H$27*(IF('Entrada e Saida'!$H$15="PESO",(P106/(SUM(P:P))),(Q106/(SUM(Q:Q))))) -> #DIV/0! | Z106: ='Entrada e Saida'!$H$28*(IF('Entrada e Saida'!$H$15="PESO",(P106/(SUM(P:P))),(Q106/(SUM(Q:Q))))) -> #DIV/0! | AA106: =X106+Y106+Z106 -> #DIV/0! | AB106: =W106*I106 -> #DIV/0! | AC106: =W106*J106 -> #DIV/0! | AD106: =W106*K106 -> #DIV/0! | AE106: =(W106+AB106)*M106 -> #DIV/0! | AF106: =IFERROR(D106*F106*L106*'Entrada e Saida'!$K$8,0) -> 0 | AG106: =((W106+AA106+AB106+AC106+AD106+AE106+AF106)/(1-'Entrada e Saida'!$G$65))*'Entrada e Saida'!$I$66 -> #DIV/0! | AH106: =SUM(AB106:AG106) -> #DIV/0! | AI106: ='Entrada e Saida'!$K$51*(IF('Entrada e Saida'!$H$15="PESO",(P106/(SUM(P:P))),(Q106/(SUM(Q:Q))))) -> #DIV/0! | AJ106: =(('Entrada e Saida'!$K$10-'Entrada e Saida'!$K$8)*E106*D106) -> 0 | AK106: =IF('Entrada e Saida'!$H$15="PESO",W106+AA106+AH106+AI106+AJ106,W106+AA106+AH106+AI106+AJ106-S106+T106-U106+V106) -> #DIV/0! | AL106: =IF('Entrada e Saida'!$H$12="REAL",AC106,0) -> #DIV/0! | AM106: =IF('Entrada e Saida'!$H$12="REAL",AD106,0) -> #DIV/0! | AN106: =IF('Entrada e Saida'!$H$13= "NÃO",AE106,0) -> #DIV/0! | AO106: =AG106 -> #DIV/0! | AP106: =AK106-SUM(AL106:AO106) -> #DIV/0! | AQ106: =IF('Entrada e Saida'!$H$11="TRADING",AU106*'Custo Resumido'!D106,0) -> #DIV/0! | AR106: =IF('Entrada e Saida'!$H$11="TRADING",AU106*'Entrada e Saida'!$G$63,0) -> #DIV/0! | AS106: =IF('Entrada e Saida'!$H$11="TRADING",AU106*'Entrada e Saida'!$G$64,0) -> #DIV/0! | AT106: =IF('Entrada e Saida'!$H$11="TRADING",AU106*'Entrada e Saida'!$G$65,0) -> #DIV/0! | AU106: =IF('Entrada e Saida'!$H$11="TRADING",AP106/(1-(SUM('Entrada e Saida'!$G$63:$G$65)+'Custo Resumido'!D106)),0) -> #DIV/0! | AV106: =IF('Entrada e Saida'!$H$13="NÃO",AU106*M106,0) -> #DIV/0! | AW106: =AU106+AV106 -> #DIV/0! | AX106: ='Entrada e Saida'!$G$74*AU106 -> #DIV/0! | AY106: =AW106-AX106 -> #DIV/0! | AZ106: =AQ106+('Entrada e Saida'!$G$65-'Entrada e Saida'!$I$65)*AU106-AX106 -> #DIV/0! | BA106: =IF('Entrada e Saida'!$H$12="REAL",AZ106*'Entrada e Saida'!$G$81,AU106*'Entrada e Saida'!$G$81) -> #DIV/0! | BB106: =IF('Entrada e Saida'!$H$12="REAL",AZ106*'Entrada e Saida'!$G$82,AU106*'Entrada e Saida'!$G$82) -> #DIV/0! | BC106: =AZ106-BA106-BB106 -> #DIV/0! | BD106: =IF('Entrada e Saida'!$H$11="TRADING",AW106/D106,AK106/D106) -> #DIV/0! | BE106: =AX106/D106 -> #DIV/0! | BF106: =BD106-BE106 -> #DIV/0! | BG106: =IF('Entrada e Saida'!$H$11="TRADING",AV106/D106,AN106/D106) -> #DIV/0! | BH106: =IF('Entrada e Saida'!$H$11="TRADING",IF('Entrada e Saida'!$H$12="REAL",AR106/D106,0),AL106/D106) -> #DIV/0! | BI106: =IF('Entrada e Saida'!$H$11="TRADING",IF('Entrada e Saida'!$H$12="REAL",AS106/D106,0),AM106/D106) -> #DIV/0! | BJ106: =IF('Entrada e Saida'!$H$11="TRADING",AT106/D106,AO106/D106) -> #DIV/0! | BK106: =BF106-SUM(BG106:BJ106) -> #DIV/0! | BL106: =IF(O106>0,IFERROR(IF('Entrada e Saida'!$H$11="DIRETA",0,(IF('Entrada e Saida'!$H$14="P.JURIDICA",(BD106*(1+O106)*N106)-((BD106/(1+M106))*'Entrada e Saida'!$G$65),((Produtos!N106-'Entrada e Saida'!$G$65)*Produtos!BD106)))),0),0) -> 0 | BM106: =BF106+BL106 -> #DIV/0!
E107: =IFERROR(VLOOKUP(A107,'Master Modelo'!A:I,9,FALSE),0) -> 0 | F107: =IFERROR(VLOOKUP(A107,'Master Modelo'!A:I,8,FALSE),0) -> 0 | G107: =IFERROR(VLOOKUP(A107,'Master Modelo'!A:K,11,FALSE),0) -> 0 | H107: =(D107*E107)/(D107*F107) -> #DIV/0! | I107: =IFERROR(VLOOKUP(A107,'Master Modelo'!A:I,3,FALSE),0) -> 0 | J107: =IFERROR(VLOOKUP(A107,'Master Modelo'!A:I,5,FALSE),0) -> 0 | K107: =IFERROR(VLOOKUP(A107,'Master Modelo'!A:I,6,FALSE),0) -> 0 | L107: =VLOOKUP(A107,'Master Modelo'!A:J,10,FALSE) -> #N/A | M107: =IFERROR(VLOOKUP(A107,'Master Modelo'!A:I,4,FALSE),0) -> 0 | P107: =D107*F107 -> 0 | Q107: =D107*G107 -> 0 | R107: =D107*E107*'Entrada e Saida'!$K$8 -> 0 | S107: ='Entrada e Saida'!$H$21*'Entrada e Saida'!$K$8*(P107/(SUM(P:P))) -> #DIV/0! | T107: ='Entrada e Saida'!$H$21*'Entrada e Saida'!$K$8*(Q107/(SUM(Q:Q))) -> #DIV/0! | U107: ='Entrada e Saida'!$H$22*(P107/(SUM(P:P))) -> #DIV/0! | V107: ='Entrada e Saida'!$H$22*(Q107/(SUM(Q:Q))) -> #DIV/0! | W107: =R107+S107+U107 -> #DIV/0! | X107: ='Entrada e Saida'!$H$26*(IF('Entrada e Saida'!$H$15="PESO",(P107/(SUM(P:P))),(Q107/(SUM(Q:Q))))) -> #DIV/0! | Y107: ='Entrada e Saida'!$H$27*(IF('Entrada e Saida'!$H$15="PESO",(P107/(SUM(P:P))),(Q107/(SUM(Q:Q))))) -> #DIV/0! | Z107: ='Entrada e Saida'!$H$28*(IF('Entrada e Saida'!$H$15="PESO",(P107/(SUM(P:P))),(Q107/(SUM(Q:Q))))) -> #DIV/0! | AA107: =X107+Y107+Z107 -> #DIV/0! | AB107: =W107*I107 -> #DIV/0! | AC107: =W107*J107 -> #DIV/0! | AD107: =W107*K107 -> #DIV/0! | AE107: =(W107+AB107)*M107 -> #DIV/0! | AF107: =IFERROR(D107*F107*L107*'Entrada e Saida'!$K$8,0) -> 0 | AG107: =((W107+AA107+AB107+AC107+AD107+AE107+AF107)/(1-'Entrada e Saida'!$G$65))*'Entrada e Saida'!$I$66 -> #DIV/0! | AH107: =SUM(AB107:AG107) -> #DIV/0! | AI107: ='Entrada e Saida'!$K$51*(IF('Entrada e Saida'!$H$15="PESO",(P107/(SUM(P:P))),(Q107/(SUM(Q:Q))))) -> #DIV/0! | AJ107: =(('Entrada e Saida'!$K$10-'Entrada e Saida'!$K$8)*E107*D107) -> 0 | AK107: =IF('Entrada e Saida'!$H$15="PESO",W107+AA107+AH107+AI107+AJ107,W107+AA107+AH107+AI107+AJ107-S107+T107-U107+V107) -> #DIV/0! | AL107: =IF('Entrada e Saida'!$H$12="REAL",AC107,0) -> #DIV/0! | AM107: =IF('Entrada e Saida'!$H$12="REAL",AD107,0) -> #DIV/0! | AN107: =IF('Entrada e Saida'!$H$13= "NÃO",AE107,0) -> #DIV/0! | AO107: =AG107 -> #DIV/0! | AP107: =AK107-SUM(AL107:AO107) -> #DIV/0! | AQ107: =IF('Entrada e Saida'!$H$11="TRADING",AU107*'Custo Resumido'!D107,0) -> #DIV/0! | AR107: =IF('Entrada e Saida'!$H$11="TRADING",AU107*'Entrada e Saida'!$G$63,0) -> #DIV/0! | AS107: =IF('Entrada e Saida'!$H$11="TRADING",AU107*'Entrada e Saida'!$G$64,0) -> #DIV/0! | AT107: =IF('Entrada e Saida'!$H$11="TRADING",AU107*'Entrada e Saida'!$G$65,0) -> #DIV/0! | AU107: =IF('Entrada e Saida'!$H$11="TRADING",AP107/(1-(SUM('Entrada e Saida'!$G$63:$G$65)+'Custo Resumido'!D107)),0) -> #DIV/0! | AV107: =IF('Entrada e Saida'!$H$13="NÃO",AU107*M107,0) -> #DIV/0! | AW107: =AU107+AV107 -> #DIV/0! | AX107: ='Entrada e Saida'!$G$74*AU107 -> #DIV/0! | AY107: =AW107-AX107 -> #DIV/0! | AZ107: =AQ107+('Entrada e Saida'!$G$65-'Entrada e Saida'!$I$65)*AU107-AX107 -> #DIV/0! | BA107: =IF('Entrada e Saida'!$H$12="REAL",AZ107*'Entrada e Saida'!$G$81,AU107*'Entrada e Saida'!$G$81) -> #DIV/0! | BB107: =IF('Entrada e Saida'!$H$12="REAL",AZ107*'Entrada e Saida'!$G$82,AU107*'Entrada e Saida'!$G$82) -> #DIV/0! | BC107: =AZ107-BA107-BB107 -> #DIV/0! | BD107: =IF('Entrada e Saida'!$H$11="TRADING",AW107/D107,AK107/D107) -> #DIV/0! | BE107: =AX107/D107 -> #DIV/0! | BF107: =BD107-BE107 -> #DIV/0! | BG107: =IF('Entrada e Saida'!$H$11="TRADING",AV107/D107,AN107/D107) -> #DIV/0! | BH107: =IF('Entrada e Saida'!$H$11="TRADING",IF('Entrada e Saida'!$H$12="REAL",AR107/D107,0),AL107/D107) -> #DIV/0! | BI107: =IF('Entrada e Saida'!$H$11="TRADING",IF('Entrada e Saida'!$H$12="REAL",AS107/D107,0),AM107/D107) -> #DIV/0! | BJ107: =IF('Entrada e Saida'!$H$11="TRADING",AT107/D107,AO107/D107) -> #DIV/0! | BK107: =BF107-SUM(BG107:BJ107) -> #DIV/0! | BL107: =IF(O107>0,IFERROR(IF('Entrada e Saida'!$H$11="DIRETA",0,(IF('Entrada e Saida'!$H$14="P.JURIDICA",(BD107*(1+O107)*N107)-((BD107/(1+M107))*'Entrada e Saida'!$G$65),((Produtos!N107-'Entrada e Saida'!$G$65)*Produtos!BD107)))),0),0) -> 0 | BM107: =BF107+BL107 -> #DIV/0!
E108: =IFERROR(VLOOKUP(A108,'Master Modelo'!A:I,9,FALSE),0) -> 0 | F108: =IFERROR(VLOOKUP(A108,'Master Modelo'!A:I,8,FALSE),0) -> 0 | G108: =IFERROR(VLOOKUP(A108,'Master Modelo'!A:K,11,FALSE),0) -> 0 | H108: =(D108*E108)/(D108*F108) -> #DIV/0! | I108: =IFERROR(VLOOKUP(A108,'Master Modelo'!A:I,3,FALSE),0) -> 0 | J108: =IFERROR(VLOOKUP(A108,'Master Modelo'!A:I,5,FALSE),0) -> 0 | K108: =IFERROR(VLOOKUP(A108,'Master Modelo'!A:I,6,FALSE),0) -> 0 | L108: =VLOOKUP(A108,'Master Modelo'!A:J,10,FALSE) -> #N/A | M108: =IFERROR(VLOOKUP(A108,'Master Modelo'!A:I,4,FALSE),0) -> 0 | P108: =D108*F108 -> 0 | Q108: =D108*G108 -> 0 | R108: =D108*E108*'Entrada e Saida'!$K$8 -> 0 | S108: ='Entrada e Saida'!$H$21*'Entrada e Saida'!$K$8*(P108/(SUM(P:P))) -> #DIV/0! | T108: ='Entrada e Saida'!$H$21*'Entrada e Saida'!$K$8*(Q108/(SUM(Q:Q))) -> #DIV/0! | U108: ='Entrada e Saida'!$H$22*(P108/(SUM(P:P))) -> #DIV/0! | V108: ='Entrada e Saida'!$H$22*(Q108/(SUM(Q:Q))) -> #DIV/0! | W108: =R108+S108+U108 -> #DIV/0! | X108: ='Entrada e Saida'!$H$26*(IF('Entrada e Saida'!$H$15="PESO",(P108/(SUM(P:P))),(Q108/(SUM(Q:Q))))) -> #DIV/0! | Y108: ='Entrada e Saida'!$H$27*(IF('Entrada e Saida'!$H$15="PESO",(P108/(SUM(P:P))),(Q108/(SUM(Q:Q))))) -> #DIV/0! | Z108: ='Entrada e Saida'!$H$28*(IF('Entrada e Saida'!$H$15="PESO",(P108/(SUM(P:P))),(Q108/(SUM(Q:Q))))) -> #DIV/0! | AA108: =X108+Y108+Z108 -> #DIV/0! | AB108: =W108*I108 -> #DIV/0! | AC108: =W108*J108 -> #DIV/0! | AD108: =W108*K108 -> #DIV/0! | AE108: =(W108+AB108)*M108 -> #DIV/0! | AF108: =IFERROR(D108*F108*L108*'Entrada e Saida'!$K$8,0) -> 0 | AG108: =((W108+AA108+AB108+AC108+AD108+AE108+AF108)/(1-'Entrada e Saida'!$G$65))*'Entrada e Saida'!$I$66 -> #DIV/0! | AH108: =SUM(AB108:AG108) -> #DIV/0! | AI108: ='Entrada e Saida'!$K$51*(IF('Entrada e Saida'!$H$15="PESO",(P108/(SUM(P:P))),(Q108/(SUM(Q:Q))))) -> #DIV/0! | AJ108: =(('Entrada e Saida'!$K$10-'Entrada e Saida'!$K$8)*E108*D108) -> 0 | AK108: =IF('Entrada e Saida'!$H$15="PESO",W108+AA108+AH108+AI108+AJ108,W108+AA108+AH108+AI108+AJ108-S108+T108-U108+V108) -> #DIV/0! | AL108: =IF('Entrada e Saida'!$H$12="REAL",AC108,0) -> #DIV/0! | AM108: =IF('Entrada e Saida'!$H$12="REAL",AD108,0) -> #DIV/0! | AN108: =IF('Entrada e Saida'!$H$13= "NÃO",AE108,0) -> #DIV/0! | AO108: =AG108 -> #DIV/0! | AP108: =AK108-SUM(AL108:AO108) -> #DIV/0! | AQ108: =IF('Entrada e Saida'!$H$11="TRADING",AU108*'Custo Resumido'!D108,0) -> #DIV/0! | AR108: =IF('Entrada e Saida'!$H$11="TRADING",AU108*'Entrada e Saida'!$G$63,0) -> #DIV/0! | AS108: =IF('Entrada e Saida'!$H$11="TRADING",AU108*'Entrada e Saida'!$G$64,0) -> #DIV/0! | AT108: =IF('Entrada e Saida'!$H$11="TRADING",AU108*'Entrada e Saida'!$G$65,0) -> #DIV/0! | AU108: =IF('Entrada e Saida'!$H$11="TRADING",AP108/(1-(SUM('Entrada e Saida'!$G$63:$G$65)+'Custo Resumido'!D108)),0) -> #DIV/0! | AV108: =IF('Entrada e Saida'!$H$13="NÃO",AU108*M108,0) -> #DIV/0! | AW108: =AU108+AV108 -> #DIV/0! | AX108: ='Entrada e Saida'!$G$74*AU108 -> #DIV/0! | AY108: =AW108-AX108 -> #DIV/0! | AZ108: =AQ108+('Entrada e Saida'!$G$65-'Entrada e Saida'!$I$65)*AU108-AX108 -> #DIV/0! | BA108: =IF('Entrada e Saida'!$H$12="REAL",AZ108*'Entrada e Saida'!$G$81,AU108*'Entrada e Saida'!$G$81) -> #DIV/0! | BB108: =IF('Entrada e Saida'!$H$12="REAL",AZ108*'Entrada e Saida'!$G$82,AU108*'Entrada e Saida'!$G$82) -> #DIV/0! | BC108: =AZ108-BA108-BB108 -> #DIV/0! | BD108: =IF('Entrada e Saida'!$H$11="TRADING",AW108/D108,AK108/D108) -> #DIV/0! | BE108: =AX108/D108 -> #DIV/0! | BF108: =BD108-BE108 -> #DIV/0! | BG108: =IF('Entrada e Saida'!$H$11="TRADING",AV108/D108,AN108/D108) -> #DIV/0! | BH108: =IF('Entrada e Saida'!$H$11="TRADING",IF('Entrada e Saida'!$H$12="REAL",AR108/D108,0),AL108/D108) -> #DIV/0! | BI108: =IF('Entrada e Saida'!$H$11="TRADING",IF('Entrada e Saida'!$H$12="REAL",AS108/D108,0),AM108/D108) -> #DIV/0! | BJ108: =IF('Entrada e Saida'!$H$11="TRADING",AT108/D108,AO108/D108) -> #DIV/0! | BK108: =BF108-SUM(BG108:BJ108) -> #DIV/0! | BL108: =IF(O108>0,IFERROR(IF('Entrada e Saida'!$H$11="DIRETA",0,(IF('Entrada e Saida'!$H$14="P.JURIDICA",(BD108*(1+O108)*N108)-((BD108/(1+M108))*'Entrada e Saida'!$G$65),((Produtos!N108-'Entrada e Saida'!$G$65)*Produtos!BD108)))),0),0) -> 0 | BM108: =BF108+BL108 -> #DIV/0!
... E350: =IFERROR(VLOOKUP(A350,'Master Modelo'!A:I,9,FALSE),0) -> 0 | F350: =IFERROR(VLOOKUP(A350,'Master Modelo'!A:I,8,FALSE),0) -> 0 | G350: =IFERROR(VLOOKUP(A350,'Master Modelo'!A:K,11,FALSE),0) -> 0 | H350: =(D350*E350)/(D350*F350) -> #DIV/0! | I350: =IFERROR(VLOOKUP(A350,'Master Modelo'!A:I,3,FALSE),0) -> 0 | J350: =IFERROR(VLOOKUP(A350,'Master Modelo'!A:I,5,FALSE),0) -> 0 | K350: =IFERROR(VLOOKUP(A350,'Master Modelo'!A:I,6,FALSE),0) -> 0 | L350: =VLOOKUP(A350,'Master Modelo'!A:J,10,FALSE) -> #N/A | M350: =IFERROR(VLOOKUP(A350,'Master Modelo'!A:I,4,FALSE),0) -> 0 | P350: =D350*F350 -> 0 | Q350: =D350*G350 -> 0 | R350: =D350*E350*'Entrada e Saida'!$K$8 -> 0 | S350: ='Entrada e Saida'!$H$21*'Entrada e Saida'!$K$8*(P350/(SUM(P:P))) -> #DIV/0! | T350: ='Entrada e Saida'!$H$21*'Entrada e Saida'!$K$8*(Q350/(SUM(Q:Q))) -> #DIV/0! | U350: ='Entrada e Saida'!$H$22*(P350/(SUM(P:P))) -> #DIV/0! | V350: ='Entrada e Saida'!$H$22*(Q350/(SUM(Q:Q))) -> #DIV/0! | W350: =R350+S350+U350 -> #DIV/0! | X350: ='Entrada e Saida'!$H$26*(IF('Entrada e Saida'!$H$15="PESO",(P350/(SUM(P:P))),(Q350/(SUM(Q:Q))))) -> #DIV/0! | Y350: ='Entrada e Saida'!$H$27*(IF('Entrada e Saida'!$H$15="PESO",(P350/(SUM(P:P))),(Q350/(SUM(Q:Q))))) -> #DIV/0! | Z350: ='Entrada e Saida'!$H$28*(IF('Entrada e Saida'!$H$15="PESO",(P350/(SUM(P:P))),(Q350/(SUM(Q:Q))))) -> #DIV/0! | AA350: =X350+Y350+Z350 -> #DIV/0! | AB350: =W350*I350 -> #DIV/0! | AC350: =W350*J350 -> #DIV/0! | AD350: =W350*K350 -> #DIV/0! | AE350: =(W350+AB350)*M350 -> #DIV/0! | AF350: =IFERROR(D350*F350*L350*'Entrada e Saida'!$K$8,0) -> 0 | AG350: =((W350+AA350+AB350+AC350+AD350+AE350+AF350)/(1-'Entrada e Saida'!$G$65))*'Entrada e Saida'!$I$66 -> #DIV/0! | AH350: =SUM(AB350:AG350) -> #DIV/0! | AI350: ='Entrada e Saida'!$K$51*(IF('Entrada e Saida'!$H$15="PESO",(P350/(SUM(P:P))),(Q350/(SUM(Q:Q))))) -> #DIV/0! | AJ350: =(('Entrada e Saida'!$K$10-'Entrada e Saida'!$K$8)*E350*D350) -> 0 | AK350: =IF('Entrada e Saida'!$H$15="PESO",W350+AA350+AH350+AI350+AJ350,W350+AA350+AH350+AI350+AJ350-S350+T350-U350+V350) -> #DIV/0! | AL350: =IF('Entrada e Saida'!$H$12="REAL",AC350,0) -> #DIV/0! | AM350: =IF('Entrada e Saida'!$H$12="REAL",AD350,0) -> #DIV/0! | AN350: =IF('Entrada e Saida'!$H$13= "NÃO",AE350,0) -> #DIV/0! | AO350: =AG350 -> #DIV/0! | AP350: =AK350-SUM(AL350:AO350) -> #DIV/0! | AQ350: =IF('Entrada e Saida'!$H$11="TRADING",AU350*'Custo Resumido'!D350,0) -> #DIV/0! | AR350: =IF('Entrada e Saida'!$H$11="TRADING",AU350*'Entrada e Saida'!$G$63,0) -> #DIV/0! | AS350: =IF('Entrada e Saida'!$H$11="TRADING",AU350*'Entrada e Saida'!$G$64,0) -> #DIV/0! | AT350: =IF('Entrada e Saida'!$H$11="TRADING",AU350*'Entrada e Saida'!$G$65,0) -> #DIV/0! | AU350: =IF('Entrada e Saida'!$H$11="TRADING",AP350/(1-(SUM('Entrada e Saida'!$G$63:$G$65)+'Custo Resumido'!D350)),0) -> #DIV/0! | AV350: =IF('Entrada e Saida'!$H$13="NÃO",AU350*M350,0) -> #DIV/0! | AW350: =AU350+AV350 -> #DIV/0! | AX350: ='Entrada e Saida'!$G$74*AU350 -> #DIV/0! | AY350: =AW350-AX350 -> #DIV/0! | AZ350: =AQ350+('Entrada e Saida'!$G$65-'Entrada e Saida'!$I$65)*AU350-AX350 -> #DIV/0! | BA350: =IF('Entrada e Saida'!$H$12="REAL",AZ350*'Entrada e Saida'!$G$81,AU350*'Entrada e Saida'!$G$81) -> #DIV/0! | BB350: =IF('Entrada e Saida'!$H$12="REAL",AZ350*'Entrada e Saida'!$G$82,AU350*'Entrada e Saida'!$G$82) -> #DIV/0! | BC350: =AZ350-BA350-BB350 -> #DIV/0! | BD350: =IF('Entrada e Saida'!$H$11="TRADING",AW350/D350,AK350/D350) -> #DIV/0! | BE350: =AX350/D350 -> #DIV/0! | BF350: =BD350-BE350 -> #DIV/0! | BG350: =IF('Entrada e Saida'!$H$11="TRADING",AV350/D350,AN350/D350) -> #DIV/0! | BH350: =IF('Entrada e Saida'!$H$11="TRADING",IF('Entrada e Saida'!$H$12="REAL",AR350/D350,0),AL350/D350) -> #DIV/0! | BI350: =IF('Entrada e Saida'!$H$11="TRADING",IF('Entrada e Saida'!$H$12="REAL",AS350/D350,0),AM350/D350) -> #DIV/0! | BJ350: =IF('Entrada e Saida'!$H$11="TRADING",AT350/D350,AO350/D350) -> #DIV/0! | BK350: =BF350-SUM(BG350:BJ350) -> #DIV/0! | BL350: =IF(O350>0,IFERROR(IF('Entrada e Saida'!$H$11="DIRETA",0,(IF('Entrada e Saida'!$H$14="P.JURIDICA",(BD350*(1+O350)*N350)-((BD350/(1+M350))*'Entrada e Saida'!$G$65),((Produtos!N350-'Entrada e Saida'!$G$65)*Produtos!BD350)))),0),0) -> 0 | BM350: =BF350+BL350 -> #DIV/0!
B351: =IFERROR(VLOOKUP(A351,'Master Modelo'!A:I,7,FALSE),0) -> 0 | C351: =IFERROR(VLOOKUP(A351,'Master Modelo'!A:I,2,FALSE),0) -> 0 | E351: =IFERROR(VLOOKUP(A351,'Master Modelo'!A:I,9,FALSE),0) -> 0 | F351: =IFERROR(VLOOKUP(A351,'Master Modelo'!A:I,8,FALSE),0) -> 0 | G351: =IFERROR(VLOOKUP(A351,'Master Modelo'!A:K,11,FALSE),0) -> 0 | H351: =(D351*E351)/(D351*F351) -> #DIV/0! | I351: =IFERROR(VLOOKUP(A351,'Master Modelo'!A:I,3,FALSE),0) -> 0 | J351: =IFERROR(VLOOKUP(A351,'Master Modelo'!A:I,5,FALSE),0) -> 0 | K351: =IFERROR(VLOOKUP(A351,'Master Modelo'!A:I,6,FALSE),0) -> 0 | L351: =VLOOKUP(A351,'Master Modelo'!A:J,10,FALSE) -> #N/A | M351: =IFERROR(VLOOKUP(A351,'Master Modelo'!A:I,4,FALSE),0) -> 0 | P351: =D351*F351 -> 0 | Q351: =D351*G351 -> 0 | R351: =D351*E351*'Entrada e Saida'!$K$8 -> 0 | S351: ='Entrada e Saida'!$H$21*'Entrada e Saida'!$K$8*(P351/(SUM(P:P))) -> #DIV/0! | T351: ='Entrada e Saida'!$H$21*'Entrada e Saida'!$K$8*(Q351/(SUM(Q:Q))) -> #DIV/0! | U351: ='Entrada e Saida'!$H$22*(P351/(SUM(P:P))) -> #DIV/0! | V351: ='Entrada e Saida'!$H$22*(Q351/(SUM(Q:Q))) -> #DIV/0! | W351: =R351+S351+U351 -> #DIV/0! | X351: ='Entrada e Saida'!$H$26*(IF('Entrada e Saida'!$H$15="PESO",(P351/(SUM(P:P))),(Q351/(SUM(Q:Q))))) -> #DIV/0! | Y351: ='Entrada e Saida'!$H$27*(IF('Entrada e Saida'!$H$15="PESO",(P351/(SUM(P:P))),(Q351/(SUM(Q:Q))))) -> #DIV/0! | Z351: ='Entrada e Saida'!$H$28*(IF('Entrada e Saida'!$H$15="PESO",(P351/(SUM(P:P))),(Q351/(SUM(Q:Q))))) -> #DIV/0! | AA351: =X351+Y351+Z351 -> #DIV/0! | AB351: =W351*I351 -> #DIV/0! | AC351: =W351*J351 -> #DIV/0! | AD351: =W351*K351 -> #DIV/0! | AE351: =(W351+AB351)*M351 -> #DIV/0! | AF351: =IFERROR(D351*F351*L351*'Entrada e Saida'!$K$8,0) -> 0 | AG351: =((W351+AA351+AB351+AC351+AD351+AE351+AF351)/(1-'Entrada e Saida'!$G$65))*'Entrada e Saida'!$I$66 -> #DIV/0! | AH351: =SUM(AB351:AG351) -> #DIV/0! | AI351: ='Entrada e Saida'!$K$51*(IF('Entrada e Saida'!$H$15="PESO",(P351/(SUM(P:P))),(Q351/(SUM(Q:Q))))) -> #DIV/0! | AJ351: =(('Entrada e Saida'!$K$10-'Entrada e Saida'!$K$8)*E351*D351) -> 0 | AK351: =IF('Entrada e Saida'!$H$15="PESO",W351+AA351+AH351+AI351+AJ351,W351+AA351+AH351+AI351+AJ351-S351+T351-U351+V351) -> #DIV/0! | AL351: =IF('Entrada e Saida'!$H$12="REAL",AC351,0) -> #DIV/0! | AM351: =IF('Entrada e Saida'!$H$12="REAL",AD351,0) -> #DIV/0! | AN351: =IF('Entrada e Saida'!$H$13= "NÃO",AE351,0) -> #DIV/0! | AO351: =AG351 -> #DIV/0! | AP351: =AK351-SUM(AL351:AO351) -> #DIV/0! | AQ351: =IF('Entrada e Saida'!$H$11="TRADING",AU351*'Custo Resumido'!D351,0) -> #DIV/0! | AR351: =IF('Entrada e Saida'!$H$11="TRADING",AU351*'Entrada e Saida'!$G$63,0) -> #DIV/0! | AS351: =IF('Entrada e Saida'!$H$11="TRADING",AU351*'Entrada e Saida'!$G$64,0) -> #DIV/0! | AT351: =IF('Entrada e Saida'!$H$11="TRADING",AU351*'Entrada e Saida'!$G$65,0) -> #DIV/0! | AU351: =IF('Entrada e Saida'!$H$11="TRADING",AP351/(1-(SUM('Entrada e Saida'!$G$63:$G$65)+'Custo Resumido'!D351)),0) -> #DIV/0! | AV351: =IF('Entrada e Saida'!$H$13="NÃO",AU351*M351,0) -> #DIV/0! | AW351: =AU351+AV351 -> #DIV/0! | AX351: ='Entrada e Saida'!$G$74*AU351 -> #DIV/0! | AY351: =AW351-AX351 -> #DIV/0! | AZ351: =AQ351+('Entrada e Saida'!$G$65-'Entrada e Saida'!$I$65)*AU351-AX351 -> #DIV/0! | BA351: =IF('Entrada e Saida'!$H$12="REAL",AZ351*'Entrada e Saida'!$G$81,AU351*'Entrada e Saida'!$G$81) -> #DIV/0! | BB351: =IF('Entrada e Saida'!$H$12="REAL",AZ351*'Entrada e Saida'!$G$82,AU351*'Entrada e Saida'!$G$82) -> #DIV/0! | BC351: =AZ351-BA351-BB351 -> #DIV/0! | BD351: =IF('Entrada e Saida'!$H$11="TRADING",AW351/D351,AK351/D351) -> #DIV/0! | BE351: =AX351/D351 -> #DIV/0! | BF351: =BD351-BE351 -> #DIV/0! | BG351: =IF('Entrada e Saida'!$H$11="TRADING",AV351/D351,AN351/D351) -> #DIV/0! | BH351: =IF('Entrada e Saida'!$H$11="TRADING",IF('Entrada e Saida'!$H$12="REAL",AR351/D351,0),AL351/D351) -> #DIV/0! | BI351: =IF('Entrada e Saida'!$H$11="TRADING",IF('Entrada e Saida'!$H$12="REAL",AS351/D351,0),AM351/D351) -> #DIV/0! | BJ351: =IF('Entrada e Saida'!$H$11="TRADING",AT351/D351,AO351/D351) -> #DIV/0! | BK351: =BF351-SUM(BG351:BJ351) -> #DIV/0! | BL351: =IF(O351>0,IFERROR(IF('Entrada e Saida'!$H$11="DIRETA",0,(IF('Entrada e Saida'!$H$14="P.JURIDICA",(BD351*(1+O351)*N351)-((BD351/(1+M351))*'Entrada e Saida'!$G$65),((Produtos!N351-'Entrada e Saida'!$G$65)*Produtos!BD351)))),0),0) -> 0 | BM351: =BF351+BL351 -> #DIV/0!
B352: =IFERROR(VLOOKUP(A352,'Master Modelo'!A:I,7,FALSE),0) -> 0 | C352: =IFERROR(VLOOKUP(A352,'Master Modelo'!A:I,2,FALSE),0) -> 0 | E352: =IFERROR(VLOOKUP(A352,'Master Modelo'!A:I,9,FALSE),0) -> 0 | F352: =IFERROR(VLOOKUP(A352,'Master Modelo'!A:I,8,FALSE),0) -> 0 | G352: =IFERROR(VLOOKUP(A352,'Master Modelo'!A:K,11,FALSE),0) -> 0 | H352: =(D352*E352)/(D352*F352) -> #DIV/0! | I352: =IFERROR(VLOOKUP(A352,'Master Modelo'!A:I,3,FALSE),0) -> 0 | J352: =IFERROR(VLOOKUP(A352,'Master Modelo'!A:I,5,FALSE),0) -> 0 | K352: =IFERROR(VLOOKUP(A352,'Master Modelo'!A:I,6,FALSE),0) -> 0 | L352: =VLOOKUP(A352,'Master Modelo'!A:J,10,FALSE) -> #N/A | M352: =IFERROR(VLOOKUP(A352,'Master Modelo'!A:I,4,FALSE),0) -> 0 | P352: =D352*F352 -> 0 | Q352: =D352*G352 -> 0 | R352: =D352*E352*'Entrada e Saida'!$K$8 -> 0 | S352: ='Entrada e Saida'!$H$21*'Entrada e Saida'!$K$8*(P352/(SUM(P:P))) -> #DIV/0! | T352: ='Entrada e Saida'!$H$21*'Entrada e Saida'!$K$8*(Q352/(SUM(Q:Q))) -> #DIV/0! | U352: ='Entrada e Saida'!$H$22*(P352/(SUM(P:P))) -> #DIV/0! | V352: ='Entrada e Saida'!$H$22*(Q352/(SUM(Q:Q))) -> #DIV/0! | W352: =R352+S352+U352 -> #DIV/0! | X352: ='Entrada e Saida'!$H$26*(IF('Entrada e Saida'!$H$15="PESO",(P352/(SUM(P:P))),(Q352/(SUM(Q:Q))))) -> #DIV/0! | Y352: ='Entrada e Saida'!$H$27*(IF('Entrada e Saida'!$H$15="PESO",(P352/(SUM(P:P))),(Q352/(SUM(Q:Q))))) -> #DIV/0! | Z352: ='Entrada e Saida'!$H$28*(IF('Entrada e Saida'!$H$15="PESO",(P352/(SUM(P:P))),(Q352/(SUM(Q:Q))))) -> #DIV/0! | AA352: =X352+Y352+Z352 -> #DIV/0! | AB352: =W352*I352 -> #DIV/0! | AC352: =W352*J352 -> #DIV/0! | AD352: =W352*K352 -> #DIV/0! | AE352: =(W352+AB352)*M352 -> #DIV/0! | AF352: =IFERROR(D352*F352*L352*'Entrada e Saida'!$K$8,0) -> 0 | AG352: =((W352+AA352+AB352+AC352+AD352+AE352+AF352)/(1-'Entrada e Saida'!$G$65))*'Entrada e Saida'!$I$66 -> #DIV/0! | AH352: =SUM(AB352:AG352) -> #DIV/0! | AI352: ='Entrada e Saida'!$K$51*(IF('Entrada e Saida'!$H$15="PESO",(P352/(SUM(P:P))),(Q352/(SUM(Q:Q))))) -> #DIV/0! | AJ352: =(('Entrada e Saida'!$K$10-'Entrada e Saida'!$K$8)*E352*D352) -> 0 | AK352: =IF('Entrada e Saida'!$H$15="PESO",W352+AA352+AH352+AI352+AJ352,W352+AA352+AH352+AI352+AJ352-S352+T352-U352+V352) -> #DIV/0! | AL352: =IF('Entrada e Saida'!$H$12="REAL",AC352,0) -> #DIV/0! | AM352: =IF('Entrada e Saida'!$H$12="REAL",AD352,0) -> #DIV/0! | AN352: =IF('Entrada e Saida'!$H$13= "NÃO",AE352,0) -> #DIV/0! | AO352: =AG352 -> #DIV/0! | AP352: =AK352-SUM(AL352:AO352) -> #DIV/0! | AQ352: =IF('Entrada e Saida'!$H$11="TRADING",AU352*'Custo Resumido'!D352,0) -> #DIV/0! | AR352: =IF('Entrada e Saida'!$H$11="TRADING",AU352*'Entrada e Saida'!$G$63,0) -> #DIV/0! | AS352: =IF('Entrada e Saida'!$H$11="TRADING",AU352*'Entrada e Saida'!$G$64,0) -> #DIV/0! | AT352: =IF('Entrada e Saida'!$H$11="TRADING",AU352*'Entrada e Saida'!$G$65,0) -> #DIV/0! | AU352: =IF('Entrada e Saida'!$H$11="TRADING",AP352/(1-(SUM('Entrada e Saida'!$G$63:$G$65)+'Custo Resumido'!D352)),0) -> #DIV/0! | AV352: =IF('Entrada e Saida'!$H$13="NÃO",AU352*M352,0) -> #DIV/0! | AW352: =AU352+AV352 -> #DIV/0! | AX352: ='Entrada e Saida'!$G$74*AU352 -> #DIV/0! | AY352: =AW352-AX352 -> #DIV/0! | AZ352: =AQ352+('Entrada e Saida'!$G$65-'Entrada e Saida'!$I$65)*AU352-AX352 -> #DIV/0! | BA352: =IF('Entrada e Saida'!$H$12="REAL",AZ352*'Entrada e Saida'!$G$81,AU352*'Entrada e Saida'!$G$81) -> #DIV/0! | BB352: =IF('Entrada e Saida'!$H$12="REAL",AZ352*'Entrada e Saida'!$G$82,AU352*'Entrada e Saida'!$G$82) -> #DIV/0! | BC352: =AZ352-BA352-BB352 -> #DIV/0! | BD352: =IF('Entrada e Saida'!$H$11="TRADING",AW352/D352,AK352/D352) -> #DIV/0! | BE352: =AX352/D352 -> #DIV/0! | BF352: =BD352-BE352 -> #DIV/0! | BG352: =IF('Entrada e Saida'!$H$11="TRADING",AV352/D352,AN352/D352) -> #DIV/0! | BH352: =IF('Entrada e Saida'!$H$11="TRADING",IF('Entrada e Saida'!$H$12="REAL",AR352/D352,0),AL352/D352) -> #DIV/0! | BI352: =IF('Entrada e Saida'!$H$11="TRADING",IF('Entrada e Saida'!$H$12="REAL",AS352/D352,0),AM352/D352) -> #DIV/0! | BJ352: =IF('Entrada e Saida'!$H$11="TRADING",AT352/D352,AO352/D352) -> #DIV/0! | BK352: =BF352-SUM(BG352:BJ352) -> #DIV/0! | BL352: =IF(O352>0,IFERROR(IF('Entrada e Saida'!$H$11="DIRETA",0,(IF('Entrada e Saida'!$H$14="P.JURIDICA",(BD352*(1+O352)*N352)-((BD352/(1+M352))*'Entrada e Saida'!$G$65),((Produtos!N352-'Entrada e Saida'!$G$65)*Produtos!BD352)))),0),0) -> 0 | BM352: =BF352+BL352 -> #DIV/0!
B353: =IFERROR(VLOOKUP(A353,'Master Modelo'!A:I,7,FALSE),0) -> 0 | C353: =IFERROR(VLOOKUP(A353,'Master Modelo'!A:I,2,FALSE),0) -> 0 | E353: =IFERROR(VLOOKUP(A353,'Master Modelo'!A:I,9,FALSE),0) -> 0 | F353: =IFERROR(VLOOKUP(A353,'Master Modelo'!A:I,8,FALSE),0) -> 0 | G353: =IFERROR(VLOOKUP(A353,'Master Modelo'!A:K,11,FALSE),0) -> 0 | H353: =(D353*E353)/(D353*F353) -> #DIV/0! | I353: =IFERROR(VLOOKUP(A353,'Master Modelo'!A:I,3,FALSE),0) -> 0 | J353: =IFERROR(VLOOKUP(A353,'Master Modelo'!A:I,5,FALSE),0) -> 0 | K353: =IFERROR(VLOOKUP(A353,'Master Modelo'!A:I,6,FALSE),0) -> 0 | L353: =VLOOKUP(A353,'Master Modelo'!A:J,10,FALSE) -> #N/A | M353: =IFERROR(VLOOKUP(A353,'Master Modelo'!A:I,4,FALSE),0) -> 0 | P353: =D353*F353 -> 0 | Q353: =D353*G353 -> 0 | R353: =D353*E353*'Entrada e Saida'!$K$8 -> 0 | S353: ='Entrada e Saida'!$H$21*'Entrada e Saida'!$K$8*(P353/(SUM(P:P))) -> #DIV/0! | T353: ='Entrada e Saida'!$H$21*'Entrada e Saida'!$K$8*(Q353/(SUM(Q:Q))) -> #DIV/0! | U353: ='Entrada e Saida'!$H$22*(P353/(SUM(P:P))) -> #DIV/0! | V353: ='Entrada e Saida'!$H$22*(Q353/(SUM(Q:Q))) -> #DIV/0! | W353: =R353+S353+U353 -> #DIV/0! | X353: ='Entrada e Saida'!$H$26*(IF('Entrada e Saida'!$H$15="PESO",(P353/(SUM(P:P))),(Q353/(SUM(Q:Q))))) -> #DIV/0! | Y353: ='Entrada e Saida'!$H$27*(IF('Entrada e Saida'!$H$15="PESO",(P353/(SUM(P:P))),(Q353/(SUM(Q:Q))))) -> #DIV/0! | Z353: ='Entrada e Saida'!$H$28*(IF('Entrada e Saida'!$H$15="PESO",(P353/(SUM(P:P))),(Q353/(SUM(Q:Q))))) -> #DIV/0! | AA353: =X353+Y353+Z353 -> #DIV/0! | AB353: =W353*I353 -> #DIV/0! | AC353: =W353*J353 -> #DIV/0! | AD353: =W353*K353 -> #DIV/0! | AE353: =(W353+AB353)*M353 -> #DIV/0! | AF353: =IFERROR(D353*F353*L353*'Entrada e Saida'!$K$8,0) -> 0 | AG353: =((W353+AA353+AB353+AC353+AD353+AE353+AF353)/(1-'Entrada e Saida'!$G$65))*'Entrada e Saida'!$I$66 -> #DIV/0! | AH353: =SUM(AB353:AG353) -> #DIV/0! | AI353: ='Entrada e Saida'!$K$51*(IF('Entrada e Saida'!$H$15="PESO",(P353/(SUM(P:P))),(Q353/(SUM(Q:Q))))) -> #DIV/0! | AJ353: =(('Entrada e Saida'!$K$10-'Entrada e Saida'!$K$8)*E353*D353) -> 0 | AK353: =IF('Entrada e Saida'!$H$15="PESO",W353+AA353+AH353+AI353+AJ353,W353+AA353+AH353+AI353+AJ353-S353+T353-U353+V353) -> #DIV/0! | AL353: =IF('Entrada e Saida'!$H$12="REAL",AC353,0) -> #DIV/0! | AM353: =IF('Entrada e Saida'!$H$12="REAL",AD353,0) -> #DIV/0! | AN353: =IF('Entrada e Saida'!$H$13= "NÃO",AE353,0) -> #DIV/0! | AO353: =AG353 -> #DIV/0! | AP353: =AK353-SUM(AL353:AO353) -> #DIV/0! | AQ353: =IF('Entrada e Saida'!$H$11="TRADING",AU353*'Custo Resumido'!D353,0) -> #DIV/0! | AR353: =IF('Entrada e Saida'!$H$11="TRADING",AU353*'Entrada e Saida'!$G$63,0) -> #DIV/0! | AS353: =IF('Entrada e Saida'!$H$11="TRADING",AU353*'Entrada e Saida'!$G$64,0) -> #DIV/0! | AT353: =IF('Entrada e Saida'!$H$11="TRADING",AU353*'Entrada e Saida'!$G$65,0) -> #DIV/0! | AU353: =IF('Entrada e Saida'!$H$11="TRADING",AP353/(1-(SUM('Entrada e Saida'!$G$63:$G$65)+'Custo Resumido'!D353)),0) -> #DIV/0! | AV353: =IF('Entrada e Saida'!$H$13="NÃO",AU353*M353,0) -> #DIV/0! | AW353: =AU353+AV353 -> #DIV/0! | AX353: ='Entrada e Saida'!$G$74*AU353 -> #DIV/0! | AY353: =AW353-AX353 -> #DIV/0! | AZ353: =AQ353+('Entrada e Saida'!$G$65-'Entrada e Saida'!$I$65)*AU353-AX353 -> #DIV/0! | BA353: =IF('Entrada e Saida'!$H$12="REAL",AZ353*'Entrada e Saida'!$G$81,AU353*'Entrada e Saida'!$G$81) -> #DIV/0! | BB353: =IF('Entrada e Saida'!$H$12="REAL",AZ353*'Entrada e Saida'!$G$82,AU353*'Entrada e Saida'!$G$82) -> #DIV/0! | BC353: =AZ353-BA353-BB353 -> #DIV/0! | BD353: =IF('Entrada e Saida'!$H$11="TRADING",AW353/D353,AK353/D353) -> #DIV/0! | BE353: =AX353/D353 -> #DIV/0! | BF353: =BD353-BE353 -> #DIV/0! | BG353: =IF('Entrada e Saida'!$H$11="TRADING",AV353/D353,AN353/D353) -> #DIV/0! | BH353: =IF('Entrada e Saida'!$H$11="TRADING",IF('Entrada e Saida'!$H$12="REAL",AR353/D353,0),AL353/D353) -> #DIV/0! | BI353: =IF('Entrada e Saida'!$H$11="TRADING",IF('Entrada e Saida'!$H$12="REAL",AS353/D353,0),AM353/D353) -> #DIV/0! | BJ353: =IF('Entrada e Saida'!$H$11="TRADING",AT353/D353,AO353/D353) -> #DIV/0! | BK353: =BF353-SUM(BG353:BJ353) -> #DIV/0! | BL353: =IF(O353>0,IFERROR(IF('Entrada e Saida'!$H$11="DIRETA",0,(IF('Entrada e Saida'!$H$14="P.JURIDICA",(BD353*(1+O353)*N353)-((BD353/(1+M353))*'Entrada e Saida'!$G$65),((Produtos!N353-'Entrada e Saida'!$G$65)*Produtos!BD353)))),0),0) -> 0 | BM353: =BF353+BL353 -> #DIV/0!
B354: =IFERROR(VLOOKUP(A354,'Master Modelo'!A:I,7,FALSE),0) -> 0 | C354: =IFERROR(VLOOKUP(A354,'Master Modelo'!A:I,2,FALSE),0) -> 0 | E354: =IFERROR(VLOOKUP(A354,'Master Modelo'!A:I,9,FALSE),0) -> 0 | F354: =IFERROR(VLOOKUP(A354,'Master Modelo'!A:I,8,FALSE),0) -> 0 | G354: =IFERROR(VLOOKUP(A354,'Master Modelo'!A:K,11,FALSE),0) -> 0 | H354: =(D354*E354)/(D354*F354) -> #DIV/0! | I354: =IFERROR(VLOOKUP(A354,'Master Modelo'!A:I,3,FALSE),0) -> 0 | J354: =IFERROR(VLOOKUP(A354,'Master Modelo'!A:I,5,FALSE),0) -> 0 | K354: =IFERROR(VLOOKUP(A354,'Master Modelo'!A:I,6,FALSE),0) -> 0 | L354: =VLOOKUP(A354,'Master Modelo'!A:J,10,FALSE) -> #N/A | M354: =IFERROR(VLOOKUP(A354,'Master Modelo'!A:I,4,FALSE),0) -> 0 | P354: =D354*F354 -> 0 | Q354: =D354*G354 -> 0 | R354: =D354*E354*'Entrada e Saida'!$K$8 -> 0 | S354: ='Entrada e Saida'!$H$21*'Entrada e Saida'!$K$8*(P354/(SUM(P:P))) -> #DIV/0! | T354: ='Entrada e Saida'!$H$21*'Entrada e Saida'!$K$8*(Q354/(SUM(Q:Q))) -> #DIV/0! | U354: ='Entrada e Saida'!$H$22*(P354/(SUM(P:P))) -> #DIV/0! | V354: ='Entrada e Saida'!$H$22*(Q354/(SUM(Q:Q))) -> #DIV/0! | W354: =R354+S354+U354 -> #DIV/0! | X354: ='Entrada e Saida'!$H$26*(IF('Entrada e Saida'!$H$15="PESO",(P354/(SUM(P:P))),(Q354/(SUM(Q:Q))))) -> #DIV/0! | Y354: ='Entrada e Saida'!$H$27*(IF('Entrada e Saida'!$H$15="PESO",(P354/(SUM(P:P))),(Q354/(SUM(Q:Q))))) -> #DIV/0! | Z354: ='Entrada e Saida'!$H$28*(IF('Entrada e Saida'!$H$15="PESO",(P354/(SUM(P:P))),(Q354/(SUM(Q:Q))))) -> #DIV/0! | AA354: =X354+Y354+Z354 -> #DIV/0! | AB354: =W354*I354 -> #DIV/0! | AC354: =W354*J354 -> #DIV/0! | AD354: =W354*K354 -> #DIV/0! | AE354: =(W354+AB354)*M354 -> #DIV/0! | AF354: =IFERROR(D354*F354*L354*'Entrada e Saida'!$K$8,0) -> 0 | AG354: =((W354+AA354+AB354+AC354+AD354+AE354+AF354)/(1-'Entrada e Saida'!$G$65))*'Entrada e Saida'!$I$66 -> #DIV/0! | AH354: =SUM(AB354:AG354) -> #DIV/0! | AI354: ='Entrada e Saida'!$K$51*(IF('Entrada e Saida'!$H$15="PESO",(P354/(SUM(P:P))),(Q354/(SUM(Q:Q))))) -> #DIV/0! | AJ354: =(('Entrada e Saida'!$K$10-'Entrada e Saida'!$K$8)*E354*D354) -> 0 | AK354: =IF('Entrada e Saida'!$H$15="PESO",W354+AA354+AH354+AI354+AJ354,W354+AA354+AH354+AI354+AJ354-S354+T354-U354+V354) -> #DIV/0! | AL354: =IF('Entrada e Saida'!$H$12="REAL",AC354,0) -> #DIV/0! | AM354: =IF('Entrada e Saida'!$H$12="REAL",AD354,0) -> #DIV/0! | AN354: =IF('Entrada e Saida'!$H$13= "NÃO",AE354,0) -> #DIV/0! | AO354: =AG354 -> #DIV/0! | AP354: =AK354-SUM(AL354:AO354) -> #DIV/0! | AQ354: =IF('Entrada e Saida'!$H$11="TRADING",AU354*'Custo Resumido'!D354,0) -> #DIV/0! | AR354: =IF('Entrada e Saida'!$H$11="TRADING",AU354*'Entrada e Saida'!$G$63,0) -> #DIV/0! | AS354: =IF('Entrada e Saida'!$H$11="TRADING",AU354*'Entrada e Saida'!$G$64,0) -> #DIV/0! | AT354: =IF('Entrada e Saida'!$H$11="TRADING",AU354*'Entrada e Saida'!$G$65,0) -> #DIV/0! | AU354: =IF('Entrada e Saida'!$H$11="TRADING",AP354/(1-(SUM('Entrada e Saida'!$G$63:$G$65)+'Custo Resumido'!D354)),0) -> #DIV/0! | AV354: =IF('Entrada e Saida'!$H$13="NÃO",AU354*M354,0) -> #DIV/0! | AW354: =AU354+AV354 -> #DIV/0! | AX354: ='Entrada e Saida'!$G$74*AU354 -> #DIV/0! | AY354: =AW354-AX354 -> #DIV/0! | AZ354: =AQ354+('Entrada e Saida'!$G$65-'Entrada e Saida'!$I$65)*AU354-AX354 -> #DIV/0! | BA354: =IF('Entrada e Saida'!$H$12="REAL",AZ354*'Entrada e Saida'!$G$81,AU354*'Entrada e Saida'!$G$81) -> #DIV/0! | BB354: =IF('Entrada e Saida'!$H$12="REAL",AZ354*'Entrada e Saida'!$G$82,AU354*'Entrada e Saida'!$G$82) -> #DIV/0! | BC354: =AZ354-BA354-BB354 -> #DIV/0! | BD354: =IF('Entrada e Saida'!$H$11="TRADING",AW354/D354,AK354/D354) -> #DIV/0! | BE354: =AX354/D354 -> #DIV/0! | BF354: =BD354-BE354 -> #DIV/0! | BG354: =IF('Entrada e Saida'!$H$11="TRADING",AV354/D354,AN354/D354) -> #DIV/0! | BH354: =IF('Entrada e Saida'!$H$11="TRADING",IF('Entrada e Saida'!$H$12="REAL",AR354/D354,0),AL354/D354) -> #DIV/0! | BI354: =IF('Entrada e Saida'!$H$11="TRADING",IF('Entrada e Saida'!$H$12="REAL",AS354/D354,0),AM354/D354) -> #DIV/0! | BJ354: =IF('Entrada e Saida'!$H$11="TRADING",AT354/D354,AO354/D354) -> #DIV/0! | BK354: =BF354-SUM(BG354:BJ354) -> #DIV/0! | BL354: =IF(O354>0,IFERROR(IF('Entrada e Saida'!$H$11="DIRETA",0,(IF('Entrada e Saida'!$H$14="P.JURIDICA",(BD354*(1+O354)*N354)-((BD354/(1+M354))*'Entrada e Saida'!$G$65),((Produtos!N354-'Entrada e Saida'!$G$65)*Produtos!BD354)))),0),0) -> 0 | BM354: =BF354+BL354 -> #DIV/0!
B355: =IFERROR(VLOOKUP(A355,'Master Modelo'!A:I,7,FALSE),0) -> 0 | C355: =IFERROR(VLOOKUP(A355,'Master Modelo'!A:I,2,FALSE),0) -> 0 | E355: =IFERROR(VLOOKUP(A355,'Master Modelo'!A:I,9,FALSE),0) -> 0 | F355: =IFERROR(VLOOKUP(A355,'Master Modelo'!A:I,8,FALSE),0) -> 0 | G355: =IFERROR(VLOOKUP(A355,'Master Modelo'!A:K,11,FALSE),0) -> 0 | H355: =(D355*E355)/(D355*F355) -> #DIV/0! | I355: =IFERROR(VLOOKUP(A355,'Master Modelo'!A:I,3,FALSE),0) -> 0 | J355: =IFERROR(VLOOKUP(A355,'Master Modelo'!A:I,5,FALSE),0) -> 0 | K355: =IFERROR(VLOOKUP(A355,'Master Modelo'!A:I,6,FALSE),0) -> 0 | L355: =VLOOKUP(A355,'Master Modelo'!A:J,10,FALSE) -> #N/A | M355: =IFERROR(VLOOKUP(A355,'Master Modelo'!A:I,4,FALSE),0) -> 0 | P355: =D355*F355 -> 0 | Q355: =D355*G355 -> 0 | R355: =D355*E355*'Entrada e Saida'!$K$8 -> 0 | S355: ='Entrada e Saida'!$H$21*'Entrada e Saida'!$K$8*(P355/(SUM(P:P))) -> #DIV/0! | T355: ='Entrada e Saida'!$H$21*'Entrada e Saida'!$K$8*(Q355/(SUM(Q:Q))) -> #DIV/0! | U355: ='Entrada e Saida'!$H$22*(P355/(SUM(P:P))) -> #DIV/0! | V355: ='Entrada e Saida'!$H$22*(Q355/(SUM(Q:Q))) -> #DIV/0! | W355: =R355+S355+U355 -> #DIV/0! | X355: ='Entrada e Saida'!$H$26*(IF('Entrada e Saida'!$H$15="PESO",(P355/(SUM(P:P))),(Q355/(SUM(Q:Q))))) -> #DIV/0! | Y355: ='Entrada e Saida'!$H$27*(IF('Entrada e Saida'!$H$15="PESO",(P355/(SUM(P:P))),(Q355/(SUM(Q:Q))))) -> #DIV/0! | Z355: ='Entrada e Saida'!$H$28*(IF('Entrada e Saida'!$H$15="PESO",(P355/(SUM(P:P))),(Q355/(SUM(Q:Q))))) -> #DIV/0! | AA355: =X355+Y355+Z355 -> #DIV/0! | AB355: =W355*I355 -> #DIV/0! | AC355: =W355*J355 -> #DIV/0! | AD355: =W355*K355 -> #DIV/0! | AE355: =(W355+AB355)*M355 -> #DIV/0! | AF355: =IFERROR(D355*F355*L355*'Entrada e Saida'!$K$8,0) -> 0 | AG355: =((W355+AA355+AB355+AC355+AD355+AE355+AF355)/(1-'Entrada e Saida'!$G$65))*'Entrada e Saida'!$I$66 -> #DIV/0! | AH355: =SUM(AB355:AG355) -> #DIV/0! | AI355: ='Entrada e Saida'!$K$51*(IF('Entrada e Saida'!$H$15="PESO",(P355/(SUM(P:P))),(Q355/(SUM(Q:Q))))) -> #DIV/0! | AJ355: =(('Entrada e Saida'!$K$10-'Entrada e Saida'!$K$8)*E355*D355) -> 0 | AK355: =IF('Entrada e Saida'!$H$15="PESO",W355+AA355+AH355+AI355+AJ355,W355+AA355+AH355+AI355+AJ355-S355+T355-U355+V355) -> #DIV/0! | AL355: =IF('Entrada e Saida'!$H$12="REAL",AC355,0) -> #DIV/0! | AM355: =IF('Entrada e Saida'!$H$12="REAL",AD355,0) -> #DIV/0! | AN355: =IF('Entrada e Saida'!$H$13= "NÃO",AE355,0) -> #DIV/0! | AO355: =AG355 -> #DIV/0! | AP355: =AK355-SUM(AL355:AO355) -> #DIV/0! | AQ355: =IF('Entrada e Saida'!$H$11="TRADING",AU355*'Custo Resumido'!D355,0) -> #DIV/0! | AR355: =IF('Entrada e Saida'!$H$11="TRADING",AU355*'Entrada e Saida'!$G$63,0) -> #DIV/0! | AS355: =IF('Entrada e Saida'!$H$11="TRADING",AU355*'Entrada e Saida'!$G$64,0) -> #DIV/0! | AT355: =IF('Entrada e Saida'!$H$11="TRADING",AU355*'Entrada e Saida'!$G$65,0) -> #DIV/0! | AU355: =IF('Entrada e Saida'!$H$11="TRADING",AP355/(1-(SUM('Entrada e Saida'!$G$63:$G$65)+'Custo Resumido'!D355)),0) -> #DIV/0! | AV355: =IF('Entrada e Saida'!$H$13="NÃO",AU355*M355,0) -> #DIV/0! | AW355: =AU355+AV355 -> #DIV/0! | AX355: ='Entrada e Saida'!$G$74*AU355 -> #DIV/0! | AY355: =AW355-AX355 -> #DIV/0! | AZ355: =AQ355+('Entrada e Saida'!$G$65-'Entrada e Saida'!$I$65)*AU355-AX355 -> #DIV/0! | BA355: =IF('Entrada e Saida'!$H$12="REAL",AZ355*'Entrada e Saida'!$G$81,AU355*'Entrada e Saida'!$G$81) -> #DIV/0! | BB355: =IF('Entrada e Saida'!$H$12="REAL",AZ355*'Entrada e Saida'!$G$82,AU355*'Entrada e Saida'!$G$82) -> #DIV/0! | BC355: =AZ355-BA355-BB355 -> #DIV/0! | BD355: =IF('Entrada e Saida'!$H$11="TRADING",AW355/D355,AK355/D355) -> #DIV/0! | BE355: =AX355/D355 -> #DIV/0! | BF355: =BD355-BE355 -> #DIV/0! | BG355: =IF('Entrada e Saida'!$H$11="TRADING",AV355/D355,AN355/D355) -> #DIV/0! | BH355: =IF('Entrada e Saida'!$H$11="TRADING",IF('Entrada e Saida'!$H$12="REAL",AR355/D355,0),AL355/D355) -> #DIV/0! | BI355: =IF('Entrada e Saida'!$H$11="TRADING",IF('Entrada e Saida'!$H$12="REAL",AS355/D355,0),AM355/D355) -> #DIV/0! | BJ355: =IF('Entrada e Saida'!$H$11="TRADING",AT355/D355,AO355/D355) -> #DIV/0! | BK355: =BF355-SUM(BG355:BJ355) -> #DIV/0! | BL355: =IF(O355>0,IFERROR(IF('Entrada e Saida'!$H$11="DIRETA",0,(IF('Entrada e Saida'!$H$14="P.JURIDICA",(BD355*(1+O355)*N355)-((BD355/(1+M355))*'Entrada e Saida'!$G$65),((Produtos!N355-'Entrada e Saida'!$G$65)*Produtos!BD355)))),0),0) -> 0 | BM355: =BF355+BL355 -> #DIV/0!
B356: =IFERROR(VLOOKUP(A356,'Master Modelo'!A:I,7,FALSE),0) -> 0 | C356: =IFERROR(VLOOKUP(A356,'Master Modelo'!A:I,2,FALSE),0) -> 0 | E356: =IFERROR(VLOOKUP(A356,'Master Modelo'!A:I,9,FALSE),0) -> 0 | F356: =IFERROR(VLOOKUP(A356,'Master Modelo'!A:I,8,FALSE),0) -> 0 | G356: =IFERROR(VLOOKUP(A356,'Master Modelo'!A:K,11,FALSE),0) -> 0 | H356: =(D356*E356)/(D356*F356) -> #DIV/0! | I356: =IFERROR(VLOOKUP(A356,'Master Modelo'!A:I,3,FALSE),0) -> 0 | J356: =IFERROR(VLOOKUP(A356,'Master Modelo'!A:I,5,FALSE),0) -> 0 | K356: =IFERROR(VLOOKUP(A356,'Master Modelo'!A:I,6,FALSE),0) -> 0 | L356: =VLOOKUP(A356,'Master Modelo'!A:J,10,FALSE) -> #N/A | M356: =IFERROR(VLOOKUP(A356,'Master Modelo'!A:I,4,FALSE),0) -> 0 | P356: =D356*F356 -> 0 | Q356: =D356*G356 -> 0 | R356: =D356*E356*'Entrada e Saida'!$K$8 -> 0 | S356: ='Entrada e Saida'!$H$21*'Entrada e Saida'!$K$8*(P356/(SUM(P:P))) -> #DIV/0! | T356: ='Entrada e Saida'!$H$21*'Entrada e Saida'!$K$8*(Q356/(SUM(Q:Q))) -> #DIV/0! | U356: ='Entrada e Saida'!$H$22*(P356/(SUM(P:P))) -> #DIV/0! | V356: ='Entrada e Saida'!$H$22*(Q356/(SUM(Q:Q))) -> #DIV/0! | W356: =R356+S356+U356 -> #DIV/0! | X356: ='Entrada e Saida'!$H$26*(IF('Entrada e Saida'!$H$15="PESO",(P356/(SUM(P:P))),(Q356/(SUM(Q:Q))))) -> #DIV/0! | Y356: ='Entrada e Saida'!$H$27*(IF('Entrada e Saida'!$H$15="PESO",(P356/(SUM(P:P))),(Q356/(SUM(Q:Q))))) -> #DIV/0! | Z356: ='Entrada e Saida'!$H$28*(IF('Entrada e Saida'!$H$15="PESO",(P356/(SUM(P:P))),(Q356/(SUM(Q:Q))))) -> #DIV/0! | AA356: =X356+Y356+Z356 -> #DIV/0! | AB356: =W356*I356 -> #DIV/0! | AC356: =W356*J356 -> #DIV/0! | AD356: =W356*K356 -> #DIV/0! | AE356: =(W356+AB356)*M356 -> #DIV/0! | AF356: =IFERROR(D356*F356*L356*'Entrada e Saida'!$K$8,0) -> 0 | AG356: =((W356+AA356+AB356+AC356+AD356+AE356+AF356)/(1-'Entrada e Saida'!$G$65))*'Entrada e Saida'!$I$66 -> #DIV/0! | AH356: =SUM(AB356:AG356) -> #DIV/0! | AI356: ='Entrada e Saida'!$K$51*(IF('Entrada e Saida'!$H$15="PESO",(P356/(SUM(P:P))),(Q356/(SUM(Q:Q))))) -> #DIV/0! | AJ356: =(('Entrada e Saida'!$K$10-'Entrada e Saida'!$K$8)*E356*D356) -> 0 | AK356: =IF('Entrada e Saida'!$H$15="PESO",W356+AA356+AH356+AI356+AJ356,W356+AA356+AH356+AI356+AJ356-S356+T356-U356+V356) -> #DIV/0! | AL356: =IF('Entrada e Saida'!$H$12="REAL",AC356,0) -> #DIV/0! | AM356: =IF('Entrada e Saida'!$H$12="REAL",AD356,0) -> #DIV/0! | AN356: =IF('Entrada e Saida'!$H$13= "NÃO",AE356,0) -> #DIV/0! | AO356: =AG356 -> #DIV/0! | AP356: =AK356-SUM(AL356:AO356) -> #DIV/0! | AQ356: =IF('Entrada e Saida'!$H$11="TRADING",AU356*'Custo Resumido'!D356,0) -> #DIV/0! | AR356: =IF('Entrada e Saida'!$H$11="TRADING",AU356*'Entrada e Saida'!$G$63,0) -> #DIV/0! | AS356: =IF('Entrada e Saida'!$H$11="TRADING",AU356*'Entrada e Saida'!$G$64,0) -> #DIV/0! | AT356: =IF('Entrada e Saida'!$H$11="TRADING",AU356*'Entrada e Saida'!$G$65,0) -> #DIV/0! | AU356: =IF('Entrada e Saida'!$H$11="TRADING",AP356/(1-(SUM('Entrada e Saida'!$G$63:$G$65)+'Custo Resumido'!D356)),0) -> #DIV/0! | AV356: =IF('Entrada e Saida'!$H$13="NÃO",AU356*M356,0) -> #DIV/0! | AW356: =AU356+AV356 -> #DIV/0! | AX356: ='Entrada e Saida'!$G$74*AU356 -> #DIV/0! | AY356: =AW356-AX356 -> #DIV/0! | AZ356: =AQ356+('Entrada e Saida'!$G$65-'Entrada e Saida'!$I$65)*AU356-AX356 -> #DIV/0! | BA356: =IF('Entrada e Saida'!$H$12="REAL",AZ356*'Entrada e Saida'!$G$81,AU356*'Entrada e Saida'!$G$81) -> #DIV/0! | BB356: =IF('Entrada e Saida'!$H$12="REAL",AZ356*'Entrada e Saida'!$G$82,AU356*'Entrada e Saida'!$G$82) -> #DIV/0! | BC356: =AZ356-BA356-BB356 -> #DIV/0! | BD356: =IF('Entrada e Saida'!$H$11="TRADING",AW356/D356,AK356/D356) -> #DIV/0! | BE356: =AX356/D356 -> #DIV/0! | BF356: =BD356-BE356 -> #DIV/0! | BG356: =IF('Entrada e Saida'!$H$11="TRADING",AV356/D356,AN356/D356) -> #DIV/0! | BH356: =IF('Entrada e Saida'!$H$11="TRADING",IF('Entrada e Saida'!$H$12="REAL",AR356/D356,0),AL356/D356) -> #DIV/0! | BI356: =IF('Entrada e Saida'!$H$11="TRADING",IF('Entrada e Saida'!$H$12="REAL",AS356/D356,0),AM356/D356) -> #DIV/0! | BJ356: =IF('Entrada e Saida'!$H$11="TRADING",AT356/D356,AO356/D356) -> #DIV/0! | BK356: =BF356-SUM(BG356:BJ356) -> #DIV/0! | BL356: =IF(O356>0,IFERROR(IF('Entrada e Saida'!$H$11="DIRETA",0,(IF('Entrada e Saida'!$H$14="P.JURIDICA",(BD356*(1+O356)*N356)-((BD356/(1+M356))*'Entrada e Saida'!$G$65),((Produtos!N356-'Entrada e Saida'!$G$65)*Produtos!BD356)))),0),0) -> 0 | BM356: =BF356+BL356 -> #DIV/0!
B357: =IFERROR(VLOOKUP(A357,'Master Modelo'!A:I,7,FALSE),0) -> 0 | C357: =IFERROR(VLOOKUP(A357,'Master Modelo'!A:I,2,FALSE),0) -> 0 | E357: =IFERROR(VLOOKUP(A357,'Master Modelo'!A:I,9,FALSE),0) -> 0 | F357: =IFERROR(VLOOKUP(A357,'Master Modelo'!A:I,8,FALSE),0) -> 0 | G357: =IFERROR(VLOOKUP(A357,'Master Modelo'!A:K,11,FALSE),0) -> 0 | H357: =(D357*E357)/(D357*F357) -> #DIV/0! | I357: =IFERROR(VLOOKUP(A357,'Master Modelo'!A:I,3,FALSE),0) -> 0 | J357: =IFERROR(VLOOKUP(A357,'Master Modelo'!A:I,5,FALSE),0) -> 0 | K357: =IFERROR(VLOOKUP(A357,'Master Modelo'!A:I,6,FALSE),0) -> 0 | L357: =VLOOKUP(A357,'Master Modelo'!A:J,10,FALSE) -> #N/A | M357: =IFERROR(VLOOKUP(A357,'Master Modelo'!A:I,4,FALSE),0) -> 0 | P357: =D357*F357 -> 0 | Q357: =D357*G357 -> 0 | R357: =D357*E357*'Entrada e Saida'!$K$8 -> 0 | S357: ='Entrada e Saida'!$H$21*'Entrada e Saida'!$K$8*(P357/(SUM(P:P))) -> #DIV/0! | T357: ='Entrada e Saida'!$H$21*'Entrada e Saida'!$K$8*(Q357/(SUM(Q:Q))) -> #DIV/0! | U357: ='Entrada e Saida'!$H$22*(P357/(SUM(P:P))) -> #DIV/0! | V357: ='Entrada e Saida'!$H$22*(Q357/(SUM(Q:Q))) -> #DIV/0! | W357: =R357+S357+U357 -> #DIV/0! | X357: ='Entrada e Saida'!$H$26*(IF('Entrada e Saida'!$H$15="PESO",(P357/(SUM(P:P))),(Q357/(SUM(Q:Q))))) -> #DIV/0! | Y357: ='Entrada e Saida'!$H$27*(IF('Entrada e Saida'!$H$15="PESO",(P357/(SUM(P:P))),(Q357/(SUM(Q:Q))))) -> #DIV/0! | Z357: ='Entrada e Saida'!$H$28*(IF('Entrada e Saida'!$H$15="PESO",(P357/(SUM(P:P))),(Q357/(SUM(Q:Q))))) -> #DIV/0! | AA357: =X357+Y357+Z357 -> #DIV/0! | AB357: =W357*I357 -> #DIV/0! | AC357: =W357*J357 -> #DIV/0! | AD357: =W357*K357 -> #DIV/0! | AE357: =(W357+AB357)*M357 -> #DIV/0! | AF357: =IFERROR(D357*F357*L357*'Entrada e Saida'!$K$8,0) -> 0 | AG357: =((W357+AA357+AB357+AC357+AD357+AE357+AF357)/(1-'Entrada e Saida'!$G$65))*'Entrada e Saida'!$I$66 -> #DIV/0! | AH357: =SUM(AB357:AG357) -> #DIV/0! | AI357: ='Entrada e Saida'!$K$51*(IF('Entrada e Saida'!$H$15="PESO",(P357/(SUM(P:P))),(Q357/(SUM(Q:Q))))) -> #DIV/0! | AJ357: =(('Entrada e Saida'!$K$10-'Entrada e Saida'!$K$8)*E357*D357) -> 0 | AK357: =IF('Entrada e Saida'!$H$15="PESO",W357+AA357+AH357+AI357+AJ357,W357+AA357+AH357+AI357+AJ357-S357+T357-U357+V357) -> #DIV/0! | AL357: =IF('Entrada e Saida'!$H$12="REAL",AC357,0) -> #DIV/0! | AM357: =IF('Entrada e Saida'!$H$12="REAL",AD357,0) -> #DIV/0! | AN357: =IF('Entrada e Saida'!$H$13= "NÃO",AE357,0) -> #DIV/0! | AO357: =AG357 -> #DIV/0! | AP357: =AK357-SUM(AL357:AO357) -> #DIV/0! | AQ357: =IF('Entrada e Saida'!$H$11="TRADING",AU357*'Custo Resumido'!D357,0) -> #DIV/0! | AR357: =IF('Entrada e Saida'!$H$11="TRADING",AU357*'Entrada e Saida'!$G$63,0) -> #DIV/0! | AS357: =IF('Entrada e Saida'!$H$11="TRADING",AU357*'Entrada e Saida'!$G$64,0) -> #DIV/0! | AT357: =IF('Entrada e Saida'!$H$11="TRADING",AU357*'Entrada e Saida'!$G$65,0) -> #DIV/0! | AU357: =IF('Entrada e Saida'!$H$11="TRADING",AP357/(1-(SUM('Entrada e Saida'!$G$63:$G$65)+'Custo Resumido'!D357)),0) -> #DIV/0! | AV357: =IF('Entrada e Saida'!$H$13="NÃO",AU357*M357,0) -> #DIV/0! | AW357: =AU357+AV357 -> #DIV/0! | AX357: ='Entrada e Saida'!$G$74*AU357 -> #DIV/0! | AY357: =AW357-AX357 -> #DIV/0! | AZ357: =AQ357+('Entrada e Saida'!$G$65-'Entrada e Saida'!$I$65)*AU357-AX357 -> #DIV/0! | BA357: =IF('Entrada e Saida'!$H$12="REAL",AZ357*'Entrada e Saida'!$G$81,AU357*'Entrada e Saida'!$G$81) -> #DIV/0! | BB357: =IF('Entrada e Saida'!$H$12="REAL",AZ357*'Entrada e Saida'!$G$82,AU357*'Entrada e Saida'!$G$82) -> #DIV/0! | BC357: =AZ357-BA357-BB357 -> #DIV/0! | BD357: =IF('Entrada e Saida'!$H$11="TRADING",AW357/D357,AK357/D357) -> #DIV/0! | BE357: =AX357/D357 -> #DIV/0! | BF357: =BD357-BE357 -> #DIV/0! | BG357: =IF('Entrada e Saida'!$H$11="TRADING",AV357/D357,AN357/D357) -> #DIV/0! | BH357: =IF('Entrada e Saida'!$H$11="TRADING",IF('Entrada e Saida'!$H$12="REAL",AR357/D357,0),AL357/D357) -> #DIV/0! | BI357: =IF('Entrada e Saida'!$H$11="TRADING",IF('Entrada e Saida'!$H$12="REAL",AS357/D357,0),AM357/D357) -> #DIV/0! | BJ357: =IF('Entrada e Saida'!$H$11="TRADING",AT357/D357,AO357/D357) -> #DIV/0! | BK357: =BF357-SUM(BG357:BJ357) -> #DIV/0! | BL357: =IF(O357>0,IFERROR(IF('Entrada e Saida'!$H$11="DIRETA",0,(IF('Entrada e Saida'!$H$14="P.JURIDICA",(BD357*(1+O357)*N357)-((BD357/(1+M357))*'Entrada e Saida'!$G$65),((Produtos!N357-'Entrada e Saida'!$G$65)*Produtos!BD357)))),0),0) -> 0 | BM357: =BF357+BL357 -> #DIV/0!
B358: =IFERROR(VLOOKUP(A358,'Master Modelo'!A:I,7,FALSE),0) -> 0 | C358: =IFERROR(VLOOKUP(A358,'Master Modelo'!A:I,2,FALSE),0) -> 0 | E358: =IFERROR(VLOOKUP(A358,'Master Modelo'!A:I,9,FALSE),0) -> 0 | F358: =IFERROR(VLOOKUP(A358,'Master Modelo'!A:I,8,FALSE),0) -> 0 | G358: =IFERROR(VLOOKUP(A358,'Master Modelo'!A:K,11,FALSE),0) -> 0 | H358: =(D358*E358)/(D358*F358) -> #DIV/0! | I358: =IFERROR(VLOOKUP(A358,'Master Modelo'!A:I,3,FALSE),0) -> 0 | J358: =IFERROR(VLOOKUP(A358,'Master Modelo'!A:I,5,FALSE),0) -> 0 | K358: =IFERROR(VLOOKUP(A358,'Master Modelo'!A:I,6,FALSE),0) -> 0 | L358: =VLOOKUP(A358,'Master Modelo'!A:J,10,FALSE) -> #N/A | M358: =IFERROR(VLOOKUP(A358,'Master Modelo'!A:I,4,FALSE),0) -> 0 | P358: =D358*F358 -> 0 | Q358: =D358*G358 -> 0 | R358: =D358*E358*'Entrada e Saida'!$K$8 -> 0 | S358: ='Entrada e Saida'!$H$21*'Entrada e Saida'!$K$8*(P358/(SUM(P:P))) -> #DIV/0! | T358: ='Entrada e Saida'!$H$21*'Entrada e Saida'!$K$8*(Q358/(SUM(Q:Q))) -> #DIV/0! | U358: ='Entrada e Saida'!$H$22*(P358/(SUM(P:P))) -> #DIV/0! | V358: ='Entrada e Saida'!$H$22*(Q358/(SUM(Q:Q))) -> #DIV/0! | W358: =R358+S358+U358 -> #DIV/0! | X358: ='Entrada e Saida'!$H$26*(IF('Entrada e Saida'!$H$15="PESO",(P358/(SUM(P:P))),(Q358/(SUM(Q:Q))))) -> #DIV/0! | Y358: ='Entrada e Saida'!$H$27*(IF('Entrada e Saida'!$H$15="PESO",(P358/(SUM(P:P))),(Q358/(SUM(Q:Q))))) -> #DIV/0! | Z358: ='Entrada e Saida'!$H$28*(IF('Entrada e Saida'!$H$15="PESO",(P358/(SUM(P:P))),(Q358/(SUM(Q:Q))))) -> #DIV/0! | AA358: =X358+Y358+Z358 -> #DIV/0! | AB358: =W358*I358 -> #DIV/0! | AC358: =W358*J358 -> #DIV/0! | AD358: =W358*K358 -> #DIV/0! | AE358: =(W358+AB358)*M358 -> #DIV/0! | AF358: =IFERROR(D358*F358*L358*'Entrada e Saida'!$K$8,0) -> 0 | AG358: =((W358+AA358+AB358+AC358+AD358+AE358+AF358)/(1-'Entrada e Saida'!$G$65))*'Entrada e Saida'!$I$66 -> #DIV/0! | AH358: =SUM(AB358:AG358) -> #DIV/0! | AI358: ='Entrada e Saida'!$K$51*(IF('Entrada e Saida'!$H$15="PESO",(P358/(SUM(P:P))),(Q358/(SUM(Q:Q))))) -> #DIV/0! | AJ358: =(('Entrada e Saida'!$K$10-'Entrada e Saida'!$K$8)*E358*D358) -> 0 | AK358: =IF('Entrada e Saida'!$H$15="PESO",W358+AA358+AH358+AI358+AJ358,W358+AA358+AH358+AI358+AJ358-S358+T358-U358+V358) -> #DIV/0! | AL358: =IF('Entrada e Saida'!$H$12="REAL",AC358,0) -> #DIV/0! | AM358: =IF('Entrada e Saida'!$H$12="REAL",AD358,0) -> #DIV/0! | AN358: =IF('Entrada e Saida'!$H$13= "NÃO",AE358,0) -> #DIV/0! | AO358: =AG358 -> #DIV/0! | AP358: =AK358-SUM(AL358:AO358) -> #DIV/0! | AQ358: =IF('Entrada e Saida'!$H$11="TRADING",AU358*'Custo Resumido'!D358,0) -> #DIV/0! | AR358: =IF('Entrada e Saida'!$H$11="TRADING",AU358*'Entrada e Saida'!$G$63,0) -> #DIV/0! | AS358: =IF('Entrada e Saida'!$H$11="TRADING",AU358*'Entrada e Saida'!$G$64,0) -> #DIV/0! | AT358: =IF('Entrada e Saida'!$H$11="TRADING",AU358*'Entrada e Saida'!$G$65,0) -> #DIV/0! | AU358: =IF('Entrada e Saida'!$H$11="TRADING",AP358/(1-(SUM('Entrada e Saida'!$G$63:$G$65)+'Custo Resumido'!D358)),0) -> #DIV/0! | AV358: =IF('Entrada e Saida'!$H$13="NÃO",AU358*M358,0) -> #DIV/0! | AW358: =AU358+AV358 -> #DIV/0! | AX358: ='Entrada e Saida'!$G$74*AU358 -> #DIV/0! | AY358: =AW358-AX358 -> #DIV/0! | AZ358: =AQ358+('Entrada e Saida'!$G$65-'Entrada e Saida'!$I$65)*AU358-AX358 -> #DIV/0! | BA358: =IF('Entrada e Saida'!$H$12="REAL",AZ358*'Entrada e Saida'!$G$81,AU358*'Entrada e Saida'!$G$81) -> #DIV/0! | BB358: =IF('Entrada e Saida'!$H$12="REAL",AZ358*'Entrada e Saida'!$G$82,AU358*'Entrada e Saida'!$G$82) -> #DIV/0! | BC358: =AZ358-BA358-BB358 -> #DIV/0! | BD358: =IF('Entrada e Saida'!$H$11="TRADING",AW358/D358,AK358/D358) -> #DIV/0! | BE358: =AX358/D358 -> #DIV/0! | BF358: =BD358-BE358 -> #DIV/0! | BG358: =IF('Entrada e Saida'!$H$11="TRADING",AV358/D358,AN358/D358) -> #DIV/0! | BH358: =IF('Entrada e Saida'!$H$11="TRADING",IF('Entrada e Saida'!$H$12="REAL",AR358/D358,0),AL358/D358) -> #DIV/0! | BI358: =IF('Entrada e Saida'!$H$11="TRADING",IF('Entrada e Saida'!$H$12="REAL",AS358/D358,0),AM358/D358) -> #DIV/0! | BJ358: =IF('Entrada e Saida'!$H$11="TRADING",AT358/D358,AO358/D358) -> #DIV/0! | BK358: =BF358-SUM(BG358:BJ358) -> #DIV/0! | BL358: =IF(O358>0,IFERROR(IF('Entrada e Saida'!$H$11="DIRETA",0,(IF('Entrada e Saida'!$H$14="P.JURIDICA",(BD358*(1+O358)*N358)-((BD358/(1+M358))*'Entrada e Saida'!$G$65),((Produtos!N358-'Entrada e Saida'!$G$65)*Produtos!BD358)))),0),0) -> 0 | BM358: =BF358+BL358 -> #DIV/0!
B359: =IFERROR(VLOOKUP(A359,'Master Modelo'!A:I,7,FALSE),0) -> 0 | C359: =IFERROR(VLOOKUP(A359,'Master Modelo'!A:I,2,FALSE),0) -> 0 | E359: =IFERROR(VLOOKUP(A359,'Master Modelo'!A:I,9,FALSE),0) -> 0 | F359: =IFERROR(VLOOKUP(A359,'Master Modelo'!A:I,8,FALSE),0) -> 0 | G359: =IFERROR(VLOOKUP(A359,'Master Modelo'!A:K,11,FALSE),0) -> 0 | H359: =(D359*E359)/(D359*F359) -> #DIV/0! | I359: =IFERROR(VLOOKUP(A359,'Master Modelo'!A:I,3,FALSE),0) -> 0 | J359: =IFERROR(VLOOKUP(A359,'Master Modelo'!A:I,5,FALSE),0) -> 0 | K359: =IFERROR(VLOOKUP(A359,'Master Modelo'!A:I,6,FALSE),0) -> 0 | L359: =VLOOKUP(A359,'Master Modelo'!A:J,10,FALSE) -> #N/A | M359: =IFERROR(VLOOKUP(A359,'Master Modelo'!A:I,4,FALSE),0) -> 0 | P359: =D359*F359 -> 0 | Q359: =D359*G359 -> 0 | R359: =D359*E359*'Entrada e Saida'!$K$8 -> 0 | S359: ='Entrada e Saida'!$H$21*'Entrada e Saida'!$K$8*(P359/(SUM(P:P))) -> #DIV/0! | T359: ='Entrada e Saida'!$H$21*'Entrada e Saida'!$K$8*(Q359/(SUM(Q:Q))) -> #DIV/0! | U359: ='Entrada e Saida'!$H$22*(P359/(SUM(P:P))) -> #DIV/0! | V359: ='Entrada e Saida'!$H$22*(Q359/(SUM(Q:Q))) -> #DIV/0! | W359: =R359+S359+U359 -> #DIV/0! | X359: ='Entrada e Saida'!$H$26*(IF('Entrada e Saida'!$H$15="PESO",(P359/(SUM(P:P))),(Q359/(SUM(Q:Q))))) -> #DIV/0! | Y359: ='Entrada e Saida'!$H$27*(IF('Entrada e Saida'!$H$15="PESO",(P359/(SUM(P:P))),(Q359/(SUM(Q:Q))))) -> #DIV/0! | Z359: ='Entrada e Saida'!$H$28*(IF('Entrada e Saida'!$H$15="PESO",(P359/(SUM(P:P))),(Q359/(SUM(Q:Q))))) -> #DIV/0! | AA359: =X359+Y359+Z359 -> #DIV/0! | AB359: =W359*I359 -> #DIV/0! | AC359: =W359*J359 -> #DIV/0! | AD359: =W359*K359 -> #DIV/0! | AE359: =(W359+AB359)*M359 -> #DIV/0! | AF359: =IFERROR(D359*F359*L359*'Entrada e Saida'!$K$8,0) -> 0 | AG359: =((W359+AA359+AB359+AC359+AD359+AE359+AF359)/(1-'Entrada e Saida'!$G$65))*'Entrada e Saida'!$I$66 -> #DIV/0! | AH359: =SUM(AB359:AG359) -> #DIV/0! | AI359: ='Entrada e Saida'!$K$51*(IF('Entrada e Saida'!$H$15="PESO",(P359/(SUM(P:P))),(Q359/(SUM(Q:Q))))) -> #DIV/0! | AJ359: =(('Entrada e Saida'!$K$10-'Entrada e Saida'!$K$8)*E359*D359) -> 0 | AK359: =IF('Entrada e Saida'!$H$15="PESO",W359+AA359+AH359+AI359+AJ359,W359+AA359+AH359+AI359+AJ359-S359+T359-U359+V359) -> #DIV/0! | AL359: =IF('Entrada e Saida'!$H$12="REAL",AC359,0) -> #DIV/0! | AM359: =IF('Entrada e Saida'!$H$12="REAL",AD359,0) -> #DIV/0! | AN359: =IF('Entrada e Saida'!$H$13= "NÃO",AE359,0) -> #DIV/0! | AO359: =AG359 -> #DIV/0! | AP359: =AK359-SUM(AL359:AO359) -> #DIV/0! | AQ359: =IF('Entrada e Saida'!$H$11="TRADING",AU359*'Custo Resumido'!D359,0) -> #DIV/0! | AR359: =IF('Entrada e Saida'!$H$11="TRADING",AU359*'Entrada e Saida'!$G$63,0) -> #DIV/0! | AS359: =IF('Entrada e Saida'!$H$11="TRADING",AU359*'Entrada e Saida'!$G$64,0) -> #DIV/0! | AT359: =IF('Entrada e Saida'!$H$11="TRADING",AU359*'Entrada e Saida'!$G$65,0) -> #DIV/0! | AU359: =IF('Entrada e Saida'!$H$11="TRADING",AP359/(1-(SUM('Entrada e Saida'!$G$63:$G$65)+'Custo Resumido'!D359)),0) -> #DIV/0! | AV359: =IF('Entrada e Saida'!$H$13="NÃO",AU359*M359,0) -> #DIV/0! | AW359: =AU359+AV359 -> #DIV/0! | AX359: ='Entrada e Saida'!$G$74*AU359 -> #DIV/0! | AY359: =AW359-AX359 -> #DIV/0! | AZ359: =AQ359+('Entrada e Saida'!$G$65-'Entrada e Saida'!$I$65)*AU359-AX359 -> #DIV/0! | BA359: =IF('Entrada e Saida'!$H$12="REAL",AZ359*'Entrada e Saida'!$G$81,AU359*'Entrada e Saida'!$G$81) -> #DIV/0! | BB359: =IF('Entrada e Saida'!$H$12="REAL",AZ359*'Entrada e Saida'!$G$82,AU359*'Entrada e Saida'!$G$82) -> #DIV/0! | BC359: =AZ359-BA359-BB359 -> #DIV/0! | BD359: =IF('Entrada e Saida'!$H$11="TRADING",AW359/D359,AK359/D359) -> #DIV/0! | BE359: =AX359/D359 -> #DIV/0! | BF359: =BD359-BE359 -> #DIV/0! | BG359: =IF('Entrada e Saida'!$H$11="TRADING",AV359/D359,AN359/D359) -> #DIV/0! | BH359: =IF('Entrada e Saida'!$H$11="TRADING",IF('Entrada e Saida'!$H$12="REAL",AR359/D359,0),AL359/D359) -> #DIV/0! | BI359: =IF('Entrada e Saida'!$H$11="TRADING",IF('Entrada e Saida'!$H$12="REAL",AS359/D359,0),AM359/D359) -> #DIV/0! | BJ359: =IF('Entrada e Saida'!$H$11="TRADING",AT359/D359,AO359/D359) -> #DIV/0! | BK359: =BF359-SUM(BG359:BJ359) -> #DIV/0! | BL359: =IF(O359>0,IFERROR(IF('Entrada e Saida'!$H$11="DIRETA",0,(IF('Entrada e Saida'!$H$14="P.JURIDICA",(BD359*(1+O359)*N359)-((BD359/(1+M359))*'Entrada e Saida'!$G$65),((Produtos!N359-'Entrada e Saida'!$G$65)*Produtos!BD359)))),0),0) -> 0 | BM359: =BF359+BL359 -> #DIV/0!
B360: =IFERROR(VLOOKUP(A360,'Master Modelo'!A:I,7,FALSE),0) -> 0 | C360: =IFERROR(VLOOKUP(A360,'Master Modelo'!A:I,2,FALSE),0) -> 0 | E360: =IFERROR(VLOOKUP(A360,'Master Modelo'!A:I,9,FALSE),0) -> 0 | F360: =IFERROR(VLOOKUP(A360,'Master Modelo'!A:I,8,FALSE),0) -> 0 | G360: =IFERROR(VLOOKUP(A360,'Master Modelo'!A:K,11,FALSE),0) -> 0 | H360: =(D360*E360)/(D360*F360) -> #DIV/0! | I360: =IFERROR(VLOOKUP(A360,'Master Modelo'!A:I,3,FALSE),0) -> 0 | J360: =IFERROR(VLOOKUP(A360,'Master Modelo'!A:I,5,FALSE),0) -> 0 | K360: =IFERROR(VLOOKUP(A360,'Master Modelo'!A:I,6,FALSE),0) -> 0 | L360: =VLOOKUP(A360,'Master Modelo'!A:J,10,FALSE) -> #N/A | M360: =IFERROR(VLOOKUP(A360,'Master Modelo'!A:I,4,FALSE),0) -> 0 | P360: =D360*F360 -> 0 | Q360: =D360*G360 -> 0 | R360: =D360*E360*'Entrada e Saida'!$K$8 -> 0 | S360: ='Entrada e Saida'!$H$21*'Entrada e Saida'!$K$8*(P360/(SUM(P:P))) -> #DIV/0! | T360: ='Entrada e Saida'!$H$21*'Entrada e Saida'!$K$8*(Q360/(SUM(Q:Q))) -> #DIV/0! | U360: ='Entrada e Saida'!$H$22*(P360/(SUM(P:P))) -> #DIV/0! | V360: ='Entrada e Saida'!$H$22*(Q360/(SUM(Q:Q))) -> #DIV/0! | W360: =R360+S360+U360 -> #DIV/0! | X360: ='Entrada e Saida'!$H$26*(IF('Entrada e Saida'!$H$15="PESO",(P360/(SUM(P:P))),(Q360/(SUM(Q:Q))))) -> #DIV/0! | Y360: ='Entrada e Saida'!$H$27*(IF('Entrada e Saida'!$H$15="PESO",(P360/(SUM(P:P))),(Q360/(SUM(Q:Q))))) -> #DIV/0! | Z360: ='Entrada e Saida'!$H$28*(IF('Entrada e Saida'!$H$15="PESO",(P360/(SUM(P:P))),(Q360/(SUM(Q:Q))))) -> #DIV/0! | AA360: =X360+Y360+Z360 -> #DIV/0! | AB360: =W360*I360 -> #DIV/0! | AC360: =W360*J360 -> #DIV/0! | AD360: =W360*K360 -> #DIV/0! | AE360: =(W360+AB360)*M360 -> #DIV/0! | AF360: =IFERROR(D360*F360*L360*'Entrada e Saida'!$K$8,0) -> 0 | AG360: =((W360+AA360+AB360+AC360+AD360+AE360+AF360)/(1-'Entrada e Saida'!$G$65))*'Entrada e Saida'!$I$66 -> #DIV/0! | AH360: =SUM(AB360:AG360) -> #DIV/0! | AI360: ='Entrada e Saida'!$K$51*(IF('Entrada e Saida'!$H$15="PESO",(P360/(SUM(P:P))),(Q360/(SUM(Q:Q))))) -> #DIV/0! | AJ360: =(('Entrada e Saida'!$K$10-'Entrada e Saida'!$K$8)*E360*D360) -> 0 | AK360: =IF('Entrada e Saida'!$H$15="PESO",W360+AA360+AH360+AI360+AJ360,W360+AA360+AH360+AI360+AJ360-S360+T360-U360+V360) -> #DIV/0! | AL360: =IF('Entrada e Saida'!$H$12="REAL",AC360,0) -> #DIV/0! | AM360: =IF('Entrada e Saida'!$H$12="REAL",AD360,0) -> #DIV/0! | AN360: =IF('Entrada e Saida'!$H$13= "NÃO",AE360,0) -> #DIV/0! | AO360: =AG360 -> #DIV/0! | AP360: =AK360-SUM(AL360:AO360) -> #DIV/0! | AQ360: =IF('Entrada e Saida'!$H$11="TRADING",AU360*'Custo Resumido'!D360,0) -> #DIV/0! | AR360: =IF('Entrada e Saida'!$H$11="TRADING",AU360*'Entrada e Saida'!$G$63,0) -> #DIV/0! | AS360: =IF('Entrada e Saida'!$H$11="TRADING",AU360*'Entrada e Saida'!$G$64,0) -> #DIV/0! | AT360: =IF('Entrada e Saida'!$H$11="TRADING",AU360*'Entrada e Saida'!$G$65,0) -> #DIV/0! | AU360: =IF('Entrada e Saida'!$H$11="TRADING",AP360/(1-(SUM('Entrada e Saida'!$G$63:$G$65)+'Custo Resumido'!D360)),0) -> #DIV/0! | AV360: =IF('Entrada e Saida'!$H$13="NÃO",AU360*M360,0) -> #DIV/0! | AW360: =AU360+AV360 -> #DIV/0! | AX360: ='Entrada e Saida'!$G$74*AU360 -> #DIV/0! | AY360: =AW360-AX360 -> #DIV/0! | AZ360: =AQ360+('Entrada e Saida'!$G$65-'Entrada e Saida'!$I$65)*AU360-AX360 -> #DIV/0! | BA360: =IF('Entrada e Saida'!$H$12="REAL",AZ360*'Entrada e Saida'!$G$81,AU360*'Entrada e Saida'!$G$81) -> #DIV/0! | BB360: =IF('Entrada e Saida'!$H$12="REAL",AZ360*'Entrada e Saida'!$G$82,AU360*'Entrada e Saida'!$G$82) -> #DIV/0! | BC360: =AZ360-BA360-BB360 -> #DIV/0! | BD360: =IF('Entrada e Saida'!$H$11="TRADING",AW360/D360,AK360/D360) -> #DIV/0! | BE360: =AX360/D360 -> #DIV/0! | BF360: =BD360-BE360 -> #DIV/0! | BG360: =IF('Entrada e Saida'!$H$11="TRADING",AV360/D360,AN360/D360) -> #DIV/0! | BH360: =IF('Entrada e Saida'!$H$11="TRADING",IF('Entrada e Saida'!$H$12="REAL",AR360/D360,0),AL360/D360) -> #DIV/0! | BI360: =IF('Entrada e Saida'!$H$11="TRADING",IF('Entrada e Saida'!$H$12="REAL",AS360/D360,0),AM360/D360) -> #DIV/0! | BJ360: =IF('Entrada e Saida'!$H$11="TRADING",AT360/D360,AO360/D360) -> #DIV/0! | BK360: =BF360-SUM(BG360:BJ360) -> #DIV/0! | BL360: =IF(O360>0,IFERROR(IF('Entrada e Saida'!$H$11="DIRETA",0,(IF('Entrada e Saida'!$H$14="P.JURIDICA",(BD360*(1+O360)*N360)-((BD360/(1+M360))*'Entrada e Saida'!$G$65),((Produtos!N360-'Entrada e Saida'!$G$65)*Produtos!BD360)))),0),0) -> 0 | BM360: =BF360+BL360 -> #DIV/0!
B361: =IFERROR(VLOOKUP(A361,'Master Modelo'!A:I,7,FALSE),0) -> 0 | C361: =IFERROR(VLOOKUP(A361,'Master Modelo'!A:I,2,FALSE),0) -> 0 | E361: =IFERROR(VLOOKUP(A361,'Master Modelo'!A:I,9,FALSE),0) -> 0 | F361: =IFERROR(VLOOKUP(A361,'Master Modelo'!A:I,8,FALSE),0) -> 0 | G361: =IFERROR(VLOOKUP(A361,'Master Modelo'!A:K,11,FALSE),0) -> 0 | H361: =(D361*E361)/(D361*F361) -> #DIV/0! | I361: =IFERROR(VLOOKUP(A361,'Master Modelo'!A:I,3,FALSE),0) -> 0 | J361: =IFERROR(VLOOKUP(A361,'Master Modelo'!A:I,5,FALSE),0) -> 0 | K361: =IFERROR(VLOOKUP(A361,'Master Modelo'!A:I,6,FALSE),0) -> 0 | L361: =VLOOKUP(A361,'Master Modelo'!A:J,10,FALSE) -> #N/A | M361: =IFERROR(VLOOKUP(A361,'Master Modelo'!A:I,4,FALSE),0) -> 0 | P361: =D361*F361 -> 0 | Q361: =D361*G361 -> 0 | R361: =D361*E361*'Entrada e Saida'!$K$8 -> 0 | S361: ='Entrada e Saida'!$H$21*'Entrada e Saida'!$K$8*(P361/(SUM(P:P))) -> #DIV/0! | T361: ='Entrada e Saida'!$H$21*'Entrada e Saida'!$K$8*(Q361/(SUM(Q:Q))) -> #DIV/0! | U361: ='Entrada e Saida'!$H$22*(P361/(SUM(P:P))) -> #DIV/0! | V361: ='Entrada e Saida'!$H$22*(Q361/(SUM(Q:Q))) -> #DIV/0! | W361: =R361+S361+U361 -> #DIV/0! | X361: ='Entrada e Saida'!$H$26*(IF('Entrada e Saida'!$H$15="PESO",(P361/(SUM(P:P))),(Q361/(SUM(Q:Q))))) -> #DIV/0! | Y361: ='Entrada e Saida'!$H$27*(IF('Entrada e Saida'!$H$15="PESO",(P361/(SUM(P:P))),(Q361/(SUM(Q:Q))))) -> #DIV/0! | Z361: ='Entrada e Saida'!$H$28*(IF('Entrada e Saida'!$H$15="PESO",(P361/(SUM(P:P))),(Q361/(SUM(Q:Q))))) -> #DIV/0! | AA361: =X361+Y361+Z361 -> #DIV/0! | AB361: =W361*I361 -> #DIV/0! | AC361: =W361*J361 -> #DIV/0! | AD361: =W361*K361 -> #DIV/0! | AE361: =(W361+AB361)*M361 -> #DIV/0! | AF361: =IFERROR(D361*F361*L361*'Entrada e Saida'!$K$8,0) -> 0 | AG361: =((W361+AA361+AB361+AC361+AD361+AE361+AF361)/(1-'Entrada e Saida'!$G$65))*'Entrada e Saida'!$I$66 -> #DIV/0! | AH361: =SUM(AB361:AG361) -> #DIV/0! | AI361: ='Entrada e Saida'!$K$51*(IF('Entrada e Saida'!$H$15="PESO",(P361/(SUM(P:P))),(Q361/(SUM(Q:Q))))) -> #DIV/0! | AJ361: =(('Entrada e Saida'!$K$10-'Entrada e Saida'!$K$8)*E361*D361) -> 0 | AK361: =IF('Entrada e Saida'!$H$15="PESO",W361+AA361+AH361+AI361+AJ361,W361+AA361+AH361+AI361+AJ361-S361+T361-U361+V361) -> #DIV/0! | AL361: =IF('Entrada e Saida'!$H$12="REAL",AC361,0) -> #DIV/0! | AM361: =IF('Entrada e Saida'!$H$12="REAL",AD361,0) -> #DIV/0! | AN361: =IF('Entrada e Saida'!$H$13= "NÃO",AE361,0) -> #DIV/0! | AO361: =AG361 -> #DIV/0! | AP361: =AK361-SUM(AL361:AO361) -> #DIV/0! | AQ361: =IF('Entrada e Saida'!$H$11="TRADING",AU361*'Custo Resumido'!D361,0) -> #DIV/0! | AR361: =IF('Entrada e Saida'!$H$11="TRADING",AU361*'Entrada e Saida'!$G$63,0) -> #DIV/0! | AS361: =IF('Entrada e Saida'!$H$11="TRADING",AU361*'Entrada e Saida'!$G$64,0) -> #DIV/0! | AT361: =IF('Entrada e Saida'!$H$11="TRADING",AU361*'Entrada e Saida'!$G$65,0) -> #DIV/0! | AU361: =IF('Entrada e Saida'!$H$11="TRADING",AP361/(1-(SUM('Entrada e Saida'!$G$63:$G$65)+'Custo Resumido'!D361)),0) -> #DIV/0! | AV361: =IF('Entrada e Saida'!$H$13="NÃO",AU361*M361,0) -> #DIV/0! | AW361: =AU361+AV361 -> #DIV/0! | AX361: ='Entrada e Saida'!$G$74*AU361 -> #DIV/0! | AY361: =AW361-AX361 -> #DIV/0! | AZ361: =AQ361+('Entrada e Saida'!$G$65-'Entrada e Saida'!$I$65)*AU361-AX361 -> #DIV/0! | BA361: =IF('Entrada e Saida'!$H$12="REAL",AZ361*'Entrada e Saida'!$G$81,AU361*'Entrada e Saida'!$G$81) -> #DIV/0! | BB361: =IF('Entrada e Saida'!$H$12="REAL",AZ361*'Entrada e Saida'!$G$82,AU361*'Entrada e Saida'!$G$82) -> #DIV/0! | BC361: =AZ361-BA361-BB361 -> #DIV/0! | BD361: =IF('Entrada e Saida'!$H$11="TRADING",AW361/D361,AK361/D361) -> #DIV/0! | BE361: =AX361/D361 -> #DIV/0! | BF361: =BD361-BE361 -> #DIV/0! | BG361: =IF('Entrada e Saida'!$H$11="TRADING",AV361/D361,AN361/D361) -> #DIV/0! | BH361: =IF('Entrada e Saida'!$H$11="TRADING",IF('Entrada e Saida'!$H$12="REAL",AR361/D361,0),AL361/D361) -> #DIV/0! | BI361: =IF('Entrada e Saida'!$H$11="TRADING",IF('Entrada e Saida'!$H$12="REAL",AS361/D361,0),AM361/D361) -> #DIV/0! | BJ361: =IF('Entrada e Saida'!$H$11="TRADING",AT361/D361,AO361/D361) -> #DIV/0! | BK361: =BF361-SUM(BG361:BJ361) -> #DIV/0! | BL361: =IF(O361>0,IFERROR(IF('Entrada e Saida'!$H$11="DIRETA",0,(IF('Entrada e Saida'!$H$14="P.JURIDICA",(BD361*(1+O361)*N361)-((BD361/(1+M361))*'Entrada e Saida'!$G$65),((Produtos!N361-'Entrada e Saida'!$G$65)*Produtos!BD361)))),0),0) -> 0 | BM361: =BF361+BL361 -> #DIV/0!
B362: =IFERROR(VLOOKUP(A362,'Master Modelo'!A:I,7,FALSE),0) -> 0 | C362: =IFERROR(VLOOKUP(A362,'Master Modelo'!A:I,2,FALSE),0) -> 0 | E362: =IFERROR(VLOOKUP(A362,'Master Modelo'!A:I,9,FALSE),0) -> 0 | F362: =IFERROR(VLOOKUP(A362,'Master Modelo'!A:I,8,FALSE),0) -> 0 | G362: =IFERROR(VLOOKUP(A362,'Master Modelo'!A:K,11,FALSE),0) -> 0 | H362: =(D362*E362)/(D362*F362) -> #DIV/0! | I362: =IFERROR(VLOOKUP(A362,'Master Modelo'!A:I,3,FALSE),0) -> 0 | J362: =IFERROR(VLOOKUP(A362,'Master Modelo'!A:I,5,FALSE),0) -> 0 | K362: =IFERROR(VLOOKUP(A362,'Master Modelo'!A:I,6,FALSE),0) -> 0 | L362: =VLOOKUP(A362,'Master Modelo'!A:J,10,FALSE) -> #N/A | M362: =IFERROR(VLOOKUP(A362,'Master Modelo'!A:I,4,FALSE),0) -> 0 | P362: =D362*F362 -> 0 | Q362: =D362*G362 -> 0 | R362: =D362*E362*'Entrada e Saida'!$K$8 -> 0 | S362: ='Entrada e Saida'!$H$21*'Entrada e Saida'!$K$8*(P362/(SUM(P:P))) -> #DIV/0! | T362: ='Entrada e Saida'!$H$21*'Entrada e Saida'!$K$8*(Q362/(SUM(Q:Q))) -> #DIV/0! | U362: ='Entrada e Saida'!$H$22*(P362/(SUM(P:P))) -> #DIV/0! | V362: ='Entrada e Saida'!$H$22*(Q362/(SUM(Q:Q))) -> #DIV/0! | W362: =R362+S362+U362 -> #DIV/0! | X362: ='Entrada e Saida'!$H$26*(IF('Entrada e Saida'!$H$15="PESO",(P362/(SUM(P:P))),(Q362/(SUM(Q:Q))))) -> #DIV/0! | Y362: ='Entrada e Saida'!$H$27*(IF('Entrada e Saida'!$H$15="PESO",(P362/(SUM(P:P))),(Q362/(SUM(Q:Q))))) -> #DIV/0! | Z362: ='Entrada e Saida'!$H$28*(IF('Entrada e Saida'!$H$15="PESO",(P362/(SUM(P:P))),(Q362/(SUM(Q:Q))))) -> #DIV/0! | AA362: =X362+Y362+Z362 -> #DIV/0! | AB362: =W362*I362 -> #DIV/0! | AC362: =W362*J362 -> #DIV/0! | AD362: =W362*K362 -> #DIV/0! | AE362: =(W362+AB362)*M362 -> #DIV/0! | AF362: =IFERROR(D362*F362*L362*'Entrada e Saida'!$K$8,0) -> 0 | AG362: =((W362+AA362+AB362+AC362+AD362+AE362+AF362)/(1-'Entrada e Saida'!$G$65))*'Entrada e Saida'!$I$66 -> #DIV/0! | AH362: =SUM(AB362:AG362) -> #DIV/0! | AI362: ='Entrada e Saida'!$K$51*(IF('Entrada e Saida'!$H$15="PESO",(P362/(SUM(P:P))),(Q362/(SUM(Q:Q))))) -> #DIV/0! | AJ362: =(('Entrada e Saida'!$K$10-'Entrada e Saida'!$K$8)*E362*D362) -> 0 | AK362: =IF('Entrada e Saida'!$H$15="PESO",W362+AA362+AH362+AI362+AJ362,W362+AA362+AH362+AI362+AJ362-S362+T362-U362+V362) -> #DIV/0! | AL362: =IF('Entrada e Saida'!$H$12="REAL",AC362,0) -> #DIV/0! | AM362: =IF('Entrada e Saida'!$H$12="REAL",AD362,0) -> #DIV/0! | AN362: =IF('Entrada e Saida'!$H$13= "NÃO",AE362,0) -> #DIV/0! | AO362: =AG362 -> #DIV/0! | AP362: =AK362-SUM(AL362:AO362) -> #DIV/0! | AQ362: =IF('Entrada e Saida'!$H$11="TRADING",AU362*'Custo Resumido'!D362,0) -> #DIV/0! | AR362: =IF('Entrada e Saida'!$H$11="TRADING",AU362*'Entrada e Saida'!$G$63,0) -> #DIV/0! | AS362: =IF('Entrada e Saida'!$H$11="TRADING",AU362*'Entrada e Saida'!$G$64,0) -> #DIV/0! | AT362: =IF('Entrada e Saida'!$H$11="TRADING",AU362*'Entrada e Saida'!$G$65,0) -> #DIV/0! | AU362: =IF('Entrada e Saida'!$H$11="TRADING",AP362/(1-(SUM('Entrada e Saida'!$G$63:$G$65)+'Custo Resumido'!D362)),0) -> #DIV/0! | AV362: =IF('Entrada e Saida'!$H$13="NÃO",AU362*M362,0) -> #DIV/0! | AW362: =AU362+AV362 -> #DIV/0! | AX362: ='Entrada e Saida'!$G$74*AU362 -> #DIV/0! | AY362: =AW362-AX362 -> #DIV/0! | AZ362: =AQ362+('Entrada e Saida'!$G$65-'Entrada e Saida'!$I$65)*AU362-AX362 -> #DIV/0! | BA362: =IF('Entrada e Saida'!$H$12="REAL",AZ362*'Entrada e Saida'!$G$81,AU362*'Entrada e Saida'!$G$81) -> #DIV/0! | BB362: =IF('Entrada e Saida'!$H$12="REAL",AZ362*'Entrada e Saida'!$G$82,AU362*'Entrada e Saida'!$G$82) -> #DIV/0! | BC362: =AZ362-BA362-BB362 -> #DIV/0! | BD362: =IF('Entrada e Saida'!$H$11="TRADING",AW362/D362,AK362/D362) -> #DIV/0! | BE362: =AX362/D362 -> #DIV/0! | BF362: =BD362-BE362 -> #DIV/0! | BG362: =IF('Entrada e Saida'!$H$11="TRADING",AV362/D362,AN362/D362) -> #DIV/0! | BH362: =IF('Entrada e Saida'!$H$11="TRADING",IF('Entrada e Saida'!$H$12="REAL",AR362/D362,0),AL362/D362) -> #DIV/0! | BI362: =IF('Entrada e Saida'!$H$11="TRADING",IF('Entrada e Saida'!$H$12="REAL",AS362/D362,0),AM362/D362) -> #DIV/0! | BJ362: =IF('Entrada e Saida'!$H$11="TRADING",AT362/D362,AO362/D362) -> #DIV/0! | BK362: =BF362-SUM(BG362:BJ362) -> #DIV/0! | BL362: =IF(O362>0,IFERROR(IF('Entrada e Saida'!$H$11="DIRETA",0,(IF('Entrada e Saida'!$H$14="P.JURIDICA",(BD362*(1+O362)*N362)-((BD362/(1+M362))*'Entrada e Saida'!$G$65),((Produtos!N362-'Entrada e Saida'!$G$65)*Produtos!BD362)))),0),0) -> 0 | BM362: =BF362+BL362 -> #DIV/0!
... B498: =IFERROR(VLOOKUP(A498,'Master Modelo'!A:I,7,FALSE),0) -> 0 | C498: =IFERROR(VLOOKUP(A498,'Master Modelo'!A:I,2,FALSE),0) -> 0 | E498: =IFERROR(VLOOKUP(A498,'Master Modelo'!A:I,9,FALSE),0) -> 0 | F498: =IFERROR(VLOOKUP(A498,'Master Modelo'!A:I,8,FALSE),0) -> 0 | G498: =IFERROR(VLOOKUP(A498,'Master Modelo'!A:K,11,FALSE),0) -> 0 | H498: =(D498*E498)/(D498*F498) -> #DIV/0! | I498: =IFERROR(VLOOKUP(A498,'Master Modelo'!A:I,3,FALSE),0) -> 0 | J498: =IFERROR(VLOOKUP(A498,'Master Modelo'!A:I,5,FALSE),0) -> 0 | K498: =IFERROR(VLOOKUP(A498,'Master Modelo'!A:I,6,FALSE),0) -> 0 | L498: =VLOOKUP(A498,'Master Modelo'!A:J,10,FALSE) -> #N/A | M498: =IFERROR(VLOOKUP(A498,'Master Modelo'!A:I,4,FALSE),0) -> 0 | P498: =D498*F498 -> 0 | Q498: =D498*G498 -> 0 | R498: =D498*E498*'Entrada e Saida'!$K$8 -> 0 | S498: ='Entrada e Saida'!$H$21*'Entrada e Saida'!$K$8*(P498/(SUM(P:P))) -> #DIV/0! | T498: ='Entrada e Saida'!$H$21*'Entrada e Saida'!$K$8*(Q498/(SUM(Q:Q))) -> #DIV/0! | U498: ='Entrada e Saida'!$H$22*(P498/(SUM(P:P))) -> #DIV/0! | V498: ='Entrada e Saida'!$H$22*(Q498/(SUM(Q:Q))) -> #DIV/0! | W498: =R498+S498+U498 -> #DIV/0! | X498: ='Entrada e Saida'!$H$26*(IF('Entrada e Saida'!$H$15="PESO",(P498/(SUM(P:P))),(Q498/(SUM(Q:Q))))) -> #DIV/0! | Y498: ='Entrada e Saida'!$H$27*(IF('Entrada e Saida'!$H$15="PESO",(P498/(SUM(P:P))),(Q498/(SUM(Q:Q))))) -> #DIV/0! | Z498: ='Entrada e Saida'!$H$28*(IF('Entrada e Saida'!$H$15="PESO",(P498/(SUM(P:P))),(Q498/(SUM(Q:Q))))) -> #DIV/0! | AA498: =X498+Y498+Z498 -> #DIV/0! | AB498: =W498*I498 -> #DIV/0! | AC498: =W498*J498 -> #DIV/0! | AD498: =W498*K498 -> #DIV/0! | AE498: =(W498+AB498)*M498 -> #DIV/0! | AF498: =IFERROR(D498*F498*L498*'Entrada e Saida'!$K$8,0) -> 0 | AG498: =((W498+AA498+AB498+AC498+AD498+AE498+AF498)/(1-'Entrada e Saida'!$G$65))*'Entrada e Saida'!$I$66 -> #DIV/0! | AH498: =SUM(AB498:AG498) -> #DIV/0! | AI498: ='Entrada e Saida'!$K$51*(IF('Entrada e Saida'!$H$15="PESO",(P498/(SUM(P:P))),(Q498/(SUM(Q:Q))))) -> #DIV/0! | AJ498: =(('Entrada e Saida'!$K$10-'Entrada e Saida'!$K$8)*E498*D498) -> 0 | AK498: =IF('Entrada e Saida'!$H$15="PESO",W498+AA498+AH498+AI498+AJ498,W498+AA498+AH498+AI498+AJ498-S498+T498-U498+V498) -> #DIV/0! | AL498: =IF('Entrada e Saida'!$H$12="REAL",AC498,0) -> #DIV/0! | AM498: =IF('Entrada e Saida'!$H$12="REAL",AD498,0) -> #DIV/0! | AN498: =IF('Entrada e Saida'!$H$13= "NÃO",AE498,0) -> #DIV/0! | AO498: =AG498 -> #DIV/0! | AP498: =AK498-SUM(AL498:AO498) -> #DIV/0! | AQ498: =IF('Entrada e Saida'!$H$11="TRADING",AU498*'Custo Resumido'!D498,0) -> #DIV/0! | AR498: =IF('Entrada e Saida'!$H$11="TRADING",AU498*'Entrada e Saida'!$G$63,0) -> #DIV/0! | AS498: =IF('Entrada e Saida'!$H$11="TRADING",AU498*'Entrada e Saida'!$G$64,0) -> #DIV/0! | AT498: =IF('Entrada e Saida'!$H$11="TRADING",AU498*'Entrada e Saida'!$G$65,0) -> #DIV/0! | AU498: =IF('Entrada e Saida'!$H$11="TRADING",AP498/(1-(SUM('Entrada e Saida'!$G$63:$G$65)+'Custo Resumido'!D498)),0) -> #DIV/0! | AV498: =IF('Entrada e Saida'!$H$13="NÃO",AU498*M498,0) -> #DIV/0! | AW498: =AU498+AV498 -> #DIV/0! | AX498: ='Entrada e Saida'!$G$74*AU498 -> #DIV/0! | AY498: =AW498-AX498 -> #DIV/0! | AZ498: =AQ498+('Entrada e Saida'!$G$65-'Entrada e Saida'!$I$65)*AU498-AX498 -> #DIV/0! | BA498: =IF('Entrada e Saida'!$H$12="REAL",AZ498*'Entrada e Saida'!$G$81,AU498*'Entrada e Saida'!$G$81) -> #DIV/0! | BB498: =IF('Entrada e Saida'!$H$12="REAL",AZ498*'Entrada e Saida'!$G$82,AU498*'Entrada e Saida'!$G$82) -> #DIV/0! | BC498: =AZ498-BA498-BB498 -> #DIV/0! | BD498: =IF('Entrada e Saida'!$H$11="TRADING",AW498/D498,AK498/D498) -> #DIV/0! | BE498: =AX498/D498 -> #DIV/0! | BF498: =BD498-BE498 -> #DIV/0! | BG498: =IF('Entrada e Saida'!$H$11="TRADING",AV498/D498,AN498/D498) -> #DIV/0! | BH498: =IF('Entrada e Saida'!$H$11="TRADING",IF('Entrada e Saida'!$H$12="REAL",AR498/D498,0),AL498/D498) -> #DIV/0! | BI498: =IF('Entrada e Saida'!$H$11="TRADING",IF('Entrada e Saida'!$H$12="REAL",AS498/D498,0),AM498/D498) -> #DIV/0! | BJ498: =IF('Entrada e Saida'!$H$11="TRADING",AT498/D498,AO498/D498) -> #DIV/0! | BK498: =BF498-SUM(BG498:BJ498) -> #DIV/0! | BL498: =IF(O498>0,IFERROR(IF('Entrada e Saida'!$H$11="DIRETA",0,(IF('Entrada e Saida'!$H$14="P.JURIDICA",(BD498*(1+O498)*N498)-((BD498/(1+M498))*'Entrada e Saida'!$G$65),((Produtos!N498-'Entrada e Saida'!$G$65)*Produtos!BD498)))),0),0) -> 0 | BM498: =BF498+BL498 -> #DIV/0!

Sheet Entrada e Saida
C3: FECHAMENTO / ESTIMATIVA DE OPERAÇÃO - MEMÓRIAS DE CÁLCULO
G5: CLIENTE: | H5: MARCHA | K5: 0488/26
G6: OPERAÇÃO: | H6: COMPRA E VENDA
G7: FECHAMENTO: | H7: HC-021 | K7: Dólar DI:
G8: Qtde Containers | H8: 1x40 | K8: 5.2275
G9: Peso Total | H9: =SUM(Produtos!P:P) -> 0 | K9: Dolar Cambio
G10: Valor Total | H10: =SUMPRODUCT(Produtos!D:D,Produtos!E:E) -> #N/A | K10: 5.2275 | N10: PESO BRUTO | O10: CXAS
G11: TIPO OPERAÇÃO | H11: TRADING | N11: 13588.8 | O11: 1233
G12: LUCRO | H12: REAL | N12: =N11-H9 -> 13588.8
G13: BENEFICIO IPI | H13: NÃO | N13: =N12/O11 -> 11.020925
G14: CONSUMIDOR | H14: P.JURIDICA
G15: RATEIO | H15: PESO
E17: CONTA | G17: REFERÊNCIAS | K17: VALOR
G18: Qtde | H18: Valor | I18: Moeda
C20: VALOR ADUANEIRO | E20: CUSTO FOB | H20: =K20/I21 -> #N/A | K20: =SUM(Produtos!R:R) -> #N/A
E21: FRETE INTERNACIONAL | H21: 1150 | I21: =K8 -> 5.2275 | K21: =H21*I21 -> 6011.625
E22: CUSTO EXTRA | H22: 0 | K22: =H22 -> 0
E24: VALOR ADUANEIRO: | K24: =SUM(K20:K22) -> #N/A
E26: SISCOMEX | H26: 401.04 | K26: =H26 -> 401.04
E27: MARINHA MERCANTE - AFRMM | H27: 561.16 | K27: =H27 -> 561.16
E28: OUTRAS DESP. ADUANEIRAS | H28: 0 | K28: 0
E30: DESPESAS ADUANEIRAS: | K30: =SUM(K26:K28) -> 962.2
C32: IMPOSTOS | E32: IMPOSTO DE IMPORTAÇÃO - II | K32: =SUM(Produtos!AB:AB) -> #N/A
E33: PROG. INTEGRAÇÃO SOCIAL - PIS | K33: =SUM(Produtos!AC:AC) -> #N/A
E34: CONTRIB. FINANC. SEGURIDADE SOCIAL - COFINS | K34: =SUM(Produtos!AD:AD) -> #N/A
E35: IMPOSTO PRODUTOS INDUSTRIALIZADOS - IPI | K35: =SUM(Produtos!AE:AE) -> #N/A
E36: DUMPING | K36: =SUM(Produtos!AF:AF) -> 0
E37: IMPOSTO CIRCULAÇÃO MERCADORIA - ICMS | K37: =SUM(Produtos!AG:AG) -> #N/A
E39: IMPOSTOS NACIONALIZAÇÃO: | K39: =SUM(K32:K37) -> #N/A
C41: DESPESAS OPERACIONAIS | E41: ARMAZENAGEM - ZONA PRIMÁRIA | H41: 6000 | K41: =H41 -> 6000
E42: DIFERENÇA FRETE INTERNACIONAL | H42: 0 | K42: =H42 -> 0
E43: DESPACHANTE | H43: 3400 | K43: =H43 -> 3400
E44: TAXA DUIMP | H44: 180 | K44: =H44 -> 180
E45: TAXAS BL | H45: 2692.39 | K45: =H45 -> 2692.39
E46: TARIFA CAMBIAL | H46: 400 | K46: =H46 -> 400
E47: CERTIFICAÇÃO | H47: 0 | K47: =H47 -> 0
E48: TAXA DE EXPEDIENTE | H48: 400 | K48: =H48 -> 400
E49: FRETE AO CLIENTE | H49: 8000 | K49: =H49 -> 8000
E51: DESPESAS OPERACIONAIS: | K51: =SUM(K41:K49) -> 21072.39
E53: VARIAÇÃO CAMBIAL | K53: =SUM(Produtos!AJ:AJ) -> #N/A
E55: CUSTO TOTAL DA OPERAÇÃO: | K55: =K24+K30+K39+K51+K53 -> #N/A
C57: OPERAÇÃO TRADING | E57: CRÉDITO PIS | K57: =IF(H12="REAL",K33,0) -> #N/A
E58: CRÉDITO COFINS | K58: =IF(H12="REAL",K34,0) -> #N/A
E59: CRÉDITO IPI | K59: =IF(H13= "NÃO",K35,0) -> #N/A
E60: CRÉDITO ICMS | K60: =K37 -> #N/A
E61: CUSTO DE ESTOQUE | K61: =K55-K57-K58-K59-K60 -> #N/A
E62: CUSTO TRADING | G62: =K62/K67 -> #N/A | K62: =SUM(Produtos!AQ:AQ) -> #N/A | O62: 51951
E63: DÉBITO PIS | G63: =IF(H12="REAL",1.65%,0.65%) -> 0.0165 | K63: =SUM(Produtos!AR:AR) -> #N/A
E64: DÉBITO COFINS | G64: =IF(H12="REAL",7.6%,3%) -> 0.076 | K64: =SUM(Produtos!AS:AS) -> #N/A | O64: =K63+K64+K65+K68 -> #N/A
E65: DÉBITO ICMS | G65: 0.04 | H65: Pag.Efetivo | I65: 0.04 | K65: =SUM(Produtos!AT:AT) -> #N/A | O65: =O64-O62 -> #N/A
H66: Pag.Desembaraço | I66: 0.04
E67: VALOR SEM IPI | K67: =SUM(K61:K65) -> #N/A
E68: IPI DESTACADO | K68: =SUM(Produtos!AV:AV) -> #N/A
E71: NOTA FISCAL DE SAÍDA / VENDA | K71: =IF(H11="DIRETA",K55,SUM(K67:K69)) -> #N/A
E74: Desconto comercial (ICMS) | G74: 0 | K74: =SUM(Produtos!AX:AX) -> #N/A
E76: Valor a Pagar | K76: =K71-K74 -> #N/A
E77: ST | K77: =SUMPRODUCT(Produtos!BL:BL,Produtos!D:D) -> 0
E80: LUCRO BRUTO OPERAÇÃO | K80: =SUM(Produtos!AZ:AZ) -> #N/A
E81: IR | G81: =IF(H12="REAL",25%,2%) -> 0.25 | K81: =SUM(Produtos!BA:BA) -> #N/A
E82: CSLL | G82: =IF(H12="REAL",9%,1.08%) -> 0.09 | K82: =SUM(Produtos!BB:BB) -> #N/A
E84: LUCRO LIQUIDO | K84: =SUM(Produtos!BC:BC) -> #N/A
K85: =K84/K67 -> #N/A
B87: DEPOSITAR NEEMAN: DESPESAS ADUANEIRAS + IMPOSTOS DE NACIONALIZAÇÃO + DESPESAS OPERACIONAIS | J87: =K30+K39+K51 -> #N/A

Sheet Custo Resumido
A1: PRODUTO | B1: FOTO | C1: DESCRIÇÃO | D1: MARKUP | E1: =Produtos!BD1 -> Valor Venda Unit. C/IPI | F1: =Produtos!BE1 -> Desconto | G1: =Produtos!BF1 -> Valor Final C/Desc. | H1: =Produtos!BL1 -> VALOR ST | I1: =Produtos!BM1 -> Valor Final C/Desc.+IPI+ST | J1: =Produtos!BG1 -> Credito Unit. IPI | K1: =Produtos!BH1 -> Credito Unit PIS | L1: =Produtos!BI1 -> Credito Unit. Cofins | M1: =Produtos!BJ1 -> Credito Unit. ICMS
A2: =Produtos!A2 -> 0 | C2: =Produtos!B2 -> #N/A | D2: 0.1 | E2: =Produtos!BD2 -> #N/A | F2: =Produtos!BE2 -> #N/A | G2: =Produtos!BF2 -> #N/A | H2: =Produtos!BL2 -> 0 | I2: =Produtos!BM2 -> #N/A | J2: =Produtos!BG2 -> #N/A | K2: =Produtos!BH2 -> #N/A | L2: =Produtos!BI2 -> #N/A | M2: =Produtos!BJ2 -> #N/A
A3: =Produtos!A3 -> 0 | C3: =Produtos!B3 -> #N/A | D3: 0.1 | E3: =Produtos!BD3 -> #DIV/0! | F3: =Produtos!BE3 -> #DIV/0! | G3: =Produtos!BF3 -> #DIV/0! | H3: =Produtos!BL3 -> 0 | I3: =Produtos!BM3 -> #DIV/0! | J3: =Produtos!BG3 -> #DIV/0! | K3: =Produtos!BH3 -> #DIV/0! | L3: =Produtos!BI3 -> #DIV/0! | M3: =Produtos!BJ3 -> #DIV/0!
A4: =Produtos!A4 -> 0 | C4: =Produtos!B4 -> #N/A | D4: 0.1 | E4: =Produtos!BD4 -> #DIV/0! | F4: =Produtos!BE4 -> #DIV/0! | G4: =Produtos!BF4 -> #DIV/0! | H4: =Produtos!BL4 -> 0 | I4: =Produtos!BM4 -> #DIV/0! | J4: =Produtos!BG4 -> #DIV/0! | K4: =Produtos!BH4 -> #DIV/0! | L4: =Produtos!BI4 -> #DIV/0! | M4: =Produtos!BJ4 -> #DIV/0!
A5: =Produtos!A5 -> 0 | C5: =Produtos!B5 -> #N/A | D5: 0.1 | E5: =Produtos!BD5 -> #DIV/0! | F5: =Produtos!BE5 -> #DIV/0! | G5: =Produtos!BF5 -> #DIV/0! | H5: =Produtos!BL5 -> 0 | I5: =Produtos!BM5 -> #DIV/0! | J5: =Produtos!BG5 -> #DIV/0! | K5: =Produtos!BH5 -> #DIV/0! | L5: =Produtos!BI5 -> #DIV/0! | M5: =Produtos!BJ5 -> #DIV/0!
A6: =Produtos!A6 -> 0 | C6: =Produtos!B6 -> #N/A | D6: 0.1 | E6: =Produtos!BD6 -> #DIV/0! | F6: =Produtos!BE6 -> #DIV/0! | G6: =Produtos!BF6 -> #DIV/0! | H6: =Produtos!BL6 -> 0 | I6: =Produtos!BM6 -> #DIV/0! | J6: =Produtos!BG6 -> #DIV/0! | K6: =Produtos!BH6 -> #DIV/0! | L6: =Produtos!BI6 -> #DIV/0! | M6: =Produtos!BJ6 -> #DIV/0!
A7: =Produtos!A7 -> 0 | C7: =Produtos!B7 -> #N/A | D7: 0.1 | E7: =Produtos!BD7 -> #DIV/0! | F7: =Produtos!BE7 -> #DIV/0! | G7: =Produtos!BF7 -> #DIV/0! | H7: =Produtos!BL7 -> 0 | I7: =Produtos!BM7 -> #DIV/0! | J7: =Produtos!BG7 -> #DIV/0! | K7: =Produtos!BH7 -> #DIV/0! | L7: =Produtos!BI7 -> #DIV/0! | M7: =Produtos!BJ7 -> #DIV/0!
A8: =Produtos!A8 -> 0 | C8: =Produtos!B8 -> #N/A | D8: 0.1 | E8: =Produtos!BD8 -> #DIV/0! | F8: =Produtos!BE8 -> #DIV/0! | G8: =Produtos!BF8 -> #DIV/0! | H8: =Produtos!BL8 -> 0 | I8: =Produtos!BM8 -> #DIV/0! | J8: =Produtos!BG8 -> #DIV/0! | K8: =Produtos!BH8 -> #DIV/0! | L8: =Produtos!BI8 -> #DIV/0! | M8: =Produtos!BJ8 -> #DIV/0!
A9: =Produtos!A9 -> 0 | C9: =Produtos!B9 -> #N/A | D9: 0.1 | E9: =Produtos!BD9 -> #DIV/0! | F9: =Produtos!BE9 -> #DIV/0! | G9: =Produtos!BF9 -> #DIV/0! | H9: =Produtos!BL9 -> 0 | I9: =Produtos!BM9 -> #DIV/0! | J9: =Produtos!BG9 -> #DIV/0! | K9: =Produtos!BH9 -> #DIV/0! | L9: =Produtos!BI9 -> #DIV/0! | M9: =Produtos!BJ9 -> #DIV/0!
A10: =Produtos!A10 -> 0 | C10: =Produtos!B10 -> #N/A | D10: 0.1 | E10: =Produtos!BD10 -> #DIV/0! | F10: =Produtos!BE10 -> #DIV/0! | G10: =Produtos!BF10 -> #DIV/0! | H10: =Produtos!BL10 -> 0 | I10: =Produtos!BM10 -> #DIV/0! | J10: =Produtos!BG10 -> #DIV/0! | K10: =Produtos!BH10 -> #DIV/0! | L10: =Produtos!BI10 -> #DIV/0! | M10: =Produtos!BJ10 -> #DIV/0!
A11: =Produtos!A11 -> 0 | C11: =Produtos!B11 -> #N/A | D11: 0.1 | E11: =Produtos!BD11 -> #DIV/0! | F11: =Produtos!BE11 -> #DIV/0! | G11: =Produtos!BF11 -> #DIV/0! | H11: =Produtos!BL11 -> 0 | I11: =Produtos!BM11 -> #DIV/0! | J11: =Produtos!BG11 -> #DIV/0! | K11: =Produtos!BH11 -> #DIV/0! | L11: =Produtos!BI11 -> #DIV/0! | M11: =Produtos!BJ11 -> #DIV/0!
A12: =Produtos!A12 -> 0 | C12: =Produtos!B12 -> #N/A | D12: 0.1 | E12: =Produtos!BD12 -> #DIV/0! | F12: =Produtos!BE12 -> #DIV/0! | G12: =Produtos!BF12 -> #DIV/0! | H12: =Produtos!BL12 -> 0 | I12: =Produtos!BM12 -> #DIV/0! | J12: =Produtos!BG12 -> #DIV/0! | K12: =Produtos!BH12 -> #DIV/0! | L12: =Produtos!BI12 -> #DIV/0! | M12: =Produtos!BJ12 -> #DIV/0!
A13: =Produtos!A13 -> 0 | C13: =Produtos!B13 -> #N/A | D13: 0.1 | E13: =Produtos!BD13 -> #DIV/0! | F13: =Produtos!BE13 -> #DIV/0! | G13: =Produtos!BF13 -> #DIV/0! | H13: =Produtos!BL13 -> 0 | I13: =Produtos!BM13 -> #DIV/0! | J13: =Produtos!BG13 -> #DIV/0! | K13: =Produtos!BH13 -> #DIV/0! | L13: =Produtos!BI13 -> #DIV/0! | M13: =Produtos!BJ13 -> #DIV/0!
... A19: =Produtos!A19 -> 0 | C19: =Produtos!B19 -> #N/A | D19: 0.1 | E19: =Produtos!BD19 -> #DIV/0! | F19: =Produtos!BE19 -> #DIV/0! | G19: =Produtos!BF19 -> #DIV/0! | H19: =Produtos!BL19 -> 0 | I19: =Produtos!BM19 -> #DIV/0! | J19: =Produtos!BG19 -> #DIV/0! | K19: =Produtos!BH19 -> #DIV/0! | L19: =Produtos!BI19 -> #DIV/0! | M19: =Produtos!BJ19 -> #DIV/0!
A20: =Produtos!A20 -> 0 | C20: =Produtos!B20 -> #N/A | E20: =Produtos!BD20 -> #DIV/0! | F20: =Produtos!BE20 -> #DIV/0! | G20: =Produtos!BF20 -> #DIV/0! | H20: =Produtos!BL20 -> 0 | I20: =Produtos!BM20 -> #DIV/0! | J20: =Produtos!BG20 -> #DIV/0! | K20: =Produtos!BH20 -> #DIV/0! | L20: =Produtos!BI20 -> #DIV/0! | M20: =Produtos!BJ20 -> #DIV/0!
A21: =Produtos!A21 -> 0 | C21: =Produtos!B21 -> #N/A | E21: =Produtos!BD21 -> #DIV/0! | F21: =Produtos!BE21 -> #DIV/0! | G21: =Produtos!BF21 -> #DIV/0! | H21: =Produtos!BL21 -> 0 | I21: =Produtos!BM21 -> #DIV/0! | J21: =Produtos!BG21 -> #DIV/0! | K21: =Produtos!BH21 -> #DIV/0! | L21: =Produtos!BI21 -> #DIV/0! | M21: =Produtos!BJ21 -> #DIV/0!
A22: =Produtos!A22 -> 0 | C22: =Produtos!B22 -> #N/A | E22: =Produtos!BD22 -> #DIV/0! | F22: =Produtos!BE22 -> #DIV/0! | G22: =Produtos!BF22 -> #DIV/0! | H22: =Produtos!BL22 -> 0 | I22: =Produtos!BM22 -> #DIV/0! | J22: =Produtos!BG22 -> #DIV/0! | K22: =Produtos!BH22 -> #DIV/0! | L22: =Produtos!BI22 -> #DIV/0! | M22: =Produtos!BJ22 -> #DIV/0!
A23: =Produtos!A23 -> 0 | C23: =Produtos!B23 -> #N/A | E23: =Produtos!BD23 -> #DIV/0! | F23: =Produtos!BE23 -> #DIV/0! | G23: =Produtos!BF23 -> #DIV/0! | H23: =Produtos!BL23 -> 0 | I23: =Produtos!BM23 -> #DIV/0! | J23: =Produtos!BG23 -> #DIV/0! | K23: =Produtos!BH23 -> #DIV/0! | L23: =Produtos!BI23 -> #DIV/0! | M23: =Produtos!BJ23 -> #DIV/0!
A24: =Produtos!A24 -> 0 | C24: =Produtos!B24 -> #N/A | E24: =Produtos!BD24 -> #DIV/0! | F24: =Produtos!BE24 -> #DIV/0! | G24: =Produtos!BF24 -> #DIV/0! | H24: =Produtos!BL24 -> 0 | I24: =Produtos!BM24 -> #DIV/0! | J24: =Produtos!BG24 -> #DIV/0! | K24: =Produtos!BH24 -> #DIV/0! | L24: =Produtos!BI24 -> #DIV/0! | M24: =Produtos!BJ24 -> #DIV/0!
A25: =Produtos!A25 -> 0 | C25: =Produtos!B25 -> #N/A | E25: =Produtos!BD25 -> #DIV/0! | F25: =Produtos!BE25 -> #DIV/0! | G25: =Produtos!BF25 -> #DIV/0! | H25: =Produtos!BL25 -> 0 | I25: =Produtos!BM25 -> #DIV/0! | J25: =Produtos!BG25 -> #DIV/0! | K25: =Produtos!BH25 -> #DIV/0! | L25: =Produtos!BI25 -> #DIV/0! | M25: =Produtos!BJ25 -> #DIV/0!
A26: =Produtos!A26 -> 0 | C26: =Produtos!B26 -> #N/A | E26: =Produtos!BD26 -> #DIV/0! | F26: =Produtos!BE26 -> #DIV/0! | G26: =Produtos!BF26 -> #DIV/0! | H26: =Produtos!BL26 -> 0 | I26: =Produtos!BM26 -> #DIV/0! | J26: =Produtos!BG26 -> #DIV/0! | K26: =Produtos!BH26 -> #DIV/0! | L26: =Produtos!BI26 -> #DIV/0! | M26: =Produtos!BJ26 -> #DIV/0!
A27: =Produtos!A27 -> 0 | C27: =Produtos!B27 -> #N/A | E27: =Produtos!BD27 -> #DIV/0! | F27: =Produtos!BE27 -> #DIV/0! | G27: =Produtos!BF27 -> #DIV/0! | H27: =Produtos!BL27 -> 0 | I27: =Produtos!BM27 -> #DIV/0! | J27: =Produtos!BG27 -> #DIV/0! | K27: =Produtos!BH27 -> #DIV/0! | L27: =Produtos!BI27 -> #DIV/0! | M27: =Produtos!BJ27 -> #DIV/0!
A28: =Produtos!A28 -> 0 | C28: =Produtos!B28 -> #N/A | E28: =Produtos!BD28 -> #DIV/0! | F28: =Produtos!BE28 -> #DIV/0! | G28: =Produtos!BF28 -> #DIV/0! | H28: =Produtos!BL28 -> 0 | I28: =Produtos!BM28 -> #DIV/0! | J28: =Produtos!BG28 -> #DIV/0! | K28: =Produtos!BH28 -> #DIV/0! | L28: =Produtos!BI28 -> #DIV/0! | M28: =Produtos!BJ28 -> #DIV/0!
A29: =Produtos!A29 -> 0 | C29: =Produtos!B29 -> #N/A | E29: =Produtos!BD29 -> #DIV/0! | F29: =Produtos!BE29 -> #DIV/0! | G29: =Produtos!BF29 -> #DIV/0! | H29: =Produtos!BL29 -> 0 | I29: =Produtos!BM29 -> #DIV/0! | J29: =Produtos!BG29 -> #DIV/0! | K29: =Produtos!BH29 -> #DIV/0! | L29: =Produtos!BI29 -> #DIV/0! | M29: =Produtos!BJ29 -> #DIV/0!
A30: =Produtos!A30 -> 0 | C30: =Produtos!B30 -> #N/A | E30: =Produtos!BD30 -> #DIV/0! | F30: =Produtos!BE30 -> #DIV/0! | G30: =Produtos!BF30 -> #DIV/0! | H30: =Produtos!BL30 -> 0 | I30: =Produtos!BM30 -> #DIV/0! | J30: =Produtos!BG30 -> #DIV/0! | K30: =Produtos!BH30 -> #DIV/0! | L30: =Produtos!BI30 -> #DIV/0! | M30: =Produtos!BJ30 -> #DIV/0!
A31: =Produtos!A31 -> 0 | C31: =Produtos!B31 -> #N/A | E31: =Produtos!BD31 -> #DIV/0! | F31: =Produtos!BE31 -> #DIV/0! | G31: =Produtos!BF31 -> #DIV/0! | H31: =Produtos!BL31 -> 0 | I31: =Produtos!BM31 -> #DIV/0! | J31: =Produtos!BG31 -> #DIV/0! | K31: =Produtos!BH31 -> #DIV/0! | L31: =Produtos!BI31 -> #DIV/0! | M31: =Produtos!BJ31 -> #DIV/0!
... A498: =Produtos!A498 -> 0 | C498: =Produtos!B498 -> 0 | E498: =Produtos!BD498 -> #DIV/0! | F498: =Produtos!BE498 -> #DIV/0! | G498: =Produtos!BF498 -> #DIV/0! | H498: =Produtos!BL498 -> 0 | I498: =Produtos!BM498 -> #DIV/0! | J498: =Produtos!BG498 -> #DIV/0! | K498: =Produtos!BH498 -> #DIV/0! | L498: =Produtos!BI498 -> #DIV/0! | M498: =Produtos!BJ498 -> #DIV/0!

Sheet Siscex
A1: PRODUTO | B1: NCM | C1: DESCRICAO | D1: QTDE | E1: UNIDADE | F1: PESOTOT | G1: FOBTOT
A2: =Produtos!A2 -> 0 | B2: =Produtos!C2 -> #N/A | C2: =Produtos!B2 -> #N/A | D2: =Produtos!D2 -> 0 | E2: 76 | F2: =Produtos!P2 -> 0 | G2: =Produtos!D2*Produtos!E2 -> #N/A
A3: =Produtos!A3 -> 0 | B3: =Produtos!C3 -> #N/A | C3: =Produtos!B3 -> #N/A | D3: =Produtos!D3 -> 0 | E3: 76 | F3: =Produtos!P3 -> 0 | G3: =Produtos!D3*Produtos!E3 -> 0
A4: =Produtos!A4 -> 0 | B4: =Produtos!C4 -> #N/A | C4: =Produtos!B4 -> #N/A | D4: =Produtos!D4 -> 0 | E4: 76 | F4: =Produtos!P4 -> 0 | G4: =Produtos!D4*Produtos!E4 -> 0
A5: =Produtos!A5 -> 0 | B5: =Produtos!C5 -> #N/A | C5: =Produtos!B5 -> #N/A | D5: =Produtos!D5 -> 0 | E5: 76 | F5: =Produtos!P5 -> 0 | G5: =Produtos!D5*Produtos!E5 -> 0
A6: =Produtos!A6 -> 0 | B6: =Produtos!C6 -> #N/A | C6: =Produtos!B6 -> #N/A | D6: =Produtos!D6 -> 0 | E6: 76 | F6: =Produtos!P6 -> 0 | G6: =Produtos!D6*Produtos!E6 -> 0
A7: =Produtos!A7 -> 0 | B7: =Produtos!C7 -> #N/A | C7: =Produtos!B7 -> #N/A | D7: =Produtos!D7 -> 0 | E7: 76 | F7: =Produtos!P7 -> 0 | G7: =Produtos!D7*Produtos!E7 -> 0
A8: =Produtos!A8 -> 0 | B8: =Produtos!C8 -> #N/A | C8: =Produtos!B8 -> #N/A | D8: =Produtos!D8 -> 0 | E8: 76 | F8: =Produtos!P8 -> 0 | G8: =Produtos!D8*Produtos!E8 -> 0
A9: =Produtos!A9 -> 0 | B9: =Produtos!C9 -> #N/A | C9: =Produtos!B9 -> #N/A | D9: =Produtos!D9 -> 0 | E9: 76 | F9: =Produtos!P9 -> 0 | G9: =Produtos!D9*Produtos!E9 -> 0
A10: =Produtos!A10 -> 0 | B10: =Produtos!C10 -> #N/A | C10: =Produtos!B10 -> #N/A | D10: =Produtos!D10 -> 0 | E10: 79 | F10: =Produtos!P10 -> 0 | G10: =Produtos!D10*Produtos!E10 -> 0
A11: =Produtos!A11 -> 0 | B11: =Produtos!C11 -> #N/A | C11: =Produtos!B11 -> #N/A | D11: =Produtos!D11 -> 0 | E11: 76 | F11: =Produtos!P11 -> 0 | G11: =Produtos!D11*Produtos!E11 -> 0
A12: =Produtos!A12 -> 0 | B12: =Produtos!C12 -> #N/A | C12: =Produtos!B12 -> #N/A | D12: =Produtos!D12 -> 0 | E12: 76 | F12: =Produtos!P12 -> 0 | G12: =Produtos!D12*Produtos!E12 -> 0
A13: =Produtos!A13 -> 0 | B13: =Produtos!C13 -> #N/A | C13: =Produtos!B13 -> #N/A | D13: =Produtos!D13 -> 0 | E13: 76 | F13: =Produtos!P13 -> 0 | G13: =Produtos!D13*Produtos!E13 -> 0
... A19: =Produtos!A19 -> 0 | B19: =Produtos!C19 -> #N/A | C19: =Produtos!B19 -> #N/A | D19: =Produtos!D19 -> 0 | E19: 19 | F19: =Produtos!P19 -> 0 | G19: =Produtos!D19*Produtos!E19 -> 0
A20: =Produtos!A20 -> 0 | B20: =Produtos!C20 -> #N/A | C20: =Produtos!B20 -> #N/A | D20: =Produtos!D20 -> 0 | E20: PEÇAS | F20: =Produtos!P20 -> 0 | G20: =Produtos!D20*Produtos!E20 -> 0
A21: =Produtos!A21 -> 0 | B21: =Produtos!C21 -> #N/A | C21: =Produtos!B21 -> #N/A | D21: =Produtos!D21 -> 0 | E21: PEÇAS | F21: =Produtos!P21 -> 0 | G21: =Produtos!D21*Produtos!E21 -> 0
A22: =Produtos!A22 -> 0 | B22: =Produtos!C22 -> #N/A | C22: =Produtos!B22 -> #N/A | D22: =Produtos!D22 -> 0 | E22: PEÇAS | F22: =Produtos!P22 -> 0 | G22: =Produtos!D22*Produtos!E22 -> 0
A23: =Produtos!A23 -> 0 | B23: =Produtos!C23 -> #N/A | C23: =Produtos!B23 -> #N/A | D23: =Produtos!D23 -> 0 | E23: PEÇAS | F23: =Produtos!P23 -> 0 | G23: =Produtos!D23*Produtos!E23 -> 0
A24: =Produtos!A24 -> 0 | B24: =Produtos!C24 -> #N/A | C24: =Produtos!B24 -> #N/A | D24: =Produtos!D24 -> 0 | E24: PEÇAS | F24: =Produtos!P24 -> 0 | G24: =Produtos!D24*Produtos!E24 -> 0
A25: =Produtos!A25 -> 0 | B25: =Produtos!C25 -> #N/A | C25: =Produtos!B25 -> #N/A | D25: =Produtos!D25 -> 0 | E25: PEÇAS | F25: =Produtos!P25 -> 0 | G25: =Produtos!D25*Produtos!E25 -> 0
A26: =Produtos!A26 -> 0 | B26: =Produtos!C26 -> #N/A | C26: =Produtos!B26 -> #N/A | D26: =Produtos!D26 -> 0 | E26: PEÇAS | F26: =Produtos!P26 -> 0 | G26: =Produtos!D26*Produtos!E26 -> 0
A27: =Produtos!A27 -> 0 | B27: =Produtos!C27 -> #N/A | C27: =Produtos!B27 -> #N/A | D27: =Produtos!D27 -> 0 | E27: PEÇAS | F27: =Produtos!P27 -> 0 | G27: =Produtos!D27*Produtos!E27 -> 0
A28: =Produtos!A28 -> 0 | B28: =Produtos!C28 -> #N/A | C28: =Produtos!B28 -> #N/A | D28: =Produtos!D28 -> 0 | E28: PEÇAS | F28: =Produtos!P28 -> 0 | G28: =Produtos!D28*Produtos!E28 -> 0
A29: =Produtos!A29 -> 0 | B29: =Produtos!C29 -> #N/A | C29: =Produtos!B29 -> #N/A | D29: =Produtos!D29 -> 0 | E29: PEÇAS | F29: =Produtos!P29 -> 0 | G29: =Produtos!D29*Produtos!E29 -> 0
A30: =Produtos!A30 -> 0 | B30: =Produtos!C30 -> #N/A | C30: =Produtos!B30 -> #N/A | D30: =Produtos!D30 -> 0 | E30: PEÇAS | F30: =Produtos!P30 -> 0 | G30: =Produtos!D30*Produtos!E30 -> 0
A31: =Produtos!A31 -> 0 | B31: =Produtos!C31 -> #N/A | C31: =Produtos!B31 -> #N/A | D31: =Produtos!D31 -> 0 | E31: PEÇAS | F31: =Produtos!P31 -> 0 | G31: =Produtos!D31*Produtos!E31 -> 0
... A42: =Produtos!A42 -> 0 | B42: =Produtos!C42 -> #N/A | C42: =Produtos!B42 -> #N/A | D42: =Produtos!D42 -> 0 | E42: PEÇAS | F42: =Produtos!P42 -> 0 | G42: =Produtos!D42*Produtos!E42 -> 0
